Workbook
Name SegmentaciónDeDatos_STATUS_FINAL: #N/A

Sheet Hoja2

Sheet PLANEAMIENTO
L2: CILINDRO | U2: VASTAGO | AD2: TAPA | AG2: PISTON | AJ2: FIN | AL2: TAPA CI | AO2: CUERPO INT.
L3: ESTANDAR | P3: FABRICACION | U3: ESTANDAR | X3: FABRICACION | AD3: ESTANDAR | AF3: N | AG3: ESTANDAR | AI3: N | AL3: ESTANDAR | AO3: ESTANDAR
A4: HP&K | B4: MINA | C4: DESCRIPCION | D4: MODELO | E4: FECHA ESTIMADA DE TERMINO DE REPARACION | F4: ESTIMADO | G4: Nombre | H4: Fecha de armado | I4: STATUS FINAL | J4: RQ | K4: FECHA | L4: Relleno | M4: Barrenado | N4: Bruñido | O4: Soldadura (Dados) | P4: Corte | Q4: Encastre | R4: Diam Salida. | S4: Soldadura | T4: Bocinas / Dados | U4: Relleno2 | V4: Barrenado3 | W4: Cromado | X4: Corte4 | Y4: Encastre5 | Z4: Espiga | AA4: Soldadura2 | AB4: Maquinar soldadura | AC4: Bocinas2 | AD4: Pulido | AE4: Rectificado | AF4: Fabricacion | AG4: Pulido2 | AH4: Rectificado2 | AI4: Fabricación | AJ4: ARMADO | AK4: PINTURA | AL4: Pulido3 / Releno | AM4: Rectificado3 / Barrenado | AN4: Fabricacion2 | AO4: Bruñido2 | AP4: Cromado4 | AQ4: Bruñido3 | AR4: Cromado2 | AS4: Cromado3 | AT4: AVANCE | AU4: FECHA ESTIMADA DE TERMINO DE REPARACION2
A5: 254824 | B5: UNIMAQ | C5: CILINDRO DE GATA ESTABILIZADORA | D5: 1219 | I5: LISTO PARA DESPACHO | AT5: =IFERROR((COUNTIF(Tabla1[[#This Row],[Relleno]:[Cromado3]],"OK")*1+COUNTIF(Tabla1[[#This Row],[Relleno]:[Cromado3]],"PR")*0.5+COUNTIF(Tabla1[[#This Row],[Relleno]:[Cromado3]],"TS")*0.05)/(COUNTIF(Tabla1[[#This Row],[Relleno]:[Cromado3]],"OK")+COUNTIF(Tabla1[[#This Row],[Relleno]:[Cromado3]],"PR")+COUNTIF(Tabla1[[#This Row],[Relleno]:[Cromado3]],"TS")+COUNTIF(Tabla1[[#This Row],[Relleno]:[Cromado3]],"X")),0) -> 0
A6: 254924 | B6: UNIMAQ | C6: CILINDRO DE GATA ESTABILIZADORA | D6: 1219 | I6: LISTO PARA DESPACHO | AT6: =IFERROR((COUNTIF(Tabla1[[#This Row],[Relleno]:[Cromado3]],"OK")*1+COUNTIF(Tabla1[[#This Row],[Relleno]:[Cromado3]],"PR")*0.5+COUNTIF(Tabla1[[#This Row],[Relleno]:[Cromado3]],"TS")*0.05)/(COUNTIF(Tabla1[[#This Row],[Relleno]:[Cromado3]],"OK")+COUNTIF(Tabla1[[#This Row],[Relleno]:[Cromado3]],"PR")+COUNTIF(Tabla1[[#This Row],[Relleno]:[Cromado3]],"TS")+COUNTIF(Tabla1[[#This Row],[Relleno]:[Cromado3]],"X")),0) -> 0
A7: 255024 | B7: UNIMAQ | C7: CILINDRO DE GATA ESTABILIZADORA | D7: 1219 | I7: LISTO PARA DESPACHO | AT7: =IFERROR((COUNTIF(Tabla1[[#This Row],[Relleno]:[Cromado3]],"OK")*1+COUNTIF(Tabla1[[#This Row],[Relleno]:[Cromado3]],"PR")*0.5+COUNTIF(Tabla1[[#This Row],[Relleno]:[Cromado3]],"TS")*0.05)/(COUNTIF(Tabla1[[#This Row],[Relleno]:[Cromado3]],"OK")+COUNTIF(Tabla1[[#This Row],[Relleno]:[Cromado3]],"PR")+COUNTIF(Tabla1[[#This Row],[Relleno]:[Cromado3]],"TS")+COUNTIF(Tabla1[[#This Row],[Relleno]:[Cromado3]],"X")),0) -> 0
A8: 255124 | B8: UNIMAQ | C8: CILINDRO DE GATA ESTABILIZADORA | D8: 1219 | I8: LISTO PARA DESPACHO | AT8: =IFERROR((COUNTIF(Tabla1[[#This Row],[Relleno]:[Cromado3]],"OK")*1+COUNTIF(Tabla1[[#This Row],[Relleno]:[Cromado3]],"PR")*0.5+COUNTIF(Tabla1[[#This Row],[Relleno]:[Cromado3]],"TS")*0.05)/(COUNTIF(Tabla1[[#This Row],[Relleno]:[Cromado3]],"OK")+COUNTIF(Tabla1[[#This Row],[Relleno]:[Cromado3]],"PR")+COUNTIF(Tabla1[[#This Row],[Relleno]:[Cromado3]],"TS")+COUNTIF(Tabla1[[#This Row],[Relleno]:[Cromado3]],"X")),0) -> 0
A9: 255824 | B9: PERU RAIL | C9: CIGÜEÑAL DE LOCOMOTARA | D9: DL-535 | I9: LISTO PARA DESPACHO | AT9: =IFERROR((COUNTIF(Tabla1[[#This Row],[Relleno]:[Cromado3]],"OK")*1+COUNTIF(Tabla1[[#This Row],[Relleno]:[Cromado3]],"PR")*0.5+COUNTIF(Tabla1[[#This Row],[Relleno]:[Cromado3]],"TS")*0.05)/(COUNTIF(Tabla1[[#This Row],[Relleno]:[Cromado3]],"OK")+COUNTIF(Tabla1[[#This Row],[Relleno]:[Cromado3]],"PR")+COUNTIF(Tabla1[[#This Row],[Relleno]:[Cromado3]],"TS")+COUNTIF(Tabla1[[#This Row],[Relleno]:[Cromado3]],"X")),0) -> 0
A10: 261224 | B10: UNIMAQ | C10: CILINDRO DE HYD | D10: 1221 | I10: FUERA DE PROGRAMA | AT10: =IFERROR((COUNTIF(Tabla1[[#This Row],[Relleno]:[Cromado3]],"OK")*1+COUNTIF(Tabla1[[#This Row],[Relleno]:[Cromado3]],"PR")*0.5+COUNTIF(Tabla1[[#This Row],[Relleno]:[Cromado3]],"TS")*0.05)/(COUNTIF(Tabla1[[#This Row],[Relleno]:[Cromado3]],"OK")+COUNTIF(Tabla1[[#This Row],[Relleno]:[Cromado3]],"PR")+COUNTIF(Tabla1[[#This Row],[Relleno]:[Cromado3]],"TS")+COUNTIF(Tabla1[[#This Row],[Relleno]:[Cromado3]],"X")),0) -> 0
A11: 261324 | B11: UNIMAQ | C11: CILINDRO DE HYD | D11: 1220 | I11: FUERA DE PROGRAMA | AT11: =IFERROR((COUNTIF(Tabla1[[#This Row],[Relleno]:[Cromado3]],"OK")*1+COUNTIF(Tabla1[[#This Row],[Relleno]:[Cromado3]],"PR")*0.5+COUNTIF(Tabla1[[#This Row],[Relleno]:[Cromado3]],"TS")*0.05)/(COUNTIF(Tabla1[[#This Row],[Relleno]:[Cromado3]],"OK")+COUNTIF(Tabla1[[#This Row],[Relleno]:[Cromado3]],"PR")+COUNTIF(Tabla1[[#This Row],[Relleno]:[Cromado3]],"TS")+COUNTIF(Tabla1[[#This Row],[Relleno]:[Cromado3]],"X")),0) -> 0
A12: 261424 | B12: UNIMAQ | C12: CILINDRO DE HYD | D12: 1220 | I12: FUERA DE PROGRAMA | AT12: =IFERROR((COUNTIF(Tabla1[[#This Row],[Relleno]:[Cromado3]],"OK")*1+COUNTIF(Tabla1[[#This Row],[Relleno]:[Cromado3]],"PR")*0.5+COUNTIF(Tabla1[[#This Row],[Relleno]:[Cromado3]],"TS")*0.05)/(COUNTIF(Tabla1[[#This Row],[Relleno]:[Cromado3]],"OK")+COUNTIF(Tabla1[[#This Row],[Relleno]:[Cromado3]],"PR")+COUNTIF(Tabla1[[#This Row],[Relleno]:[Cromado3]],"TS")+COUNTIF(Tabla1[[#This Row],[Relleno]:[Cromado3]],"X")),0) -> 0
A13: 266824 | B13: UNIMAQ | C13: CILINDRO DE LEVANTE | D13: 1150 | I13: FUERA DE PROGRAMA | AT13: =IFERROR((COUNTIF(Tabla1[[#This Row],[Relleno]:[Cromado3]],"OK")*1+COUNTIF(Tabla1[[#This Row],[Relleno]:[Cromado3]],"PR")*0.5+COUNTIF(Tabla1[[#This Row],[Relleno]:[Cromado3]],"TS")*0.05)/(COUNTIF(Tabla1[[#This Row],[Relleno]:[Cromado3]],"OK")+COUNTIF(Tabla1[[#This Row],[Relleno]:[Cromado3]],"PR")+COUNTIF(Tabla1[[#This Row],[Relleno]:[Cromado3]],"TS")+COUNTIF(Tabla1[[#This Row],[Relleno]:[Cromado3]],"X")),0) -> 0
A14: 273924 | B14: ANTAPACCAY | C14: CILINDRO DE SUSPENSION POSTERIOR | D14: 797F | I14: LISTO PARA DESPACHO | P14: OK | Q14: OK | S14: OK | U14: OK | V14: OK | W14: OK | AF14: OK | AG14: OK | AH14: OK | AJ14: OK | AK14: OK | AT14: =IFERROR((COUNTIF(Tabla1[[#This Row],[Relleno]:[Cromado3]],"OK")*1+COUNTIF(Tabla1[[#This Row],[Relleno]:[Cromado3]],"PR")*0.5+COUNTIF(Tabla1[[#This Row],[Relleno]:[Cromado3]],"TS")*0.05)/(COUNTIF(Tabla1[[#This Row],[Relleno]:[Cromado3]],"OK")+COUNTIF(Tabla1[[#This Row],[Relleno]:[Cromado3]],"PR")+COUNTIF(Tabla1[[#This Row],[Relleno]:[Cromado3]],"TS")+COUNTIF(Tabla1[[#This Row],[Relleno]:[Cromado3]],"X")),0) -> 1
A15: 275424 | B15: BAMBAS | C15: CILINDRO DE LEVANTE DE TOLVA | D15: 930E-4SE | F15: 4400570845 | I15: ENTREGADO | AT15: =IFERROR((COUNTIF(Tabla1[[#This Row],[Relleno]:[Cromado3]],"OK")*1+COUNTIF(Tabla1[[#This Row],[Relleno]:[Cromado3]],"PR")*0.5+COUNTIF(Tabla1[[#This Row],[Relleno]:[Cromado3]],"TS")*0.05)/(COUNTIF(Tabla1[[#This Row],[Relleno]:[Cromado3]],"OK")+COUNTIF(Tabla1[[#This Row],[Relleno]:[Cromado3]],"PR")+COUNTIF(Tabla1[[#This Row],[Relleno]:[Cromado3]],"TS")+COUNTIF(Tabla1[[#This Row],[Relleno]:[Cromado3]],"X")),0) -> 0
A16: 279224 | B16: UNIMAQ | C16: CILINDRO HIDRAULICO DE MANIPULADOR | D16: GENERICO | I16: FUERA DE PROGRAMA | T16: X | W16: X | AC16: X | AD16: OK | AJ16: X | AK16: X | AT16: =IFERROR((COUNTIF(Tabla1[[#This Row],[Relleno]:[Cromado3]],"OK")*1+COUNTIF(Tabla1[[#This Row],[Relleno]:[Cromado3]],"PR")*0.5+COUNTIF(Tabla1[[#This Row],[Relleno]:[Cromado3]],"TS")*0.05)/(COUNTIF(Tabla1[[#This Row],[Relleno]:[Cromado3]],"OK")+COUNTIF(Tabla1[[#This Row],[Relleno]:[Cromado3]],"PR")+COUNTIF(Tabla1[[#This Row],[Relleno]:[Cromado3]],"TS")+COUNTIF(Tabla1[[#This Row],[Relleno]:[Cromado3]],"X")),0) -> 0.16666667
A17: 279624 | B17: ANTAPACCAY | C17: CILINDRO DE SUSPENSION POSTERIOR | D17: 797F | F17: 4500512788 | I17: LISTO PARA DESPACHO | P17: OK | Q17: OK | S17: OK | U17: OK | V17: OK | W17: OK | AD17: TS | AG17: OK | AJ17: OK | AK17: OK | AT17: =IFERROR((COUNTIF(Tabla1[[#This Row],[Relleno]:[Cromado3]],"OK")*1+COUNTIF(Tabla1[[#This Row],[Relleno]:[Cromado3]],"PR")*0.5+COUNTIF(Tabla1[[#This Row],[Relleno]:[Cromado3]],"TS")*0.05)/(COUNTIF(Tabla1[[#This Row],[Relleno]:[Cromado3]],"OK")+COUNTIF(Tabla1[[#This Row],[Relleno]:[Cromado3]],"PR")+COUNTIF(Tabla1[[#This Row],[Relleno]:[Cromado3]],"TS")+COUNTIF(Tabla1[[#This Row],[Relleno]:[Cromado3]],"X")),0) -> 0.905
A18: 281024 | B18: ANTAPACCAY | C18: CILINDRO HIDRAULICO DE CLAM | D18: 6060FS | F18: 4500514311 | I18: LISTO PARA DESPACHO | N18: OK | O18: OK | P18: OK | Q18: OK | R18: OK | S18: OK | W18: OK | AD18: X | AG18: X | AJ18: X | AK18: X | AT18: =IFERROR((COUNTIF(Tabla1[[#This Row],[Relleno]:[Cromado3]],"OK")*1+COUNTIF(Tabla1[[#This Row],[Relleno]:[Cromado3]],"PR")*0.5+COUNTIF(Tabla1[[#This Row],[Relleno]:[Cromado3]],"TS")*0.05)/(COUNTIF(Tabla1[[#This Row],[Relleno]:[Cromado3]],"OK")+COUNTIF(Tabla1[[#This Row],[Relleno]:[Cromado3]],"PR")+COUNTIF(Tabla1[[#This Row],[Relleno]:[Cromado3]],"TS")+COUNTIF(Tabla1[[#This Row],[Relleno]:[Cromado3]],"X")),0) -> 0.63636364
A19: 281224 | B19: ANTAPACCAY | C19: CILINDRO DE LEVANTE | D19: 988K | F19: 4500515962 | I19: LISTO PARA DESPACHO | N19: OK | W19: OK | AD19: OK | AG19: OK | AJ19: OK | AK19: OK | AT19: =IFERROR((COUNTIF(Tabla1[[#This Row],[Relleno]:[Cromado3]],"OK")*1+COUNTIF(Tabla1[[#This Row],[Relleno]:[Cromado3]],"PR")*0.5+COUNTIF(Tabla1[[#This Row],[Relleno]:[Cromado3]],"TS")*0.05)/(COUNTIF(Tabla1[[#This Row],[Relleno]:[Cromado3]],"OK")+COUNTIF(Tabla1[[#This Row],[Relleno]:[Cromado3]],"PR")+COUNTIF(Tabla1[[#This Row],[Relleno]:[Cromado3]],"TS")+COUNTIF(Tabla1[[#This Row],[Relleno]:[Cromado3]],"X")),0) -> 1
A20: 282824 | B20: BAMBAS | C20: FRENO DELANTERO | D20: 24 | F20: 4400579125 | I20: ENTREGADO | AJ20: OK | AK20: OK | AT20: =IFERROR((COUNTIF(Tabla1[[#This Row],[Relleno]:[Cromado3]],"OK")*1+COUNTIF(Tabla1[[#This Row],[Relleno]:[Cromado3]],"PR")*0.5+COUNTIF(Tabla1[[#This Row],[Relleno]:[Cromado3]],"TS")*0.05)/(COUNTIF(Tabla1[[#This Row],[Relleno]:[Cromado3]],"OK")+COUNTIF(Tabla1[[#This Row],[Relleno]:[Cromado3]],"PR")+COUNTIF(Tabla1[[#This Row],[Relleno]:[Cromado3]],"TS")+COUNTIF(Tabla1[[#This Row],[Relleno]:[Cromado3]],"X")),0) -> 1
A21: 282924 | B21: BAMBAS | C21: FRENO DELANTERO | D21: 24 | F21: 4400579126 | I21: ENTREGADO | AJ21: OK | AK21: OK | AT21: =IFERROR((COUNTIF(Tabla1[[#This Row],[Relleno]:[Cromado3]],"OK")*1+COUNTIF(Tabla1[[#This Row],[Relleno]:[Cromado3]],"PR")*0.5+COUNTIF(Tabla1[[#This Row],[Relleno]:[Cromado3]],"TS")*0.05)/(COUNTIF(Tabla1[[#This Row],[Relleno]:[Cromado3]],"OK")+COUNTIF(Tabla1[[#This Row],[Relleno]:[Cromado3]],"PR")+COUNTIF(Tabla1[[#This Row],[Relleno]:[Cromado3]],"TS")+COUNTIF(Tabla1[[#This Row],[Relleno]:[Cromado3]],"X")),0) -> 1
A22: 283724 | B22: ANTAPACCAY | C22: CILINDRO DE LEVANTE DE BULLDOZER | D22: D11T | F22: 4500518233 | I22: ENTREGADO | N22: OK | U22: OK | V22: OK | W22: OK | AD22: OK | AG22: OK | AJ22: OK | AK22: OK | AT22: =IFERROR((COUNTIF(Tabla1[[#This Row],[Relleno]:[Cromado3]],"OK")*1+COUNTIF(Tabla1[[#This Row],[Relleno]:[Cromado3]],"PR")*0.5+COUNTIF(Tabla1[[#This Row],[Relleno]:[Cromado3]],"TS")*0.05)/(COUNTIF(Tabla1[[#This Row],[Relleno]:[Cromado3]],"OK")+COUNTIF(Tabla1[[#This Row],[Relleno]:[Cromado3]],"PR")+COUNTIF(Tabla1[[#This Row],[Relleno]:[Cromado3]],"TS")+COUNTIF(Tabla1[[#This Row],[Relleno]:[Cromado3]],"X")),0) -> 1
A23: 284024 | B23: BAMBAS | C23: CILINDRO DE STICK | D23: 390DL | F23: 4400580039 | I23: ENTREGADO | L23: OK | M23: OK | N23: OK | U23: OK | V23: OK | X23: OK | Y23: OK | Z23: OK | AA23: OK | AD23: OK | AG23: OK | AJ23: OK | AK23: OK | AT23: =IFERROR((COUNTIF(Tabla1[[#This Row],[Relleno]:[Cromado3]],"OK")*1+COUNTIF(Tabla1[[#This Row],[Relleno]:[Cromado3]],"PR")*0.5+COUNTIF(Tabla1[[#This Row],[Relleno]:[Cromado3]],"TS")*0.05)/(COUNTIF(Tabla1[[#This Row],[Relleno]:[Cromado3]],"OK")+COUNTIF(Tabla1[[#This Row],[Relleno]:[Cromado3]],"PR")+COUNTIF(Tabla1[[#This Row],[Relleno]:[Cromado3]],"TS")+COUNTIF(Tabla1[[#This Row],[Relleno]:[Cromado3]],"X")),0) -> 1
A24: 284124 | B24: BAMBAS | C24: CILINDRO DE INCLINACION DE BULLDOZER | D24: D475 | F24: 4400580037 | I24: ENTREGADO | L24: OK | M24: OK | P24: OK | Q24: OK | S24: OK | T24: OK | U24: OK | V24: OK | W24: OK | AD24: OK | AE24: OK | AG24: OK | AJ24: OK | AK24: OK | AT24: =IFERROR((COUNTIF(Tabla1[[#This Row],[Relleno]:[Cromado3]],"OK")*1+COUNTIF(Tabla1[[#This Row],[Relleno]:[Cromado3]],"PR")*0.5+COUNTIF(Tabla1[[#This Row],[Relleno]:[Cromado3]],"TS")*0.05)/(COUNTIF(Tabla1[[#This Row],[Relleno]:[Cromado3]],"OK")+COUNTIF(Tabla1[[#This Row],[Relleno]:[Cromado3]],"PR")+COUNTIF(Tabla1[[#This Row],[Relleno]:[Cromado3]],"TS")+COUNTIF(Tabla1[[#This Row],[Relleno]:[Cromado3]],"X")),0) -> 1
A25: 284224 | B25: BAMBAS | C25: CILINDRO DE DIRECCION | D25: 930E-4SE | F25: 4400580038 | I25: ENTREGADO | AT25: =IFERROR((COUNTIF(Tabla1[[#This Row],[Relleno]:[Cromado3]],"OK")*1+COUNTIF(Tabla1[[#This Row],[Relleno]:[Cromado3]],"PR")*0.5+COUNTIF(Tabla1[[#This Row],[Relleno]:[Cromado3]],"TS")*0.05)/(COUNTIF(Tabla1[[#This Row],[Relleno]:[Cromado3]],"OK")+COUNTIF(Tabla1[[#This Row],[Relleno]:[Cromado3]],"PR")+COUNTIF(Tabla1[[#This Row],[Relleno]:[Cromado3]],"TS")+COUNTIF(Tabla1[[#This Row],[Relleno]:[Cromado3]],"X")),0) -> 0
A26: 284524 | B26: BAMBAS | C26: CILINDRO DE INCLINACION DE BULLDOZER | D26: 844H | F26: 4400580457 | I26: ENTREGADO | L26: OK | M26: OK | N26: OK | O26: OK | U26: OK | V26: OK | W26: OK | AD26: OK | AE26: OK | AG26: OK | AJ26: OK | AK26: OK | AT26: =IFERROR((COUNTIF(Tabla1[[#This Row],[Relleno]:[Cromado3]],"OK")*1+COUNTIF(Tabla1[[#This Row],[Relleno]:[Cromado3]],"PR")*0.5+COUNTIF(Tabla1[[#This Row],[Relleno]:[Cromado3]],"TS")*0.05)/(COUNTIF(Tabla1[[#This Row],[Relleno]:[Cromado3]],"OK")+COUNTIF(Tabla1[[#This Row],[Relleno]:[Cromado3]],"PR")+COUNTIF(Tabla1[[#This Row],[Relleno]:[Cromado3]],"TS")+COUNTIF(Tabla1[[#This Row],[Relleno]:[Cromado3]],"X")),0) -> 1
A27: 284624 | B27: BAMBAS | C27: CILINDRO DE LEVANTE DE BULLDOZER | D27: D475 | F27: 4400580466 | I27: ENTREGADO | AT27: =IFERROR((COUNTIF(Tabla1[[#This Row],[Relleno]:[Cromado3]],"OK")*1+COUNTIF(Tabla1[[#This Row],[Relleno]:[Cromado3]],"PR")*0.5+COUNTIF(Tabla1[[#This Row],[Relleno]:[Cromado3]],"TS")*0.05)/(COUNTIF(Tabla1[[#This Row],[Relleno]:[Cromado3]],"OK")+COUNTIF(Tabla1[[#This Row],[Relleno]:[Cromado3]],"PR")+COUNTIF(Tabla1[[#This Row],[Relleno]:[Cromado3]],"TS")+COUNTIF(Tabla1[[#This Row],[Relleno]:[Cromado3]],"X")),0) -> 0
A28: 284724 | B28: BAMBAS | C28: CILINDRO DE LEVANTE DE BULLDOZER | D28: D475 | F28: 4400580467 | I28: ENTREGADO | N28: OK | P28: OK | Q28: OK | S28: OK | T28: OK | U28: OK | V28: OK | X28: OK | Y28: OK | Z28: OK | AA28: OK | AD28: OK | AG28: OK | AJ28: OK | AK28: OK | AS28: ESTA ARMADO EL V´STAGO CON TAPA Y PSITON + SELLOS | AT28: =IFERROR((COUNTIF(Tabla1[[#This Row],[Relleno]:[Cromado3]],"OK")*1+COUNTIF(Tabla1[[#This Row],[Relleno]:[Cromado3]],"PR")*0.5+COUNTIF(Tabla1[[#This Row],[Relleno]:[Cromado3]],"TS")*0.05)/(COUNTIF(Tabla1[[#This Row],[Relleno]:[Cromado3]],"OK")+COUNTIF(Tabla1[[#This Row],[Relleno]:[Cromado3]],"PR")+COUNTIF(Tabla1[[#This Row],[Relleno]:[Cromado3]],"TS")+COUNTIF(Tabla1[[#This Row],[Relleno]:[Cromado3]],"X")),0) -> 1
A29: 285124 | B29: ANTAPACCAY | C29: CILINDRO DE LEVANTE DE RIPPER | D29: D11 | F29: 4500519627 | I29: ENTREGADO | AT29: =IFERROR((COUNTIF(Tabla1[[#This Row],[Relleno]:[Cromado3]],"OK")*1+COUNTIF(Tabla1[[#This Row],[Relleno]:[Cromado3]],"PR")*0.5+COUNTIF(Tabla1[[#This Row],[Relleno]:[Cromado3]],"TS")*0.05)/(COUNTIF(Tabla1[[#This Row],[Relleno]:[Cromado3]],"OK")+COUNTIF(Tabla1[[#This Row],[Relleno]:[Cromado3]],"PR")+COUNTIF(Tabla1[[#This Row],[Relleno]:[Cromado3]],"TS")+COUNTIF(Tabla1[[#This Row],[Relleno]:[Cromado3]],"X")),0) -> 0
A30: 285224 | B30: ANTAPACCAY | C30: CILINDRO DE INCLINACION DE BULLDOZER | D30: D11T | F30: 4500519625 | I30: ENTREGADO | L30: OK | M30: OK | N30: OK | O30: OK | P30: OK | Q30: OK | S30: OK | U30: OK | V30: OK | W30: OK | AD30: OK | AG30: OK | AJ30: OK | AK30: X | AT30: =IFERROR((COUNTIF(Tabla1[[#This Row],[Relleno]:[Cromado3]],"OK")*1+COUNTIF(Tabla1[[#This Row],[Relleno]:[Cromado3]],"PR")*0.5+COUNTIF(Tabla1[[#This Row],[Relleno]:[Cromado3]],"TS")*0.05)/(COUNTIF(Tabla1[[#This Row],[Relleno]:[Cromado3]],"OK")+COUNTIF(Tabla1[[#This Row],[Relleno]:[Cromado3]],"PR")+COUNTIF(Tabla1[[#This Row],[Relleno]:[Cromado3]],"TS")+COUNTIF(Tabla1[[#This Row],[Relleno]:[Cromado3]],"X")),0) -> 0.92857143
A31: 285324 | B31: ANTAPACCAY | C31: CILINDRO DE DIRECCION | D31: 24 | F31: 4500519626 | I31: LISTO PARA DESPACHO | L31: OK | M31: OK | N31: OK | O31: OK | P31: OK | Q31: OK | S31: OK | U31: OK | V31: OK | X31: OK | Y31: OK | Z31: OK | AA31: OK | AC31: ESPERA DE BARRA CROMADA | AD31: OK | AG31: OK | AJ31: PR | AK31: X | AT31: =IFERROR((COUNTIF(Tabla1[[#This Row],[Relleno]:[Cromado3]],"OK")*1+COUNTIF(Tabla1[[#This Row],[Relleno]:[Cromado3]],"PR")*0.5+COUNTIF(Tabla1[[#This Row],[Relleno]:[Cromado3]],"TS")*0.05)/(COUNTIF(Tabla1[[#This Row],[Relleno]:[Cromado3]],"OK")+COUNTIF(Tabla1[[#This Row],[Relleno]:[Cromado3]],"PR")+COUNTIF(Tabla1[[#This Row],[Relleno]:[Cromado3]],"TS")+COUNTIF(Tabla1[[#This Row],[Relleno]:[Cromado3]],"X")),0) -> 0.91176471
A32: 285524 | B32: ANTAPACCAY | C32: CILINDRO DE DIRECCION | D32: HD1500 | F32: 4500520946 | I32: LISTO PARA DESPACHO | L32: OK | M32: OK | N32: OK | P32: OK | Q32: OK | S32: OK | U32: OK | V32: OK | W32: OK | AD32: OK | AG32: OK | AJ32: OK | AK32: TS | AT32: =IFERROR((COUNTIF(Tabla1[[#This Row],[Relleno]:[Cromado3]],"OK")*1+COUNTIF(Tabla1[[#This Row],[Relleno]:[Cromado3]],"PR")*0.5+COUNTIF(Tabla1[[#This Row],[Relleno]:[Cromado3]],"TS")*0.05)/(COUNTIF(Tabla1[[#This Row],[Relleno]:[Cromado3]],"OK")+COUNTIF(Tabla1[[#This Row],[Relleno]:[Cromado3]],"PR")+COUNTIF(Tabla1[[#This Row],[Relleno]:[Cromado3]],"TS")+COUNTIF(Tabla1[[#This Row],[Relleno]:[Cromado3]],"X")),0) -> 0.92692308
A33: 285724 | B33: ANTAPACCAY | C33: CILINDRO DE LEVANTE | D33: 994F | E33: 21 | F33: 4500520964 | I33: ENTREGADO | N33: OK | P33: OK | Q33: OK | S33: OK | U33: OK | V33: OK | W33: OK | AD33: OK | AG33: OK | AJ33: TS | AK33: X | AT33: =IFERROR((COUNTIF(Tabla1[[#This Row],[Relleno]:[Cromado3]],"OK")*1+COUNTIF(Tabla1[[#This Row],[Relleno]:[Cromado3]],"PR")*0.5+COUNTIF(Tabla1[[#This Row],[Relleno]:[Cromado3]],"TS")*0.05)/(COUNTIF(Tabla1[[#This Row],[Relleno]:[Cromado3]],"OK")+COUNTIF(Tabla1[[#This Row],[Relleno]:[Cromado3]],"PR")+COUNTIF(Tabla1[[#This Row],[Relleno]:[Cromado3]],"TS")+COUNTIF(Tabla1[[#This Row],[Relleno]:[Cromado3]],"X")),0) -> 0.82272727
A34: 286024 | B34: ANTAPACCAY | C34: CILINDRO DE DIRECCION | D34: 930E-4SE | F34: 4500522025 | I34: LISTO PARA DESPACHO | L34: OK | M34: OK | N34: OK | X34: OK | Y34: OK | Z34: OK | AA34: OK | AD34: OK | AI34: OK | AJ34: OK | AK34: X | AT34: =IFERROR((COUNTIF(Tabla1[[#This Row],[Relleno]:[Cromado3]],"OK")*1+COUNTIF(Tabla1[[#This Row],[Relleno]:[Cromado3]],"PR")*0.5+COUNTIF(Tabla1[[#This Row],[Relleno]:[Cromado3]],"TS")*0.05)/(COUNTIF(Tabla1[[#This Row],[Relleno]:[Cromado3]],"OK")+COUNTIF(Tabla1[[#This Row],[Relleno]:[Cromado3]],"PR")+COUNTIF(Tabla1[[#This Row],[Relleno]:[Cromado3]],"TS")+COUNTIF(Tabla1[[#This Row],[Relleno]:[Cromado3]],"X")),0) -> 0.90909091
A35: 286624 | B35: BAMBAS | C35: CILINDRO DE INCLINACION DE BULLDOZER | D35: D11T | F35: 4400583123 | I35: ENTREGADO | L35: OK | M35: OK | P35: OK | Q35: OK | S35: OK | U35: OK | V35: OK | W35: OK | AD35: OK | AE35: CAMBIO DE TAPA CON LA 285224 | AG35: OK | AH35: CAMBIO DE PISTON CON LA 285224 | AJ35: OK | AK35: OK | AT35: =IFERROR((COUNTIF(Tabla1[[#This Row],[Relleno]:[Cromado3]],"OK")*1+COUNTIF(Tabla1[[#This Row],[Relleno]:[Cromado3]],"PR")*0.5+COUNTIF(Tabla1[[#This Row],[Relleno]:[Cromado3]],"TS")*0.05)/(COUNTIF(Tabla1[[#This Row],[Relleno]:[Cromado3]],"OK")+COUNTIF(Tabla1[[#This Row],[Relleno]:[Cromado3]],"PR")+COUNTIF(Tabla1[[#This Row],[Relleno]:[Cromado3]],"TS")+COUNTIF(Tabla1[[#This Row],[Relleno]:[Cromado3]],"X")),0) -> 1
A36: 286724 | B36: ANTAPACCAY | C36: ACUMULADOR DE DIRECCION | D36: 797F | F36: 4500524867 | I36: ENTREGADO | AT36: =IFERROR((COUNTIF(Tabla1[[#This Row],[Relleno]:[Cromado3]],"OK")*1+COUNTIF(Tabla1[[#This Row],[Relleno]:[Cromado3]],"PR")*0.5+COUNTIF(Tabla1[[#This Row],[Relleno]:[Cromado3]],"TS")*0.05)/(COUNTIF(Tabla1[[#This Row],[Relleno]:[Cromado3]],"OK")+COUNTIF(Tabla1[[#This Row],[Relleno]:[Cromado3]],"PR")+COUNTIF(Tabla1[[#This Row],[Relleno]:[Cromado3]],"TS")+COUNTIF(Tabla1[[#This Row],[Relleno]:[Cromado3]],"X")),0) -> 0
A37: 286824 | B37: ANTAPACCAY | C37: ACUMULADOR DE DIRECCION | D37: 797F | F37: 4500524408 | I37: ENTREGADO | AT37: =IFERROR((COUNTIF(Tabla1[[#This Row],[Relleno]:[Cromado3]],"OK")*1+COUNTIF(Tabla1[[#This Row],[Relleno]:[Cromado3]],"PR")*0.5+COUNTIF(Tabla1[[#This Row],[Relleno]:[Cromado3]],"TS")*0.05)/(COUNTIF(Tabla1[[#This Row],[Relleno]:[Cromado3]],"OK")+COUNTIF(Tabla1[[#This Row],[Relleno]:[Cromado3]],"PR")+COUNTIF(Tabla1[[#This Row],[Relleno]:[Cromado3]],"TS")+COUNTIF(Tabla1[[#This Row],[Relleno]:[Cromado3]],"X")),0) -> 0
A38: 286924 | B38: ANTAPACCAY | C38: ACUMULADOR DE DIRECCION | D38: 797F | F38: 4500524410 | I38: ENTREGADO | AT38: =IFERROR((COUNTIF(Tabla1[[#This Row],[Relleno]:[Cromado3]],"OK")*1+COUNTIF(Tabla1[[#This Row],[Relleno]:[Cromado3]],"PR")*0.5+COUNTIF(Tabla1[[#This Row],[Relleno]:[Cromado3]],"TS")*0.05)/(COUNTIF(Tabla1[[#This Row],[Relleno]:[Cromado3]],"OK")+COUNTIF(Tabla1[[#This Row],[Relleno]:[Cromado3]],"PR")+COUNTIF(Tabla1[[#This Row],[Relleno]:[Cromado3]],"TS")+COUNTIF(Tabla1[[#This Row],[Relleno]:[Cromado3]],"X")),0) -> 0
A39: 287024 | B39: ANTAPACCAY | C39: CILINDRO DE LEVANTE DE BULLDOZER | D39: D475 | F39: 4500524754 | I39: LISTO PARA DESPACHO | N39: OK | P39: OK | Q39: OK | T39: OK | X39: OK | Y39: OK | Z39: OK | AA39: OK | AC39: OK | AD39: OK | AG39: OK | AJ39: OK | AT39: =IFERROR((COUNTIF(Tabla1[[#This Row],[Relleno]:[Cromado3]],"OK")*1+COUNTIF(Tabla1[[#This Row],[Relleno]:[Cromado3]],"PR")*0.5+COUNTIF(Tabla1[[#This Row],[Relleno]:[Cromado3]],"TS")*0.05)/(COUNTIF(Tabla1[[#This Row],[Relleno]:[Cromado3]],"OK")+COUNTIF(Tabla1[[#This Row],[Relleno]:[Cromado3]],"PR")+COUNTIF(Tabla1[[#This Row],[Relleno]:[Cromado3]],"TS")+COUNTIF(Tabla1[[#This Row],[Relleno]:[Cromado3]],"X")),0) -> 1
A40: 287124 | B40: ANTAPACCAY | C40: CILINDRO DE INCLINACION DE RIPPER | D40: D11T | F40: 4500525793 | I40: ENTREGADO | L40: OK | M40: OK | N40: OK | U40: OK | V40: OK | W40: OK | AD40: OK | AE40: OK | AG40: OK | AJ40: OK | AK40: TS | AT40: =IFERROR((COUNTIF(Tabla1[[#This Row],[Relleno]:[Cromado3]],"OK")*1+COUNTIF(Tabla1[[#This Row],[Relleno]:[Cromado3]],"PR")*0.5+COUNTIF(Tabla1[[#This Row],[Relleno]:[Cromado3]],"TS")*0.05)/(COUNTIF(Tabla1[[#This Row],[Relleno]:[Cromado3]],"OK")+COUNTIF(Tabla1[[#This Row],[Relleno]:[Cromado3]],"PR")+COUNTIF(Tabla1[[#This Row],[Relleno]:[Cromado3]],"TS")+COUNTIF(Tabla1[[#This Row],[Relleno]:[Cromado3]],"X")),0) -> 0.91363636
A41: 287224 | B41: ANTAPACCAY | C41: CILINDRO DE INCLINACION DE RIPPER | D41: D11T | F41: 4500525794 | I41: ENTREGADO | L41: OK | M41: OK | N41: OK | U41: OK | V41: OK | W41: OK | AD41: OK | AG41: OK | AJ41: OK | AK41: TS | AT41: =IFERROR((COUNTIF(Tabla1[[#This Row],[Relleno]:[Cromado3]],"OK")*1+COUNTIF(Tabla1[[#This Row],[Relleno]:[Cromado3]],"PR")*0.5+COUNTIF(Tabla1[[#This Row],[Relleno]:[Cromado3]],"TS")*0.05)/(COUNTIF(Tabla1[[#This Row],[Relleno]:[Cromado3]],"OK")+COUNTIF(Tabla1[[#This Row],[Relleno]:[Cromado3]],"PR")+COUNTIF(Tabla1[[#This Row],[Relleno]:[Cromado3]],"TS")+COUNTIF(Tabla1[[#This Row],[Relleno]:[Cromado3]],"X")),0) -> 0.905
A42: 287324 | B42: ANTAPACCAY | C42: CILINDRO DE DIRECCION | D42: 24 | F42: 4500525801 | I42: LISTO PARA DESPACHO | L42: OK | M42: OK | N42: OK | P42: OK | Q42: OK | S42: OK | W42: OK | AD42: OK | AG42: OK | AJ42: OK | AK42: OK | AT42: =IFERROR((COUNTIF(Tabla1[[#This Row],[Relleno]:[Cromado3]],"OK")*1+COUNTIF(Tabla1[[#This Row],[Relleno]:[Cromado3]],"PR")*0.5+COUNTIF(Tabla1[[#This Row],[Relleno]:[Cromado3]],"TS")*0.05)/(COUNTIF(Tabla1[[#This Row],[Relleno]:[Cromado3]],"OK")+COUNTIF(Tabla1[[#This Row],[Relleno]:[Cromado3]],"PR")+COUNTIF(Tabla1[[#This Row],[Relleno]:[Cromado3]],"TS")+COUNTIF(Tabla1[[#This Row],[Relleno]:[Cromado3]],"X")),0) -> 1
A43: 287424 | B43: BAMBAS | C43: CILINDRO DE SUSPENSION POSTERIOR | D43: 930E-4SE | F43: 4400583646 | I43: ENTREGADO | L43: OK | M43: OK | N43: OK | U43: OK | V43: OK | W43: OK | AD43: OK | AG43: OK | AJ43: OK | AK43: OK | AT43: =IFERROR((COUNTIF(Tabla1[[#This Row],[Relleno]:[Cromado3]],"OK")*1+COUNTIF(Tabla1[[#This Row],[Relleno]:[Cromado3]],"PR")*0.5+COUNTIF(Tabla1[[#This Row],[Relleno]:[Cromado3]],"TS")*0.05)/(COUNTIF(Tabla1[[#This Row],[Relleno]:[Cromado3]],"OK")+COUNTIF(Tabla1[[#This Row],[Relleno]:[Cromado3]],"PR")+COUNTIF(Tabla1[[#This Row],[Relleno]:[Cromado3]],"TS")+COUNTIF(Tabla1[[#This Row],[Relleno]:[Cromado3]],"X")),0) -> 1
A44: 287524 | B44: BAMBAS | C44: CILINDRO DE STICK | D44: 988K | F44: 4400584449 | I44: LISTO PARA DESPACHO | L44: OK | M44: OK | N44: OK | U44: OK | V44: OK | W44: OK | AD44: OK | AG44: OK | AJ44: OK | AT44: =IFERROR((COUNTIF(Tabla1[[#This Row],[Relleno]:[Cromado3]],"OK")*1+COUNTIF(Tabla1[[#This Row],[Relleno]:[Cromado3]],"PR")*0.5+COUNTIF(Tabla1[[#This Row],[Relleno]:[Cromado3]],"TS")*0.05)/(COUNTIF(Tabla1[[#This Row],[Relleno]:[Cromado3]],"OK")+COUNTIF(Tabla1[[#This Row],[Relleno]:[Cromado3]],"PR")+COUNTIF(Tabla1[[#This Row],[Relleno]:[Cromado3]],"TS")+COUNTIF(Tabla1[[#This Row],[Relleno]:[Cromado3]],"X")),0) -> 1
A45: 287624 | B45: BAMBAS | C45: CILINDRO DE BLADELIFT | D45: 24 | F45: 4400584447 | I45: LISTO PARA DESPACHO | N45: OK | W45: OK | AD45: OK | AG45: OK | AJ45: OK | AK45: OK | AT45: =IFERROR((COUNTIF(Tabla1[[#This Row],[Relleno]:[Cromado3]],"OK")*1+COUNTIF(Tabla1[[#This Row],[Relleno]:[Cromado3]],"PR")*0.5+COUNTIF(Tabla1[[#This Row],[Relleno]:[Cromado3]],"TS")*0.05)/(COUNTIF(Tabla1[[#This Row],[Relleno]:[Cromado3]],"OK")+COUNTIF(Tabla1[[#This Row],[Relleno]:[Cromado3]],"PR")+COUNTIF(Tabla1[[#This Row],[Relleno]:[Cromado3]],"TS")+COUNTIF(Tabla1[[#This Row],[Relleno]:[Cromado3]],"X")),0) -> 1
A46: 287724 | B46: BAMBAS | C46: CILINDRO DE JACK HYD | D46: PITVIPER 351 | F46: 4400584470 | I46: LISTO PARA DESPACHO | N46: OK | P46: OK | S46: OK | W46: OK | AD46: OK | AG46: OK | AJ46: OK | AK46: TS | AT46: =IFERROR((COUNTIF(Tabla1[[#This Row],[Relleno]:[Cromado3]],"OK")*1+COUNTIF(Tabla1[[#This Row],[Relleno]:[Cromado3]],"PR")*0.5+COUNTIF(Tabla1[[#This Row],[Relleno]:[Cromado3]],"TS")*0.05)/(COUNTIF(Tabla1[[#This Row],[Relleno]:[Cromado3]],"OK")+COUNTIF(Tabla1[[#This Row],[Relleno]:[Cromado3]],"PR")+COUNTIF(Tabla1[[#This Row],[Relleno]:[Cromado3]],"TS")+COUNTIF(Tabla1[[#This Row],[Relleno]:[Cromado3]],"X")),0) -> 0.88125
A47: 287824 | B47: BAMBAS | C47: CILINDRO DE JACK HYD | D47: PITVIPER 351 | F47: 4400584469 | I47: LISTO PARA DESPACHO | N47: OK | P47: OK | S47: OK | W47: OK | AD47: OK | AG47: OK | AJ47: OK | AK47: TS | AT47: =IFERROR((COUNTIF(Tabla1[[#This Row],[Relleno]:[Cromado3]],"OK")*1+COUNTIF(Tabla1[[#This Row],[Relleno]:[Cromado3]],"PR")*0.5+COUNTIF(Tabla1[[#This Row],[Relleno]:[Cromado3]],"TS")*0.05)/(COUNTIF(Tabla1[[#This Row],[Relleno]:[Cromado3]],"OK")+COUNTIF(Tabla1[[#This Row],[Relleno]:[Cromado3]],"PR")+COUNTIF(Tabla1[[#This Row],[Relleno]:[Cromado3]],"TS")+COUNTIF(Tabla1[[#This Row],[Relleno]:[Cromado3]],"X")),0) -> 0.88125
A48: 287924 | B48: BAMBAS | C48: CILINDRO DE STICK | D48: 390DL | F48: 4400584468 | I48: LISTO PARA DESPACHO | N48: OK | P48: OK | Q48: OK | S48: OK | U48: OK | V48: OK | X48: OK | Y48: OK | Z48: OK | AA48: OK | AD48: OK | AG48: OK | AJ48: OK | AK48: OK | AT48: =IFERROR((COUNTIF(Tabla1[[#This Row],[Relleno]:[Cromado3]],"OK")*1+COUNTIF(Tabla1[[#This Row],[Relleno]:[Cromado3]],"PR")*0.5+COUNTIF(Tabla1[[#This Row],[Relleno]:[Cromado3]],"TS")*0.05)/(COUNTIF(Tabla1[[#This Row],[Relleno]:[Cromado3]],"OK")+COUNTIF(Tabla1[[#This Row],[Relleno]:[Cromado3]],"PR")+COUNTIF(Tabla1[[#This Row],[Relleno]:[Cromado3]],"TS")+COUNTIF(Tabla1[[#This Row],[Relleno]:[Cromado3]],"X")),0) -> 1
A49: 288024 | B49: UNIMAQ | C49: CILINDRO HIDRAULICO | D49: 1320 | I49: LISTO PARA DESPACHO | L49: OK | M49: OK | N49: OK | T49: OK | U49: OK | V49: OK | W49: OK | AC49: OK | AD49: OK | AG49: OK | AJ49: OK | AS49: TIENE BOCINA INSTALADA VASTGO | AT49: =IFERROR((COUNTIF(Tabla1[[#This Row],[Relleno]:[Cromado3]],"OK")*1+COUNTIF(Tabla1[[#This Row],[Relleno]:[Cromado3]],"PR")*0.5+COUNTIF(Tabla1[[#This Row],[Relleno]:[Cromado3]],"TS")*0.05)/(COUNTIF(Tabla1[[#This Row],[Relleno]:[Cromado3]],"OK")+COUNTIF(Tabla1[[#This Row],[Relleno]:[Cromado3]],"PR")+COUNTIF(Tabla1[[#This Row],[Relleno]:[Cromado3]],"TS")+COUNTIF(Tabla1[[#This Row],[Relleno]:[Cromado3]],"X")),0) -> 1
A50: 288124 | B50: ANTAPACCAY | C50: CILINDRO HIDRAULICO | D50: 1153 | I50: ENTREGADO | N50: OK | W50: OK | AD50: OK | AG50: OK | AJ50: PR | AT50: =IFERROR((COUNTIF(Tabla1[[#This Row],[Relleno]:[Cromado3]],"OK")*1+COUNTIF(Tabla1[[#This Row],[Relleno]:[Cromado3]],"PR")*0.5+COUNTIF(Tabla1[[#This Row],[Relleno]:[Cromado3]],"TS")*0.05)/(COUNTIF(Tabla1[[#This Row],[Relleno]:[Cromado3]],"OK")+COUNTIF(Tabla1[[#This Row],[Relleno]:[Cromado3]],"PR")+COUNTIF(Tabla1[[#This Row],[Relleno]:[Cromado3]],"TS")+COUNTIF(Tabla1[[#This Row],[Relleno]:[Cromado3]],"X")),0) -> 0.9
A51: 288224 | B51: ANTAPACCAY | C51: CILINDRO HIDRAULICO | D51: 1153 | I51: ENTREGADO | N51: OK | W51: OK | AD51: OK | AG51: OK | AJ51: PR | AT51: =IFERROR((COUNTIF(Tabla1[[#This Row],[Relleno]:[Cromado3]],"OK")*1+COUNTIF(Tabla1[[#This Row],[Relleno]:[Cromado3]],"PR")*0.5+COUNTIF(Tabla1[[#This Row],[Relleno]:[Cromado3]],"TS")*0.05)/(COUNTIF(Tabla1[[#This Row],[Relleno]:[Cromado3]],"OK")+COUNTIF(Tabla1[[#This Row],[Relleno]:[Cromado3]],"PR")+COUNTIF(Tabla1[[#This Row],[Relleno]:[Cromado3]],"TS")+COUNTIF(Tabla1[[#This Row],[Relleno]:[Cromado3]],"X")),0) -> 0.9
A52: 288324 | B52: ANTAPACCAY | C52: CILINDRO DE INCLINACION DE BULLDOZER | D52: D11T | F52: 4500525799 | I52: LISTO PARA DESPACHO | L52: OK | M52: OK | N52: OK | P52: OK | Q52: OK | S52: OK | W52: OK | AD52: OK | AG52: OK | AJ52: ok | AK52: PR | AT52: =IFERROR((COUNTIF(Tabla1[[#This Row],[Relleno]:[Cromado3]],"OK")*1+COUNTIF(Tabla1[[#This Row],[Relleno]:[Cromado3]],"PR")*0.5+COUNTIF(Tabla1[[#This Row],[Relleno]:[Cromado3]],"TS")*0.05)/(COUNTIF(Tabla1[[#This Row],[Relleno]:[Cromado3]],"OK")+COUNTIF(Tabla1[[#This Row],[Relleno]:[Cromado3]],"PR")+COUNTIF(Tabla1[[#This Row],[Relleno]:[Cromado3]],"TS")+COUNTIF(Tabla1[[#This Row],[Relleno]:[Cromado3]],"X")),0) -> 0.95454545
A53: 288424 | B53: ANTAPACCAY | C53: CILINDRO DE ARTICULACION | D53: 24 | F53: 4500528882 | I53: LISTO PARA DESPACHO | L53: OK | M53: OK | N53: OK | P53: OK | Q53: OK | R53: OK | S53: OK | U53: OK | V53: OK | X53: OK | Y53: OK | Z53: OK | AA53: OK | AD53: X | AE53: X | AG53: X | AT53: =IFERROR((COUNTIF(Tabla1[[#This Row],[Relleno]:[Cromado3]],"OK")*1+COUNTIF(Tabla1[[#This Row],[Relleno]:[Cromado3]],"PR")*0.5+COUNTIF(Tabla1[[#This Row],[Relleno]:[Cromado3]],"TS")*0.05)/(COUNTIF(Tabla1[[#This Row],[Relleno]:[Cromado3]],"OK")+COUNTIF(Tabla1[[#This Row],[Relleno]:[Cromado3]],"PR")+COUNTIF(Tabla1[[#This Row],[Relleno]:[Cromado3]],"TS")+COUNTIF(Tabla1[[#This Row],[Relleno]:[Cromado3]],"X")),0) -> 0.8125
A54: 288524 | B54: ANTAPACCAY | C54: CILINDRO DE LEVANTE DE TOLVA | D54: 797F | F54: 4500528753 | I54: LISTO PARA DESPACHO | L54: OK | M54: OK | N54: OK | U54: OK | V54: OK | W54: OK | AA54: OK | AD54: X | AG54: X | AL54: X | AM54: X | AO54: X | AR54: X | AT54: =IFERROR((COUNTIF(Tabla1[[#This Row],[Relleno]:[Cromado3]],"OK")*1+COUNTIF(Tabla1[[#This Row],[Relleno]:[Cromado3]],"PR")*0.5+COUNTIF(Tabla1[[#This Row],[Relleno]:[Cromado3]],"TS")*0.05)/(COUNTIF(Tabla1[[#This Row],[Relleno]:[Cromado3]],"OK")+COUNTIF(Tabla1[[#This Row],[Relleno]:[Cromado3]],"PR")+COUNTIF(Tabla1[[#This Row],[Relleno]:[Cromado3]],"TS")+COUNTIF(Tabla1[[#This Row],[Relleno]:[Cromado3]],"X")),0) -> 0.53846154
A55: 288624 | B55: BAMBAS | C55: CILINDRO DE BOOM | D55: 390DL | E55: M | F55: 4400586161 | I55: LISTO PARA DESPACHO | N55: OK | U55: OK | V55: OK | W55: OK | AD55: OK | AG55: OK | AJ55: OK | AK55: OK | AT55: =IFERROR((COUNTIF(Tabla1[[#This Row],[Relleno]:[Cromado3]],"OK")*1+COUNTIF(Tabla1[[#This Row],[Relleno]:[Cromado3]],"PR")*0.5+COUNTIF(Tabla1[[#This Row],[Relleno]:[Cromado3]],"TS")*0.05)/(COUNTIF(Tabla1[[#This Row],[Relleno]:[Cromado3]],"OK")+COUNTIF(Tabla1[[#This Row],[Relleno]:[Cromado3]],"PR")+COUNTIF(Tabla1[[#This Row],[Relleno]:[Cromado3]],"TS")+COUNTIF(Tabla1[[#This Row],[Relleno]:[Cromado3]],"X")),0) -> 1
A56: 288724 | B56: BAMBAS | C56: CILINDRO DE BOOM | D56: 390DL | E56: M | F56: 4400586157 | I56: LISTO PARA DESPACHO | L56: OK | M56: OK | N56: OK | U56: OK | V56: OK | W56: - | X56: OK | Y56: OK | Z56: OK | AA56: OK | AD56: X | AG56: X | AT56: =IFERROR((COUNTIF(Tabla1[[#This Row],[Relleno]:[Cromado3]],"OK")*1+COUNTIF(Tabla1[[#This Row],[Relleno]:[Cromado3]],"PR")*0.5+COUNTIF(Tabla1[[#This Row],[Relleno]:[Cromado3]],"TS")*0.05)/(COUNTIF(Tabla1[[#This Row],[Relleno]:[Cromado3]],"OK")+COUNTIF(Tabla1[[#This Row],[Relleno]:[Cromado3]],"PR")+COUNTIF(Tabla1[[#This Row],[Relleno]:[Cromado3]],"TS")+COUNTIF(Tabla1[[#This Row],[Relleno]:[Cromado3]],"X")),0) -> 0.81818182
A57: 288824 | B57: BAMBAS | C57: FRENO DELANTERO | D57: 24M | F57: 4400585966 | I57: LISTO PARA DESPACHO | AT57: =IFERROR((COUNTIF(Tabla1[[#This Row],[Relleno]:[Cromado3]],"OK")*1+COUNTIF(Tabla1[[#This Row],[Relleno]:[Cromado3]],"PR")*0.5+COUNTIF(Tabla1[[#This Row],[Relleno]:[Cromado3]],"TS")*0.05)/(COUNTIF(Tabla1[[#This Row],[Relleno]:[Cromado3]],"OK")+COUNTIF(Tabla1[[#This Row],[Relleno]:[Cromado3]],"PR")+COUNTIF(Tabla1[[#This Row],[Relleno]:[Cromado3]],"TS")+COUNTIF(Tabla1[[#This Row],[Relleno]:[Cromado3]],"X")),0) -> 0
A58: 288924 | B58: BAMBAS | C58: FRENO DELANTERO | D58: 24M | F58: 4400585971 | I58: LISTO PARA DESPACHO | AT58: =IFERROR((COUNTIF(Tabla1[[#This Row],[Relleno]:[Cromado3]],"OK")*1+COUNTIF(Tabla1[[#This Row],[Relleno]:[Cromado3]],"PR")*0.5+COUNTIF(Tabla1[[#This Row],[Relleno]:[Cromado3]],"TS")*0.05)/(COUNTIF(Tabla1[[#This Row],[Relleno]:[Cromado3]],"OK")+COUNTIF(Tabla1[[#This Row],[Relleno]:[Cromado3]],"PR")+COUNTIF(Tabla1[[#This Row],[Relleno]:[Cromado3]],"TS")+COUNTIF(Tabla1[[#This Row],[Relleno]:[Cromado3]],"X")),0) -> 0
A59: 289024 | B59: BAMBAS | C59: CILINDRO DE LEVANTE DE BULLDOZER | D59: 844H | F59: 4400585961 | I59: ENTREGADO | L59: X | M59: X | N59: X | O59: X | W59: PR | AD59: X | AG59: X | AT59: =IFERROR((COUNTIF(Tabla1[[#This Row],[Relleno]:[Cromado3]],"OK")*1+COUNTIF(Tabla1[[#This Row],[Relleno]:[Cromado3]],"PR")*0.5+COUNTIF(Tabla1[[#This Row],[Relleno]:[Cromado3]],"TS")*0.05)/(COUNTIF(Tabla1[[#This Row],[Relleno]:[Cromado3]],"OK")+COUNTIF(Tabla1[[#This Row],[Relleno]:[Cromado3]],"PR")+COUNTIF(Tabla1[[#This Row],[Relleno]:[Cromado3]],"TS")+COUNTIF(Tabla1[[#This Row],[Relleno]:[Cromado3]],"X")),0) -> 0.071428571
A60: 289124 | B60: BAMBAS | C60: ACUMULADOR DE DIRECCION | D60: 930E-4SE | F60: 4400585958 | I60: ENTREGADO | AJ60: OK | AK60: OK | AT60: =IFERROR((COUNTIF(Tabla1[[#This Row],[Relleno]:[Cromado3]],"OK")*1+COUNTIF(Tabla1[[#This Row],[Relleno]:[Cromado3]],"PR")*0.5+COUNTIF(Tabla1[[#This Row],[Relleno]:[Cromado3]],"TS")*0.05)/(COUNTIF(Tabla1[[#This Row],[Relleno]:[Cromado3]],"OK")+COUNTIF(Tabla1[[#This Row],[Relleno]:[Cromado3]],"PR")+COUNTIF(Tabla1[[#This Row],[Relleno]:[Cromado3]],"TS")+COUNTIF(Tabla1[[#This Row],[Relleno]:[Cromado3]],"X")),0) -> 1
A61: 289224 | B61: BAMBAS | C61: CILINDRO DE DIRECCION | D61: 930E-4SE | F61: 4400587007 | I61: LISTO PARA DESPACHO | L61: OK | M61: OK | N61: OK | U61: OK | V61: OK | W61: OK | AD61: OK | AE61: OK | AG61: OK | AJ61: OK | AK61: OK | AT61: =IFERROR((COUNTIF(Tabla1[[#This Row],[Relleno]:[Cromado3]],"OK")*1+COUNTIF(Tabla1[[#This Row],[Relleno]:[Cromado3]],"PR")*0.5+COUNTIF(Tabla1[[#This Row],[Relleno]:[Cromado3]],"TS")*0.05)/(COUNTIF(Tabla1[[#This Row],[Relleno]:[Cromado3]],"OK")+COUNTIF(Tabla1[[#This Row],[Relleno]:[Cromado3]],"PR")+COUNTIF(Tabla1[[#This Row],[Relleno]:[Cromado3]],"TS")+COUNTIF(Tabla1[[#This Row],[Relleno]:[Cromado3]],"X")),0) -> 1
A62: 289324 | B62: BAMBAS | C62: CILINDRO DE DIRECCION | D62: 930E-4SE | F62: 4400587006 | I62: LISTO PARA DESPACHO | L62: OK | M62: OK | N62: OK | U62: OK | V62: OK | W62: OK | AD62: ok | AG62: OK | AJ62: OK | AK62: OK | AT62: =IFERROR((COUNTIF(Tabla1[[#This Row],[Relleno]:[Cromado3]],"OK")*1+COUNTIF(Tabla1[[#This Row],[Relleno]:[Cromado3]],"PR")*0.5+COUNTIF(Tabla1[[#This Row],[Relleno]:[Cromado3]],"TS")*0.05)/(COUNTIF(Tabla1[[#This Row],[Relleno]:[Cromado3]],"OK")+COUNTIF(Tabla1[[#This Row],[Relleno]:[Cromado3]],"PR")+COUNTIF(Tabla1[[#This Row],[Relleno]:[Cromado3]],"TS")+COUNTIF(Tabla1[[#This Row],[Relleno]:[Cromado3]],"X")),0) -> 1
A63: 289424 | B63: BAMBAS | C63: GATA HIDRONEUMATICA + PLATO ESTABILIZADOR | D63: 250700N | I63: FUERA DE PROGRAMA | N63: OK | P63: SE ENVIA A UN TERCERO | AJ63: OK | AK63: TS | AL63: FALTA EMBALAR Y PINTAR | AT63: =IFERROR((COUNTIF(Tabla1[[#This Row],[Relleno]:[Cromado3]],"OK")*1+COUNTIF(Tabla1[[#This Row],[Relleno]:[Cromado3]],"PR")*0.5+COUNTIF(Tabla1[[#This Row],[Relleno]:[Cromado3]],"TS")*0.05)/(COUNTIF(Tabla1[[#This Row],[Relleno]:[Cromado3]],"OK")+COUNTIF(Tabla1[[#This Row],[Relleno]:[Cromado3]],"PR")+COUNTIF(Tabla1[[#This Row],[Relleno]:[Cromado3]],"TS")+COUNTIF(Tabla1[[#This Row],[Relleno]:[Cromado3]],"X")),0) -> 0.68333333
A64: 289524 | B64: ANTAPACCAY | C64: CILINDRO DE LEVANTE DE BULLDOZER | D64: 844H | F64: 4500530643 | I64: LISTO PARA DESPACHO | N64: OK | X64: OK | Y64: OK | Z64: OK | AA64: OK | AD64: OK | AG64: X | AJ64: TS | AK64: X | AT64: =IFERROR((COUNTIF(Tabla1[[#This Row],[Relleno]:[Cromado3]],"OK")*1+COUNTIF(Tabla1[[#This Row],[Relleno]:[Cromado3]],"PR")*0.5+COUNTIF(Tabla1[[#This Row],[Relleno]:[Cromado3]],"TS")*0.05)/(COUNTIF(Tabla1[[#This Row],[Relleno]:[Cromado3]],"OK")+COUNTIF(Tabla1[[#This Row],[Relleno]:[Cromado3]],"PR")+COUNTIF(Tabla1[[#This Row],[Relleno]:[Cromado3]],"TS")+COUNTIF(Tabla1[[#This Row],[Relleno]:[Cromado3]],"X")),0) -> 0.67222222
A65: 289624 | B65: ANTAPACCAY | C65: CILINDRO DE INCLINACION DE BULLDOZER | D65: 844K | F65: 4500530645 | I65: LISTO PARA DESPACHO | L65: OK | M65: OK | N65: OK | O65: OK | P65: OK | Q65: OK | S65: OK | T65: OK | U65: OK | V65: OK | X65: OK | Y65: OK | Z65: OK | AA65: OK | AD65: OK | AE65: OK | AG65: OK | AJ65: OK | AT65: =IFERROR((COUNTIF(Tabla1[[#This Row],[Relleno]:[Cromado3]],"OK")*1+COUNTIF(Tabla1[[#This Row],[Relleno]:[Cromado3]],"PR")*0.5+COUNTIF(Tabla1[[#This Row],[Relleno]:[Cromado3]],"TS")*0.05)/(COUNTIF(Tabla1[[#This Row],[Relleno]:[Cromado3]],"OK")+COUNTIF(Tabla1[[#This Row],[Relleno]:[Cromado3]],"PR")+COUNTIF(Tabla1[[#This Row],[Relleno]:[Cromado3]],"TS")+COUNTIF(Tabla1[[#This Row],[Relleno]:[Cromado3]],"X")),0) -> 1
A66: 289724 | B66: ANTAPACCAY | C66: CILINDRO DE STICK | D66: 390DL | E66: 27 | F66: 4500530646 | I66: ENTREGADO | L66: OK | M66: OK | N66: OK | P66: OK | Q66: OK | R66: OK | S66: OK | U66: OK | V66: OK | X66: OK | Y66: OK | Z66: OK | AA66: OK | AD66: OK | AG66: OK | AJ66: OK | AK66: OK | AT66: =IFERROR((COUNTIF(Tabla1[[#This Row],[Relleno]:[Cromado3]],"OK")*1+COUNTIF(Tabla1[[#This Row],[Relleno]:[Cromado3]],"PR")*0.5+COUNTIF(Tabla1[[#This Row],[Relleno]:[Cromado3]],"TS")*0.05)/(COUNTIF(Tabla1[[#This Row],[Relleno]:[Cromado3]],"OK")+COUNTIF(Tabla1[[#This Row],[Relleno]:[Cromado3]],"PR")+COUNTIF(Tabla1[[#This Row],[Relleno]:[Cromado3]],"TS")+COUNTIF(Tabla1[[#This Row],[Relleno]:[Cromado3]],"X")),0) -> 1
A67: 289924 | B67: BAMBAS | C67: CILINDRO DE GARRA | D67: 988K | I67: ENTREGADO | P67: OK | Q67: OK | T67: OK | X67: OK | Y67: OK | Z67: OK | AA67: OK | AF67: OK | AI67: OK | AJ67: OK | AK67: OK | AT67: =IFERROR((COUNTIF(Tabla1[[#This Row],[Relleno]:[Cromado3]],"OK")*1+COUNTIF(Tabla1[[#This Row],[Relleno]:[Cromado3]],"PR")*0.5+COUNTIF(Tabla1[[#This Row],[Relleno]:[Cromado3]],"TS")*0.05)/(COUNTIF(Tabla1[[#This Row],[Relleno]:[Cromado3]],"OK")+COUNTIF(Tabla1[[#This Row],[Relleno]:[Cromado3]],"PR")+COUNTIF(Tabla1[[#This Row],[Relleno]:[Cromado3]],"TS")+COUNTIF(Tabla1[[#This Row],[Relleno]:[Cromado3]],"X")),0) -> 1
A68: 290324 | B68: BAMBAS | C68: MOTOR DE GIRO DE TORNAMESA | D68: 988K | I68: FUERA DE PROGRAMA | AT68: =IFERROR((COUNTIF(Tabla1[[#This Row],[Relleno]:[Cromado3]],"OK")*1+COUNTIF(Tabla1[[#This Row],[Relleno]:[Cromado3]],"PR")*0.5+COUNTIF(Tabla1[[#This Row],[Relleno]:[Cromado3]],"TS")*0.05)/(COUNTIF(Tabla1[[#This Row],[Relleno]:[Cromado3]],"OK")+COUNTIF(Tabla1[[#This Row],[Relleno]:[Cromado3]],"PR")+COUNTIF(Tabla1[[#This Row],[Relleno]:[Cromado3]],"TS")+COUNTIF(Tabla1[[#This Row],[Relleno]:[Cromado3]],"X")),0) -> 0
A69: 290424 | B69: BAMBAS | C69: BOMA HIDRAULICA DE ENROLLADOR | D69: 988K | I69: FUERA DE PROGRAMA | AT69: =IFERROR((COUNTIF(Tabla1[[#This Row],[Relleno]:[Cromado3]],"OK")*1+COUNTIF(Tabla1[[#This Row],[Relleno]:[Cromado3]],"PR")*0.5+COUNTIF(Tabla1[[#This Row],[Relleno]:[Cromado3]],"TS")*0.05)/(COUNTIF(Tabla1[[#This Row],[Relleno]:[Cromado3]],"OK")+COUNTIF(Tabla1[[#This Row],[Relleno]:[Cromado3]],"PR")+COUNTIF(Tabla1[[#This Row],[Relleno]:[Cromado3]],"TS")+COUNTIF(Tabla1[[#This Row],[Relleno]:[Cromado3]],"X")),0) -> 0
A70: 290524 | B70: BAMBAS | C70: PIÑON CEMENTADO | D70: 988K | I70: FUERA DE PROGRAMA | AT70: =IFERROR((COUNTIF(Tabla1[[#This Row],[Relleno]:[Cromado3]],"OK")*1+COUNTIF(Tabla1[[#This Row],[Relleno]:[Cromado3]],"PR")*0.5+COUNTIF(Tabla1[[#This Row],[Relleno]:[Cromado3]],"TS")*0.05)/(COUNTIF(Tabla1[[#This Row],[Relleno]:[Cromado3]],"OK")+COUNTIF(Tabla1[[#This Row],[Relleno]:[Cromado3]],"PR")+COUNTIF(Tabla1[[#This Row],[Relleno]:[Cromado3]],"TS")+COUNTIF(Tabla1[[#This Row],[Relleno]:[Cromado3]],"X")),0) -> 0
A71: 290624 | B71: BAMBAS | C71: CILINDRO DE BLADETIP | D71: 24M | E71: A | F71: 4400587631 | I71: LISTO PARA DESPACHO | L71: OK | M71: OK | N71: OK | X71: OK | Y71: OK | Z71: OK | AA71: OK | AD71: OK | AE71: OK | AG71: X | AJ71: X | AK71: X | AT71: =IFERROR((COUNTIF(Tabla1[[#This Row],[Relleno]:[Cromado3]],"OK")*1+COUNTIF(Tabla1[[#This Row],[Relleno]:[Cromado3]],"PR")*0.5+COUNTIF(Tabla1[[#This Row],[Relleno]:[Cromado3]],"TS")*0.05)/(COUNTIF(Tabla1[[#This Row],[Relleno]:[Cromado3]],"OK")+COUNTIF(Tabla1[[#This Row],[Relleno]:[Cromado3]],"PR")+COUNTIF(Tabla1[[#This Row],[Relleno]:[Cromado3]],"TS")+COUNTIF(Tabla1[[#This Row],[Relleno]:[Cromado3]],"X")),0) -> 0.75
A72: 290724 | B72: BAMBAS | C72: CILINDRO DE DIRECCION | D72: 834K | E72: M | F72: 4400587628 | I72: ENTREGADO | L72: OK | M72: OK | N72: OK | U72: OK | V72: OK | W72: OK | AD72: X | AG72: X | AJ72: X | AK72: X | AS72: Compra de seager | AT72: =IFERROR((COUNTIF(Tabla1[[#This Row],[Relleno]:[Cromado3]],"OK")*1+COUNTIF(Tabla1[[#This Row],[Relleno]:[Cromado3]],"PR")*0.5+COUNTIF(Tabla1[[#This Row],[Relleno]:[Cromado3]],"TS")*0.05)/(COUNTIF(Tabla1[[#This Row],[Relleno]:[Cromado3]],"OK")+COUNTIF(Tabla1[[#This Row],[Relleno]:[Cromado3]],"PR")+COUNTIF(Tabla1[[#This Row],[Relleno]:[Cromado3]],"TS")+COUNTIF(Tabla1[[#This Row],[Relleno]:[Cromado3]],"X")),0) -> 0.6
A73: 290824 | B73: BAMBAS | C73: CILINDRO DE DIRECCION | D73: 834K | E73: M | F73: 4400587624 | I73: ENTREGADO | L73: OK | M73: OK | N73: OK | U73: OK | V73: OK | W73: OK | AD73: X | AG73: X | AJ73: X | AK73: X | AS73: Compra de seager | AT73: =IFERROR((COUNTIF(Tabla1[[#This Row],[Relleno]:[Cromado3]],"OK")*1+COUNTIF(Tabla1[[#This Row],[Relleno]:[Cromado3]],"PR")*0.5+COUNTIF(Tabla1[[#This Row],[Relleno]:[Cromado3]],"TS")*0.05)/(COUNTIF(Tabla1[[#This Row],[Relleno]:[Cromado3]],"OK")+COUNTIF(Tabla1[[#This Row],[Relleno]:[Cromado3]],"PR")+COUNTIF(Tabla1[[#This Row],[Relleno]:[Cromado3]],"TS")+COUNTIF(Tabla1[[#This Row],[Relleno]:[Cromado3]],"X")),0) -> 0.6
A74: 290924 | B74: BAMBAS | C74: CILINDRO DE LEVANTE DE RIPPER | D74: D11T | E74: A | F74: 4400587623 | I74: LISTO PARA DESPACHO | L74: OK | M74: OK | N74: OK | W74: OK | AD74: OK | AG74: OK | AJ74: OK | AK74: OK | AT74: =IFERROR((COUNTIF(Tabla1[[#This Row],[Relleno]:[Cromado3]],"OK")*1+COUNTIF(Tabla1[[#This Row],[Relleno]:[Cromado3]],"PR")*0.5+COUNTIF(Tabla1[[#This Row],[Relleno]:[Cromado3]],"TS")*0.05)/(COUNTIF(Tabla1[[#This Row],[Relleno]:[Cromado3]],"OK")+COUNTIF(Tabla1[[#This Row],[Relleno]:[Cromado3]],"PR")+COUNTIF(Tabla1[[#This Row],[Relleno]:[Cromado3]],"TS")+COUNTIF(Tabla1[[#This Row],[Relleno]:[Cromado3]],"X")),0) -> 1
A75: 291024 | B75: BAMBAS | C75: CILINDRO DE LEVANTE DE BULLDOZER | D75: 844H | E75: A | F75: 4400587575 | I75: LISTO PARA DESPACHO | N75: OK | W75: OK | AD75: OK | AE75: OK | AG75: x | AJ75: X | AK75: X | AT75: =IFERROR((COUNTIF(Tabla1[[#This Row],[Relleno]:[Cromado3]],"OK")*1+COUNTIF(Tabla1[[#This Row],[Relleno]:[Cromado3]],"PR")*0.5+COUNTIF(Tabla1[[#This Row],[Relleno]:[Cromado3]],"TS")*0.05)/(COUNTIF(Tabla1[[#This Row],[Relleno]:[Cromado3]],"OK")+COUNTIF(Tabla1[[#This Row],[Relleno]:[Cromado3]],"PR")+COUNTIF(Tabla1[[#This Row],[Relleno]:[Cromado3]],"TS")+COUNTIF(Tabla1[[#This Row],[Relleno]:[Cromado3]],"X")),0) -> 0.57142857
A76: 291124 | B76: BAMBAS | C76: CILINDRO DE INCLINACION DE BULLDOZER | D76: 844H | F76: 4400587576 | I76: LISTO PARA DESPACHO | L76: OK | M76: OK | N76: OK | O76: OK | P76: OK | Q76: OK | S76: OK | T76: OK | U76: OK | V76: OK | X76: OK | Y76: OK | Z76: OK | AA76: OK | AD76: OK | AE76: OK | AG76: OK | AJ76: OK | AK76: OK | AT76: =IFERROR((COUNTIF(Tabla1[[#This Row],[Relleno]:[Cromado3]],"OK")*1+COUNTIF(Tabla1[[#This Row],[Relleno]:[Cromado3]],"PR")*0.5+COUNTIF(Tabla1[[#This Row],[Relleno]:[Cromado3]],"TS")*0.05)/(COUNTIF(Tabla1[[#This Row],[Relleno]:[Cromado3]],"OK")+COUNTIF(Tabla1[[#This Row],[Relleno]:[Cromado3]],"PR")+COUNTIF(Tabla1[[#This Row],[Relleno]:[Cromado3]],"TS")+COUNTIF(Tabla1[[#This Row],[Relleno]:[Cromado3]],"X")),0) -> 1
A77: 291224 | B77: BAMBAS | C77: CILINDRO DE ARTICULACION | D77: 24M | E77: A | F77: 4400587580 | I77: LISTO PARA DESPACHO | L77: OK | M77: OK | N77: OK | U77: OK | V77: OK | W77: OK | X77: FAFLTA RELLENAR ESPIGA | AD77: X | AE77: X | AG77: X | AJ77: X | AK77: X | AT77: =IFERROR((COUNTIF(Tabla1[[#This Row],[Relleno]:[Cromado3]],"OK")*1+COUNTIF(Tabla1[[#This Row],[Relleno]:[Cromado3]],"PR")*0.5+COUNTIF(Tabla1[[#This Row],[Relleno]:[Cromado3]],"TS")*0.05)/(COUNTIF(Tabla1[[#This Row],[Relleno]:[Cromado3]],"OK")+COUNTIF(Tabla1[[#This Row],[Relleno]:[Cromado3]],"PR")+COUNTIF(Tabla1[[#This Row],[Relleno]:[Cromado3]],"TS")+COUNTIF(Tabla1[[#This Row],[Relleno]:[Cromado3]],"X")),0) -> 0.54545455
A78: 291324 | B78: BAMBAS | C78: CILINDRO DE LEVANTE DE BULLDOZER | D78: 844H | E78: A | F78: 4400587589 | I78: ENTREGADO | N78: OK | X78: OK | Y78: OK | Z78: OK | AA78: OK | AB78: OK | AD78: OK | AI78: OK | AJ78: X | AK78: X | AT78: =IFERROR((COUNTIF(Tabla1[[#This Row],[Relleno]:[Cromado3]],"OK")*1+COUNTIF(Tabla1[[#This Row],[Relleno]:[Cromado3]],"PR")*0.5+COUNTIF(Tabla1[[#This Row],[Relleno]:[Cromado3]],"TS")*0.05)/(COUNTIF(Tabla1[[#This Row],[Relleno]:[Cromado3]],"OK")+COUNTIF(Tabla1[[#This Row],[Relleno]:[Cromado3]],"PR")+COUNTIF(Tabla1[[#This Row],[Relleno]:[Cromado3]],"TS")+COUNTIF(Tabla1[[#This Row],[Relleno]:[Cromado3]],"X")),0) -> 0.8
A79: 291424 | B79: BAMBAS | C79: CILINDRO DE DIRECCION DE GIRO | D79: 988K | I79: ENTREGADO | L79: OK | M79: OK | N79: OK | U79: OK | V79: OK | X79: OK | Y79: OK | Z79: OK | AA79: OK | AD79: OK | AG79: OK | AH79: OK | AJ79: OK | AK79: OK | AS79: CAMBIO DE SEAGERS / SELLOS FAB | AT79: =IFERROR((COUNTIF(Tabla1[[#This Row],[Relleno]:[Cromado3]],"OK")*1+COUNTIF(Tabla1[[#This Row],[Relleno]:[Cromado3]],"PR")*0.5+COUNTIF(Tabla1[[#This Row],[Relleno]:[Cromado3]],"TS")*0.05)/(COUNTIF(Tabla1[[#This Row],[Relleno]:[Cromado3]],"OK")+COUNTIF(Tabla1[[#This Row],[Relleno]:[Cromado3]],"PR")+COUNTIF(Tabla1[[#This Row],[Relleno]:[Cromado3]],"TS")+COUNTIF(Tabla1[[#This Row],[Relleno]:[Cromado3]],"X")),0) -> 1
A80: 291524 | B80: BAMBAS | C80: CILINDRO DE INCLINACION DE BULLDOZER | D80: 844H | I80: FUERA DE PROGRAMA | L80: OK | M80: OK | N80: X | O80: TS | P80: OK | Q80: OK | R80: OK | S80: OK | T80: OK | U80: OK | V80: OK | X80: OK | Y80: OK | Z80: OK | AA80: OK | AD80: X | AE80: X | AG80: X | AJ80: X | AK80: X | AS80: 3 PERNOS Y ARANDELAS / GUIA DE TAPA | AT80: =IFERROR((COUNTIF(Tabla1[[#This Row],[Relleno]:[Cromado3]],"OK")*1+COUNTIF(Tabla1[[#This Row],[Relleno]:[Cromado3]],"PR")*0.5+COUNTIF(Tabla1[[#This Row],[Relleno]:[Cromado3]],"TS")*0.05)/(COUNTIF(Tabla1[[#This Row],[Relleno]:[Cromado3]],"OK")+COUNTIF(Tabla1[[#This Row],[Relleno]:[Cromado3]],"PR")+COUNTIF(Tabla1[[#This Row],[Relleno]:[Cromado3]],"TS")+COUNTIF(Tabla1[[#This Row],[Relleno]:[Cromado3]],"X")),0) -> 0.6525
A81: 291624 | B81: BAMBAS | C81: CILINDRO DE LEVANTE DE BULLDOZER | D81: 844H | I81: LISTO PARA DESPACHO | N81: OK | P81: OK | Q81: OK | R81: OK | S81: OK | X81: OK | Y81: OK | Z81: OK | AA81: OK | AD81: OK | AI81: OK | AJ81: OK | AK81: OK | AT81: =IFERROR((COUNTIF(Tabla1[[#This Row],[Relleno]:[Cromado3]],"OK")*1+COUNTIF(Tabla1[[#This Row],[Relleno]:[Cromado3]],"PR")*0.5+COUNTIF(Tabla1[[#This Row],[Relleno]:[Cromado3]],"TS")*0.05)/(COUNTIF(Tabla1[[#This Row],[Relleno]:[Cromado3]],"OK")+COUNTIF(Tabla1[[#This Row],[Relleno]:[Cromado3]],"PR")+COUNTIF(Tabla1[[#This Row],[Relleno]:[Cromado3]],"TS")+COUNTIF(Tabla1[[#This Row],[Relleno]:[Cromado3]],"X")),0) -> 1
A82: 291724 | B82: BAMBAS | C82: RUEDA DELANTERA | D82: 930E-4SE | F82: 4400588879 | I82: LISTO PARA DESPACHO | AT82: =IFERROR((COUNTIF(Tabla1[[#This Row],[Relleno]:[Cromado3]],"OK")*1+COUNTIF(Tabla1[[#This Row],[Relleno]:[Cromado3]],"PR")*0.5+COUNTIF(Tabla1[[#This Row],[Relleno]:[Cromado3]],"TS")*0.05)/(COUNTIF(Tabla1[[#This Row],[Relleno]:[Cromado3]],"OK")+COUNTIF(Tabla1[[#This Row],[Relleno]:[Cromado3]],"PR")+COUNTIF(Tabla1[[#This Row],[Relleno]:[Cromado3]],"TS")+COUNTIF(Tabla1[[#This Row],[Relleno]:[Cromado3]],"X")),0) -> 0
A83: 291824 | B83: BAMBAS | C83: CILINDRO DE SUSPENSION DELANTERA | D83: 930E-4SE | F83: 4400588878 | I83: LISTO PARA DESPACHO | AT83: =IFERROR((COUNTIF(Tabla1[[#This Row],[Relleno]:[Cromado3]],"OK")*1+COUNTIF(Tabla1[[#This Row],[Relleno]:[Cromado3]],"PR")*0.5+COUNTIF(Tabla1[[#This Row],[Relleno]:[Cromado3]],"TS")*0.05)/(COUNTIF(Tabla1[[#This Row],[Relleno]:[Cromado3]],"OK")+COUNTIF(Tabla1[[#This Row],[Relleno]:[Cromado3]],"PR")+COUNTIF(Tabla1[[#This Row],[Relleno]:[Cromado3]],"TS")+COUNTIF(Tabla1[[#This Row],[Relleno]:[Cromado3]],"X")),0) -> 0
A84: 291924 | B84: BAMBAS | C84: CILINDRO DE INCLINACION | D84: 980G | E84: M | F84: 4400587573 | I84: LISTO PARA DESPACHO | N84: OK | W84: OK | AD84: OK | AG84: OK | AH84: OK | AJ84: X | AK84: X | AT84: =IFERROR((COUNTIF(Tabla1[[#This Row],[Relleno]:[Cromado3]],"OK")*1+COUNTIF(Tabla1[[#This Row],[Relleno]:[Cromado3]],"PR")*0.5+COUNTIF(Tabla1[[#This Row],[Relleno]:[Cromado3]],"TS")*0.05)/(COUNTIF(Tabla1[[#This Row],[Relleno]:[Cromado3]],"OK")+COUNTIF(Tabla1[[#This Row],[Relleno]:[Cromado3]],"PR")+COUNTIF(Tabla1[[#This Row],[Relleno]:[Cromado3]],"TS")+COUNTIF(Tabla1[[#This Row],[Relleno]:[Cromado3]],"X")),0) -> 0.71428571
A85: 292024 | B85: BAMBAS | C85: CILINDRO DE INCLINACION DE BULLDOZER | D85: D11T | E85: A | F85: 4400587584 | I85: ENTREGADO | L85: OK | M85: OK | N85: OK | O85: OK | T85: OK | X85: OK | Y85: OK | Z85: OK | AA85: OK | AD85: OK | AE85: OK | AG85: OK | AJ85: OK | AK85: OK | AT85: =IFERROR((COUNTIF(Tabla1[[#This Row],[Relleno]:[Cromado3]],"OK")*1+COUNTIF(Tabla1[[#This Row],[Relleno]:[Cromado3]],"PR")*0.5+COUNTIF(Tabla1[[#This Row],[Relleno]:[Cromado3]],"TS")*0.05)/(COUNTIF(Tabla1[[#This Row],[Relleno]:[Cromado3]],"OK")+COUNTIF(Tabla1[[#This Row],[Relleno]:[Cromado3]],"PR")+COUNTIF(Tabla1[[#This Row],[Relleno]:[Cromado3]],"TS")+COUNTIF(Tabla1[[#This Row],[Relleno]:[Cromado3]],"X")),0) -> 1
A86: 292124 | B86: BAMBAS | C86: CILINDRO DE LEVANTE DE RIPPER | D86: 24 | E86: 27 | F86: 4400588269 | I86: LISTO PARA DESPACHO | J86: S | N86: OK | P86: OK | Q86: OK | S86: OK | U86: OK | V86: OK | X86: OK | Y86: OK | Z86: OK | AA86: OK | AB86: OK | AD86: OK | AE86: OK | AG86: OK | AJ86: OK | AK86: OK | AT86: =IFERROR((COUNTIF(Tabla1[[#This Row],[Relleno]:[Cromado3]],"OK")*1+COUNTIF(Tabla1[[#This Row],[Relleno]:[Cromado3]],"PR")*0.5+COUNTIF(Tabla1[[#This Row],[Relleno]:[Cromado3]],"TS")*0.05)/(COUNTIF(Tabla1[[#This Row],[Relleno]:[Cromado3]],"OK")+COUNTIF(Tabla1[[#This Row],[Relleno]:[Cromado3]],"PR")+COUNTIF(Tabla1[[#This Row],[Relleno]:[Cromado3]],"TS")+COUNTIF(Tabla1[[#This Row],[Relleno]:[Cromado3]],"X")),0) -> 1
A87: 292224 | B87: BAMBAS | C87: CILINDRO DE BLADELIFT | D87: 24M | E87: A | F87: 4400538270 | I87: ENTREGADO | L87: OK | M87: OK | N87: OK | W87: OK | X87: SOLO PULIDO DE VASTAGO | AD87: OK | AG87: OK | AJ87: OK | AK87: OK | AS87: SELLO FAB | AT87: =IFERROR((COUNTIF(Tabla1[[#This Row],[Relleno]:[Cromado3]],"OK")*1+COUNTIF(Tabla1[[#This Row],[Relleno]:[Cromado3]],"PR")*0.5+COUNTIF(Tabla1[[#This Row],[Relleno]:[Cromado3]],"TS")*0.05)/(COUNTIF(Tabla1[[#This Row],[Relleno]:[Cromado3]],"OK")+COUNTIF(Tabla1[[#This Row],[Relleno]:[Cromado3]],"PR")+COUNTIF(Tabla1[[#This Row],[Relleno]:[Cromado3]],"TS")+COUNTIF(Tabla1[[#This Row],[Relleno]:[Cromado3]],"X")),0) -> 1
A88: 292324 | B88: BAMBAS | C88: CILINDRO DE LEVANTE DE BULLDOZER | D88: D11T | E88: A | F88: 4400588271 | I88: LISTO PARA DESPACHO | N88: OK | O88: OK | T88: OK | U88: OK | V88: OK | W88: OK | AD88: OK | AG88: OK | AJ88: X | AK88: X | AT88: =IFERROR((COUNTIF(Tabla1[[#This Row],[Relleno]:[Cromado3]],"OK")*1+COUNTIF(Tabla1[[#This Row],[Relleno]:[Cromado3]],"PR")*0.5+COUNTIF(Tabla1[[#This Row],[Relleno]:[Cromado3]],"TS")*0.05)/(COUNTIF(Tabla1[[#This Row],[Relleno]:[Cromado3]],"OK")+COUNTIF(Tabla1[[#This Row],[Relleno]:[Cromado3]],"PR")+COUNTIF(Tabla1[[#This Row],[Relleno]:[Cromado3]],"TS")+COUNTIF(Tabla1[[#This Row],[Relleno]:[Cromado3]],"X")),0) -> 0.8
A89: 292424 | B89: BAMBAS | C89: CILINDRO DE SUSPENSION POSTERIOR | D89: 930E-4SE | E89: 29 | F89: 4400588656 | I89: LISTO PARA DESPACHO | J89: 10 | L89: OK | M89: OK | N89: OK | P89: OK | Q89: OK | S89: OK | U89: OK | V89: OK | W89: OK | AD89: OK | AG89: OK | AJ89: OK | AK89: X | AT89: =IFERROR((COUNTIF(Tabla1[[#This Row],[Relleno]:[Cromado3]],"OK")*1+COUNTIF(Tabla1[[#This Row],[Relleno]:[Cromado3]],"PR")*0.5+COUNTIF(Tabla1[[#This Row],[Relleno]:[Cromado3]],"TS")*0.05)/(COUNTIF(Tabla1[[#This Row],[Relleno]:[Cromado3]],"OK")+COUNTIF(Tabla1[[#This Row],[Relleno]:[Cromado3]],"PR")+COUNTIF(Tabla1[[#This Row],[Relleno]:[Cromado3]],"TS")+COUNTIF(Tabla1[[#This Row],[Relleno]:[Cromado3]],"X")),0) -> 0.92307692
A90: 292524 | B90: BAMBAS | C90: CILINDRO DE DIRECCION | D90: 930E-4SE | F90: 4400588869 | I90: LISTO PARA DESPACHO | L90: OK | M90: OK | N90: OK | U90: OK | V90: OK | W90: OK | AD90: OK | AG90: OK | AJ90: OK | AK90: OK | AT90: =IFERROR((COUNTIF(Tabla1[[#This Row],[Relleno]:[Cromado3]],"OK")*1+COUNTIF(Tabla1[[#This Row],[Relleno]:[Cromado3]],"PR")*0.5+COUNTIF(Tabla1[[#This Row],[Relleno]:[Cromado3]],"TS")*0.05)/(COUNTIF(Tabla1[[#This Row],[Relleno]:[Cromado3]],"OK")+COUNTIF(Tabla1[[#This Row],[Relleno]:[Cromado3]],"PR")+COUNTIF(Tabla1[[#This Row],[Relleno]:[Cromado3]],"TS")+COUNTIF(Tabla1[[#This Row],[Relleno]:[Cromado3]],"X")),0) -> 1
A91: 292624 | B91: BAMBAS | C91: CILINDRO DE DIRECCION | D91: 930E-4SE | F91: 4400588867 | I91: LISTO PARA DESPACHO | L91: OK | M91: OK | N91: OK | U91: OK | V91: OK | W91: OK | AD91: OK | AE91: OK | AG91: OK | AJ91: OK | AK91: OK | AT91: =IFERROR((COUNTIF(Tabla1[[#This Row],[Relleno]:[Cromado3]],"OK")*1+COUNTIF(Tabla1[[#This Row],[Relleno]:[Cromado3]],"PR")*0.5+COUNTIF(Tabla1[[#This Row],[Relleno]:[Cromado3]],"TS")*0.05)/(COUNTIF(Tabla1[[#This Row],[Relleno]:[Cromado3]],"OK")+COUNTIF(Tabla1[[#This Row],[Relleno]:[Cromado3]],"PR")+COUNTIF(Tabla1[[#This Row],[Relleno]:[Cromado3]],"TS")+COUNTIF(Tabla1[[#This Row],[Relleno]:[Cromado3]],"X")),0) -> 1
A92: 292724 | B92: BAMBAS | C92: CILINDRO DE DIRECCION | D92: 930E-4SE | F92: 4400588865 | I92: LISTO PARA DESPACHO | N92: OK | U92: OK | V92: OK | W92: OK | AD92: OK | AE92: OK | AG92: OK | AJ92: OK | AK92: OK | AT92: =IFERROR((COUNTIF(Tabla1[[#This Row],[Relleno]:[Cromado3]],"OK")*1+COUNTIF(Tabla1[[#This Row],[Relleno]:[Cromado3]],"PR")*0.5+COUNTIF(Tabla1[[#This Row],[Relleno]:[Cromado3]],"TS")*0.05)/(COUNTIF(Tabla1[[#This Row],[Relleno]:[Cromado3]],"OK")+COUNTIF(Tabla1[[#This Row],[Relleno]:[Cromado3]],"PR")+COUNTIF(Tabla1[[#This Row],[Relleno]:[Cromado3]],"TS")+COUNTIF(Tabla1[[#This Row],[Relleno]:[Cromado3]],"X")),0) -> 1
A93: 292824 | B93: ANTAPACCAY | C93: CILINDRO DE INCLINACION DE BULLDOZER | D93: 844K | E93: 12 | F93: 4500530644 | I93: LISTO PARA DESPACHO | L93: OK | M93: OK | N93: OK | O93: OK | P93: OK | Q93: OK | R93: OK | S93: OK | T93: OK | U93: OK | V93: OK | X93: OK | Y93: OK | Z93: OK | AA93: OK | AB93: OK | AD93: OK | AE93: OK | AG93: X | AT93: =IFERROR((COUNTIF(Tabla1[[#This Row],[Relleno]:[Cromado3]],"OK")*1+COUNTIF(Tabla1[[#This Row],[Relleno]:[Cromado3]],"PR")*0.5+COUNTIF(Tabla1[[#This Row],[Relleno]:[Cromado3]],"TS")*0.05)/(COUNTIF(Tabla1[[#This Row],[Relleno]:[Cromado3]],"OK")+COUNTIF(Tabla1[[#This Row],[Relleno]:[Cromado3]],"PR")+COUNTIF(Tabla1[[#This Row],[Relleno]:[Cromado3]],"TS")+COUNTIF(Tabla1[[#This Row],[Relleno]:[Cromado3]],"X")),0) -> 0.94736842
A94: 292924 | B94: ANTAPACCAY | C94: CILINDRO DE STICK | D94: 390FL | E94: 29 | F94: 4500531305 | G94: JIMMY | I94: LISTO PARA DESPACHO | N94: OK | U94: OK | V94: OK | X94: OK | Y94: OK | Z94: OK | AA94: OK | AB94: OK | AD94: OK | AG94: OK | AJ94: X | AK94: X | AT94: =IFERROR((COUNTIF(Tabla1[[#This Row],[Relleno]:[Cromado3]],"OK")*1+COUNTIF(Tabla1[[#This Row],[Relleno]:[Cromado3]],"PR")*0.5+COUNTIF(Tabla1[[#This Row],[Relleno]:[Cromado3]],"TS")*0.05)/(COUNTIF(Tabla1[[#This Row],[Relleno]:[Cromado3]],"OK")+COUNTIF(Tabla1[[#This Row],[Relleno]:[Cromado3]],"PR")+COUNTIF(Tabla1[[#This Row],[Relleno]:[Cromado3]],"TS")+COUNTIF(Tabla1[[#This Row],[Relleno]:[Cromado3]],"X")),0) -> 0.83333333
A95: 293024 | B95: ANTAPACCAY | C95: ACUMULADOR DE DIRECCION | D95: 797F | F95: 4500531281 | I95: LISTO PARA DESPACHO | N95: OK | AD95: X | AG95: X | AT95: =IFERROR((COUNTIF(Tabla1[[#This Row],[Relleno]:[Cromado3]],"OK")*1+COUNTIF(Tabla1[[#This Row],[Relleno]:[Cromado3]],"PR")*0.5+COUNTIF(Tabla1[[#This Row],[Relleno]:[Cromado3]],"TS")*0.05)/(COUNTIF(Tabla1[[#This Row],[Relleno]:[Cromado3]],"OK")+COUNTIF(Tabla1[[#This Row],[Relleno]:[Cromado3]],"PR")+COUNTIF(Tabla1[[#This Row],[Relleno]:[Cromado3]],"TS")+COUNTIF(Tabla1[[#This Row],[Relleno]:[Cromado3]],"X")),0) -> 0.33333333
A96: 293124 | B96: ANTAPACCAY | C96: CILINDRO DE DIRECCION | D96: 844K | F96: 4500531308 | I96: LISTO PARA DESPACHO | L96: OK | M96: OK | N96: OK | W96: OK | AD96: OK | AG96: OK | AJ96: OK | AK96: OK | AT96: =IFERROR((COUNTIF(Tabla1[[#This Row],[Relleno]:[Cromado3]],"OK")*1+COUNTIF(Tabla1[[#This Row],[Relleno]:[Cromado3]],"PR")*0.5+COUNTIF(Tabla1[[#This Row],[Relleno]:[Cromado3]],"TS")*0.05)/(COUNTIF(Tabla1[[#This Row],[Relleno]:[Cromado3]],"OK")+COUNTIF(Tabla1[[#This Row],[Relleno]:[Cromado3]],"PR")+COUNTIF(Tabla1[[#This Row],[Relleno]:[Cromado3]],"TS")+COUNTIF(Tabla1[[#This Row],[Relleno]:[Cromado3]],"X")),0) -> 1
A97: 293224 | B97: ANTAPACCAY | C97: CILINDRO DE DIRECCION | D97: 797F | F97: 4500531279 | I97: LISTO PARA DESPACHO | L97: OK | M97: OK | N97: OK | U97: OK | V97: OK | W97: OK | AD97: OK | AE97: OK | AG97: OK | AJ97: OK | AK97: OK | AT97: =IFERROR((COUNTIF(Tabla1[[#This Row],[Relleno]:[Cromado3]],"OK")*1+COUNTIF(Tabla1[[#This Row],[Relleno]:[Cromado3]],"PR")*0.5+COUNTIF(Tabla1[[#This Row],[Relleno]:[Cromado3]],"TS")*0.05)/(COUNTIF(Tabla1[[#This Row],[Relleno]:[Cromado3]],"OK")+COUNTIF(Tabla1[[#This Row],[Relleno]:[Cromado3]],"PR")+COUNTIF(Tabla1[[#This Row],[Relleno]:[Cromado3]],"TS")+COUNTIF(Tabla1[[#This Row],[Relleno]:[Cromado3]],"X")),0) -> 1
A98: 293324 | B98: ANTAPACCAY | C98: CILINDRO DE DIRECCION | D98: 930E-4SE | F98: 4500533511 | I98: LISTO PARA DESPACHO | L98: OK | M98: OK | N98: OK | U98: OK | V98: OK | W98: OK | AD98: OK | AE98: OK | AI98: X | AJ98: X | AK98: X | AT98: =IFERROR((COUNTIF(Tabla1[[#This Row],[Relleno]:[Cromado3]],"OK")*1+COUNTIF(Tabla1[[#This Row],[Relleno]:[Cromado3]],"PR")*0.5+COUNTIF(Tabla1[[#This Row],[Relleno]:[Cromado3]],"TS")*0.05)/(COUNTIF(Tabla1[[#This Row],[Relleno]:[Cromado3]],"OK")+COUNTIF(Tabla1[[#This Row],[Relleno]:[Cromado3]],"PR")+COUNTIF(Tabla1[[#This Row],[Relleno]:[Cromado3]],"TS")+COUNTIF(Tabla1[[#This Row],[Relleno]:[Cromado3]],"X")),0) -> 0.72727273
A99: 293424 | B99: ANTAPACCAY | C99: CILINDRO DE DIRECCION | D99: 830E | F99: 4500533683 | I99: LISTO PARA DESPACHO | AJ99: OK | AT99: =IFERROR((COUNTIF(Tabla1[[#This Row],[Relleno]:[Cromado3]],"OK")*1+COUNTIF(Tabla1[[#This Row],[Relleno]:[Cromado3]],"PR")*0.5+COUNTIF(Tabla1[[#This Row],[Relleno]:[Cromado3]],"TS")*0.05)/(COUNTIF(Tabla1[[#This Row],[Relleno]:[Cromado3]],"OK")+COUNTIF(Tabla1[[#This Row],[Relleno]:[Cromado3]],"PR")+COUNTIF(Tabla1[[#This Row],[Relleno]:[Cromado3]],"TS")+COUNTIF(Tabla1[[#This Row],[Relleno]:[Cromado3]],"X")),0) -> 1
A100: 293524 | B100: BAMBAS | C100: CILINDRO DE INCLINACION DE BULLDOZER | D100: D11T | E100: 2 | F100: 4400589268 | I100: LISTO PARA DESPACHO | J100: 6 | M100: OK | N100: OK | P100: OK | Q100: OK | S100: OK | U100: OK | V100: OK | X100: OK | Y100: OK | Z100: OK | AA100: OK | AB100: OK | AD100: OK | AE100: OK | AG100: OK | AJ100: X | AK100: X | AT100: =IFERROR((COUNTIF(Tabla1[[#This Row],[Relleno]:[Cromado3]],"OK")*1+COUNTIF(Tabla1[[#This Row],[Relleno]:[Cromado3]],"PR")*0.5+COUNTIF(Tabla1[[#This Row],[Relleno]:[Cromado3]],"TS")*0.05)/(COUNTIF(Tabla1[[#This Row],[Relleno]:[Cromado3]],"OK")+COUNTIF(Tabla1[[#This Row],[Relleno]:[Cromado3]],"PR")+COUNTIF(Tabla1[[#This Row],[Relleno]:[Cromado3]],"TS")+COUNTIF(Tabla1[[#This Row],[Relleno]:[Cromado3]],"X")),0) -> 0.88235294
A101: 293624 | B101: BAMBAS | C101: CILINDRO DE INCLINACION DE BULLDOZER | D101: D475 | E101: 29 | F101: 4400589585 | I101: LISTO PARA DESPACHO | J101: 6 | L101: OK | M101: OK | N101: OK | O101: OK | P101: OK | Q101: OK | R101: OK | S101: OK | T101: OK | U101: OK | V101: OK | W101: OK | AD101: OK | AE101: OK | AG101: OK | AJ101: X | AK101: X | AT101: =IFERROR((COUNTIF(Tabla1[[#This Row],[Relleno]:[Cromado3]],"OK")*1+COUNTIF(Tabla1[[#This Row],[Relleno]:[Cromado3]],"PR")*0.5+COUNTIF(Tabla1[[#This Row],[Relleno]:[Cromado3]],"TS")*0.05)/(COUNTIF(Tabla1[[#This Row],[Relleno]:[Cromado3]],"OK")+COUNTIF(Tabla1[[#This Row],[Relleno]:[Cromado3]],"PR")+COUNTIF(Tabla1[[#This Row],[Relleno]:[Cromado3]],"TS")+COUNTIF(Tabla1[[#This Row],[Relleno]:[Cromado3]],"X")),0) -> 0.88235294
...

Sheet Programa
B2: OT | C2: DESCRIPCION | D2: MODELO | E2: Nombre de tarea | F2: Nombres de los recursos | G2: Duración | H2: Comienzo | I2: Fin | J2: % trabajo completado
B3: OT | C3: DESCRIPCION | D3: MODELO | E3: TORNO 1 | F3: Gabriel Anco | G3: 5.53 días | H3: lun 30/09/24 | I3: lun 7/10/24 | J3: 0.36
B4: 287724 | C4: =_xlfn.XLOOKUP(B4,PLANEAMIENTO!A:A,PLANEAMIENTO!C:C) -> CILINDRO DE JACK HYD | D4: =_xlfn.XLOOKUP(B4,PLANEAMIENTO!A:A,PLANEAMIENTO!D:D) -> PITVIPER 351 | E4: Corte de tapa de cilindro | F4: Gabriel Anco | G4: 4 horas | H4: jue 3/10/24 | I4: jue 3/10/24 | J4: 0.2
B5: 286624 | C5: =_xlfn.XLOOKUP(B5,PLANEAMIENTO!A:A,PLANEAMIENTO!C:C) -> CILINDRO DE INCLINACION DE BULLDOZER | D5: =_xlfn.XLOOKUP(B5,PLANEAMIENTO!A:A,PLANEAMIENTO!D:D) -> D11T | E5: Maquinado de diámetro de salida de cilindro | F5: Gabriel Anco | G5: 3 horas | H5: jue 3/10/24 | I5: jue 3/10/24 | J5: 0
B6: 287824 | C6: =_xlfn.XLOOKUP(B6,PLANEAMIENTO!A:A,PLANEAMIENTO!C:C) -> CILINDRO DE JACK HYD | D6: =_xlfn.XLOOKUP(B6,PLANEAMIENTO!A:A,PLANEAMIENTO!D:D) -> PITVIPER 351 | E6: Corte de tapa de cilindro | F6: Gabriel Anco | G6: 4.5 horas | H6: jue 3/10/24 | I6: vie 4/10/24 | J6: 0
B7: 288324 | C7: =_xlfn.XLOOKUP(B7,PLANEAMIENTO!A:A,PLANEAMIENTO!C:C) -> CILINDRO DE INCLINACION DE BULLDOZER | D7: =_xlfn.XLOOKUP(B7,PLANEAMIENTO!A:A,PLANEAMIENTO!D:D) -> D11T | E7: Corte de cilindro | F7: Gabriel Anco | G7: 7 horas | H7: vie 4/10/24 | I7: lun 7/10/24 | J7: 0
B8: 288324 | C8: =_xlfn.XLOOKUP(B8,PLANEAMIENTO!A:A,PLANEAMIENTO!C:C) -> CILINDRO DE INCLINACION DE BULLDOZER | D8: =_xlfn.XLOOKUP(B8,PLANEAMIENTO!A:A,PLANEAMIENTO!D:D) -> D11T | E8: Maquinado de encastre de cilindro | F8: Gabriel Anco | G8: 7 horas | H8: lun 7/10/24 | I8: lun 7/10/24 | J8: 0
B9: OT | C9: DESCRIPCION | D9: MODELO | E9: TORNO 2 | F9: Rolando Yaique | G9: 4.42 días | H9: mar 1/10/24 | I9: lun 7/10/24 | J9: 0.19
B10: 287024 | C10: =_xlfn.XLOOKUP(B10,PLANEAMIENTO!A:A,PLANEAMIENTO!C:C) -> CILINDRO DE LEVANTE DE BULLDOZER | D10: =_xlfn.XLOOKUP(B10,PLANEAMIENTO!A:A,PLANEAMIENTO!D:D) -> D475 | E10: Fabricación de cojinetes | F10: Rolando Yaique | G10: 2 días | H10: mié 2/10/24 | I10: vie 4/10/24 | J10: 0.2
B11: 287324 | C11: =_xlfn.XLOOKUP(B11,PLANEAMIENTO!A:A,PLANEAMIENTO!C:C) -> CILINDRO DE DIRECCION | D11: =_xlfn.XLOOKUP(B11,PLANEAMIENTO!A:A,PLANEAMIENTO!D:D) -> 24 | E11: Maquinado de rosca de cilindro | F11: Rolando Yaique | G11: 4.5 horas | H11: vie 4/10/24 | I11: vie 4/10/24 | J11: 0
B12: 286024 | C12: =_xlfn.XLOOKUP(B12,PLANEAMIENTO!A:A,PLANEAMIENTO!C:C) -> CILINDRO DE DIRECCION | D12: =_xlfn.XLOOKUP(B12,PLANEAMIENTO!A:A,PLANEAMIENTO!D:D) -> 930E-4SE | E12: Fabricacion de piston | F12: Rolando Yaique | G12: 1 día | H12: vie 4/10/24 | I12: lun 7/10/24 | J12: 0
B13: OT | C13: DESCRIPCION | D13: MODELO | E13: TORNO 3 | F13: Luis Ramos | G13: 4.84 días? | H13: lun 30/09/24 | I13: lun 7/10/24 | J13: 0.65
B14: 291524 | C14: =_xlfn.XLOOKUP(B14,PLANEAMIENTO!A:A,PLANEAMIENTO!C:C) -> CILINDRO DE INCLINACION DE BULLDOZER | D14: =_xlfn.XLOOKUP(B14,PLANEAMIENTO!A:A,PLANEAMIENTO!D:D) -> 844H | E14: Corte de vastago | F14: Luis Ramos | G14: 2.5 horas | H14: mié 2/10/24 | I14: jue 3/10/24 | J14: 0.7
B15: 291324 | C15: =_xlfn.XLOOKUP(B15,PLANEAMIENTO!A:A,PLANEAMIENTO!C:C) -> CILINDRO DE LEVANTE DE BULLDOZER | D15: =_xlfn.XLOOKUP(B15,PLANEAMIENTO!A:A,PLANEAMIENTO!D:D) -> 844H | E15: Corte de vastago | F15: Luis Ramos | G15: 2.5 horas | H15: jue 3/10/24 | I15: jue 3/10/24 | J15: 0
B16: 291624 | C16: =_xlfn.XLOOKUP(B16,PLANEAMIENTO!A:A,PLANEAMIENTO!C:C) -> CILINDRO DE LEVANTE DE BULLDOZER | D16: =_xlfn.XLOOKUP(B16,PLANEAMIENTO!A:A,PLANEAMIENTO!D:D) -> 844H | E16: Corte de vastago | F16: Luis Ramos | G16: 2.5 horas | H16: jue 3/10/24 | I16: jue 3/10/24 | J16: 0
B17: 289524 | C17: =_xlfn.XLOOKUP(B17,PLANEAMIENTO!A:A,PLANEAMIENTO!C:C) -> CILINDRO DE LEVANTE DE BULLDOZER | D17: =_xlfn.XLOOKUP(B17,PLANEAMIENTO!A:A,PLANEAMIENTO!D:D) -> 844H | E17: Corte de vastago | F17: Luis Ramos | G17: 2.5 horas | H17: jue 3/10/24 | I17: vie 4/10/24 | J17: 0
B18: 286024 | C18: =_xlfn.XLOOKUP(B18,PLANEAMIENTO!A:A,PLANEAMIENTO!C:C) -> CILINDRO DE DIRECCION | D18: =_xlfn.XLOOKUP(B18,PLANEAMIENTO!A:A,PLANEAMIENTO!D:D) -> 930E-4SE | E18: Fabricación de cáncamo de vástago | F18: Luis Ramos | G18: 1 día | H18: vie 4/10/24 | I18: lun 7/10/24 | J18: 0
B19: OT | C19: DESCRIPCION | D19: MODELO | E19: SOLDADURA 1 | G19: 5.79 días? | H19: lun 30/09/24 | I19: mar 8/10/24 | J19: 0.47
B20: 286624 | C20: =_xlfn.XLOOKUP(B20,PLANEAMIENTO!A:A,PLANEAMIENTO!C:C) -> CILINDRO DE INCLINACION DE BULLDOZER | D20: =_xlfn.XLOOKUP(B20,PLANEAMIENTO!A:A,PLANEAMIENTO!D:D) -> D11T | E20: Soldadura de cilindro | F20: Justo Arocutipa | G20: 11 horas | H20: mié 2/10/24 | I20: jue 3/10/24 | J20: 0.3
B21: 287324 | C21: =_xlfn.XLOOKUP(B21,PLANEAMIENTO!A:A,PLANEAMIENTO!C:C) -> CILINDRO DE DIRECCION | D21: =_xlfn.XLOOKUP(B21,PLANEAMIENTO!A:A,PLANEAMIENTO!D:D) -> 24 | E21: Soldadura de cilindro y relleno de ojo | F21: Justo Arocutipa | G21: 5 horas | H21: vie 4/10/24 | I21: vie 4/10/24 | J21: 0
B22: 287724 | C22: =_xlfn.XLOOKUP(B22,PLANEAMIENTO!A:A,PLANEAMIENTO!C:C) -> CILINDRO DE JACK HYD | D22: =_xlfn.XLOOKUP(B22,PLANEAMIENTO!A:A,PLANEAMIENTO!D:D) -> PITVIPER 351 | E22: Rellenado de tapa posterior cilindro | F22: Justo Arocutipa | G22: 4 horas | H22: vie 4/10/24 | I22: vie 4/10/24 | J22: 0
B23: 273924 | C23: =_xlfn.XLOOKUP(B23,PLANEAMIENTO!A:A,PLANEAMIENTO!C:C) -> CILINDRO DE SUSPENSION POSTERIOR | D23: =_xlfn.XLOOKUP(B23,PLANEAMIENTO!A:A,PLANEAMIENTO!D:D) -> 797F | E23: Soldadura encastre de cilindro | F23: Justo Arocutipa | G23: 7 horas | H23: lun 7/10/24 | I23: lun 7/10/24 | J23: 0
B24: 273924 | C24: =_xlfn.XLOOKUP(B24,PLANEAMIENTO!A:A,PLANEAMIENTO!C:C) -> CILINDRO DE SUSPENSION POSTERIOR | D24: =_xlfn.XLOOKUP(B24,PLANEAMIENTO!A:A,PLANEAMIENTO!D:D) -> 797F | E24: Relleno Ojo de cilindro | F24: Justo Arocutipa | G24: 3 horas | H24: lun 7/10/24 | I24: mar 8/10/24 | J24: 0
B25: OT | C25: DESCRIPCION | D25: MODELO | E25: SOLDADURA 2 | G25: 5.58 días? | H25: lun 30/09/24 | I25: lun 7/10/24 | J25: 0
B26: 287024 | C26: =_xlfn.XLOOKUP(B26,PLANEAMIENTO!A:A,PLANEAMIENTO!C:C) -> CILINDRO DE LEVANTE DE BULLDOZER | D26: =_xlfn.XLOOKUP(B26,PLANEAMIENTO!A:A,PLANEAMIENTO!D:D) -> D475 | E26: Soldadura de encastre de vástago | F26: Victor Caceres | G26: 5 horas | H26: jue 3/10/24 | I26: jue 3/10/24 | J26: 0
B27: 287024 | C27: =_xlfn.XLOOKUP(B27,PLANEAMIENTO!A:A,PLANEAMIENTO!C:C) -> CILINDRO DE LEVANTE DE BULLDOZER | D27: =_xlfn.XLOOKUP(B27,PLANEAMIENTO!A:A,PLANEAMIENTO!D:D) -> D475 | E27: Relleno de ojo de vástago | F27: Victor Caceres | G27: 1 hora | H27: jue 3/10/24 | I27: jue 3/10/24 | J27: 0
B28: 279624 | C28: =_xlfn.XLOOKUP(B28,PLANEAMIENTO!A:A,PLANEAMIENTO!C:C) -> CILINDRO DE SUSPENSION POSTERIOR | D28: =_xlfn.XLOOKUP(B28,PLANEAMIENTO!A:A,PLANEAMIENTO!D:D) -> 797F | E28: Extraer rótula | F28: Victor Caceres | G28: 1 hora | H28: jue 3/10/24 | I28: jue 3/10/24 | J28: 0
B29: 279624 | C29: =_xlfn.XLOOKUP(B29,PLANEAMIENTO!A:A,PLANEAMIENTO!C:C) -> CILINDRO DE SUSPENSION POSTERIOR | D29: =_xlfn.XLOOKUP(B29,PLANEAMIENTO!A:A,PLANEAMIENTO!D:D) -> 797F | E29: Relleno ojo vástago | F29: Victor Caceres | G29: 4 horas | H29: jue 3/10/24 | I29: vie 4/10/24 | J29: 0
B30: 287924 | C30: =_xlfn.XLOOKUP(B30,PLANEAMIENTO!A:A,PLANEAMIENTO!C:C) -> CILINDRO DE STICK | D30: =_xlfn.XLOOKUP(B30,PLANEAMIENTO!A:A,PLANEAMIENTO!D:D) -> 390DL | E30: Extraer cojinete de cilindro | F30: Victor Caceres | G30: 1.3 horas | H30: vie 4/10/24 | I30: vie 4/10/24 | J30: 0
B31: 287924 | C31: =_xlfn.XLOOKUP(B31,PLANEAMIENTO!A:A,PLANEAMIENTO!C:C) -> CILINDRO DE STICK | D31: =_xlfn.XLOOKUP(B31,PLANEAMIENTO!A:A,PLANEAMIENTO!D:D) -> 390DL | E31: Relleno ojo cilindro | F31: Victor Caceres | G31: 6.5 horas | H31: vie 4/10/24 | I31: lun 7/10/24 | J31: 0
B32: OT | C32: DESCRIPCION | D32: MODELO | E32: BRUÑIDO | F32: Gabriel Gallegos | G32: 3.95 días | H32: mar 1/10/24 | I32: lun 7/10/24 | J32: 0.22
B33: 287024 | C33: =_xlfn.XLOOKUP(B33,PLANEAMIENTO!A:A,PLANEAMIENTO!C:C) -> CILINDRO DE LEVANTE DE BULLDOZER | D33: =_xlfn.XLOOKUP(B33,PLANEAMIENTO!A:A,PLANEAMIENTO!D:D) -> D475 | E33: Bruñido | F33: Gabriel Gallegos | G33: 2.5 horas | H33: jue 3/10/24 | I33: jue 3/10/24 | J33: 0.4
B34: 288624 | C34: =_xlfn.XLOOKUP(B34,PLANEAMIENTO!A:A,PLANEAMIENTO!C:C) -> CILINDRO DE BOOM | D34: =_xlfn.XLOOKUP(B34,PLANEAMIENTO!A:A,PLANEAMIENTO!D:D) -> 390DL | E34: Bruñido | F34: Gabriel Gallegos | G34: 2.5 horas | H34: jue 3/10/24 | I34: jue 3/10/24 | J34: 0
B35: 285224 | C35: =_xlfn.XLOOKUP(B35,PLANEAMIENTO!A:A,PLANEAMIENTO!C:C) -> CILINDRO DE INCLINACION DE BULLDOZER | D35: =_xlfn.XLOOKUP(B35,PLANEAMIENTO!A:A,PLANEAMIENTO!D:D) -> D11T | E35: Bruñido | F35: Gabriel Gallegos | G35: 2.5 horas | H35: jue 3/10/24 | I35: jue 3/10/24 | J35: 0
B36: 290724 | C36: =_xlfn.XLOOKUP(B36,PLANEAMIENTO!A:A,PLANEAMIENTO!C:C) -> CILINDRO DE DIRECCION | D36: =_xlfn.XLOOKUP(B36,PLANEAMIENTO!A:A,PLANEAMIENTO!D:D) -> 834K | E36: Bruñido | F36: Gabriel Gallegos | G36: 2.5 horas | H36: vie 4/10/24 | I36: vie 4/10/24 | J36: 0
B37: 290824 | C37: =_xlfn.XLOOKUP(B37,PLANEAMIENTO!A:A,PLANEAMIENTO!C:C) -> CILINDRO DE DIRECCION | D37: =_xlfn.XLOOKUP(B37,PLANEAMIENTO!A:A,PLANEAMIENTO!D:D) -> 834K | E37: Bruñido | F37: Gabriel Gallegos | G37: 2.5 horas | H37: vie 4/10/24 | I37: vie 4/10/24 | J37: 0
B38: 290924 | C38: =_xlfn.XLOOKUP(B38,PLANEAMIENTO!A:A,PLANEAMIENTO!C:C) -> CILINDRO DE LEVANTE DE RIPPER | D38: =_xlfn.XLOOKUP(B38,PLANEAMIENTO!A:A,PLANEAMIENTO!D:D) -> D11T | E38: Bruñido | F38: Gabriel Gallegos | G38: 2.5 horas | H38: vie 4/10/24 | I38: vie 4/10/24 | J38: 0
B39: 287724 | C39: =_xlfn.XLOOKUP(B39,PLANEAMIENTO!A:A,PLANEAMIENTO!C:C) -> CILINDRO DE JACK HYD | D39: =_xlfn.XLOOKUP(B39,PLANEAMIENTO!A:A,PLANEAMIENTO!D:D) -> PITVIPER 351 | E39: Bruñido | F39: Gabriel Gallegos | G39: 2.5 horas | H39: vie 4/10/24 | I39: lun 7/10/24 | J39: 0
B40: 286624 | C40: =_xlfn.XLOOKUP(B40,PLANEAMIENTO!A:A,PLANEAMIENTO!C:C) -> CILINDRO DE INCLINACION DE BULLDOZER | D40: =_xlfn.XLOOKUP(B40,PLANEAMIENTO!A:A,PLANEAMIENTO!D:D) -> D11T | E40: Bruñido | F40: Gabriel Gallegos | G40: 2.5 horas | H40: lun 7/10/24 | I40: lun 7/10/24 | J40: 0
B41: OT | C41: DESCRIPCION | D41: MODELO | E41: EVALUACION | G41: 4.68 días? | H41: mar 1/10/24 | I41: mar 8/10/24 | J41: 0
B42: 292124 | C42: =_xlfn.XLOOKUP(B42,PLANEAMIENTO!A:A,PLANEAMIENTO!C:C) -> CILINDRO DE LEVANTE DE RIPPER | D42: =_xlfn.XLOOKUP(B42,PLANEAMIENTO!A:A,PLANEAMIENTO!D:D) -> 24 | E42: EVALUACION | G42: 1 día? | H42: lun 7/10/24 | I42: mar 8/10/24 | J42: 0.02
B43: 291724 | C43: =_xlfn.XLOOKUP(B43,PLANEAMIENTO!A:A,PLANEAMIENTO!C:C) -> RUEDA DELANTERA | D43: =_xlfn.XLOOKUP(B43,PLANEAMIENTO!A:A,PLANEAMIENTO!D:D) -> 930E-4SE | E43: EVALUACION | G43: 1 día? | H43: jue 3/10/24 | I43: vie 4/10/24 | J43: 0.05
B44: 291824 | C44: =_xlfn.XLOOKUP(B44,PLANEAMIENTO!A:A,PLANEAMIENTO!C:C) -> CILINDRO DE SUSPENSION DELANTERA | D44: =_xlfn.XLOOKUP(B44,PLANEAMIENTO!A:A,PLANEAMIENTO!D:D) -> 930E-4SE | E44: EVALUACION | G44: 1 día? | H44: jue 3/10/24 | I44: vie 4/10/24 | J44: 0.05
B45: 292424 | C45: =_xlfn.XLOOKUP(B45,PLANEAMIENTO!A:A,PLANEAMIENTO!C:C) -> CILINDRO DE SUSPENSION POSTERIOR | D45: =_xlfn.XLOOKUP(B45,PLANEAMIENTO!A:A,PLANEAMIENTO!D:D) -> 930E-4SE | E45: DESARMADO | G45: 1 día? | H45: mar 1/10/24 | I45: mié 2/10/24 | J45: 0
B46: OT | C46: DESCRIPCION | D46: MODELO | E46: ARMADO | G46: 1.84 días | H46: jue 3/10/24 | I46: vie 4/10/24 | J46: 0
B47: 288024 | C47: =_xlfn.XLOOKUP(B47,PLANEAMIENTO!A:A,PLANEAMIENTO!C:C) -> CILINDRO HIDRAULICO | D47: =_xlfn.XLOOKUP(B47,PLANEAMIENTO!A:A,PLANEAMIENTO!D:D) -> 1320 | E47: PULIDO TAPA Y PISTON | F47: Luis Choque | G47: 2.5 horas | H47: jue 3/10/24 | I47: jue 3/10/24 | J47: 0
B48: 288024 | C48: =_xlfn.XLOOKUP(B48,PLANEAMIENTO!A:A,PLANEAMIENTO!C:C) -> CILINDRO HIDRAULICO | D48: =_xlfn.XLOOKUP(B48,PLANEAMIENTO!A:A,PLANEAMIENTO!D:D) -> 1320 | E48: ARMADO | F48: Luis Choque | G48: 2.5 horas | H48: jue 3/10/24 | I48: jue 3/10/24 | J48: 0
B49: 287524 | C49: =_xlfn.XLOOKUP(B49,PLANEAMIENTO!A:A,PLANEAMIENTO!C:C) -> CILINDRO DE STICK | D49: =_xlfn.XLOOKUP(B49,PLANEAMIENTO!A:A,PLANEAMIENTO!D:D) -> 988K | E49: PULIDO TAPA Y PISTON | F49: Jimmy Cuba | G49: 2.5 horas | H49: jue 3/10/24 | I49: jue 3/10/24 | J49: 0
B50: 287524 | C50: =_xlfn.XLOOKUP(B50,PLANEAMIENTO!A:A,PLANEAMIENTO!C:C) -> CILINDRO DE STICK | D50: =_xlfn.XLOOKUP(B50,PLANEAMIENTO!A:A,PLANEAMIENTO!D:D) -> 988K | E50: ARMADO | F50: Jimmy Cuba | G50: 2.5 horas | H50: jue 3/10/24 | I50: jue 3/10/24 | J50: 0
B51: 287624 | C51: =_xlfn.XLOOKUP(B51,PLANEAMIENTO!A:A,PLANEAMIENTO!C:C) -> CILINDRO DE BLADELIFT | D51: =_xlfn.XLOOKUP(B51,PLANEAMIENTO!A:A,PLANEAMIENTO!D:D) -> 24 | E51: PULIDO TAPA Y PISTON | F51: Luis Choque | G51: 2.5 horas | H51: jue 3/10/24 | I51: jue 3/10/24 | J51: 0
B52: 287624 | C52: =_xlfn.XLOOKUP(B52,PLANEAMIENTO!A:A,PLANEAMIENTO!C:C) -> CILINDRO DE BLADELIFT | D52: =_xlfn.XLOOKUP(B52,PLANEAMIENTO!A:A,PLANEAMIENTO!D:D) -> 24 | E52: ARMADO | F52: Luis Choque | G52: 2.5 horas | H52: jue 3/10/24 | I52: vie 4/10/24 | J52: 0
B53: 285224 | C53: =_xlfn.XLOOKUP(B53,PLANEAMIENTO!A:A,PLANEAMIENTO!C:C) -> CILINDRO DE INCLINACION DE BULLDOZER | D53: =_xlfn.XLOOKUP(B53,PLANEAMIENTO!A:A,PLANEAMIENTO!D:D) -> D11T | E53: PULIDO TAPA Y PISTON | F53: Jimmy Cuba | G53: 2.5 horas | H53: jue 3/10/24 | I53: jue 3/10/24 | J53: 0
B54: 285224 | C54: =_xlfn.XLOOKUP(B54,PLANEAMIENTO!A:A,PLANEAMIENTO!C:C) -> CILINDRO DE INCLINACION DE BULLDOZER | D54: =_xlfn.XLOOKUP(B54,PLANEAMIENTO!A:A,PLANEAMIENTO!D:D) -> D11T | E54: ARMADO | F54: Jimmy Cuba | G54: 2.5 horas | H54: jue 3/10/24 | I54: vie 4/10/24 | J54: 0
B55: 287024 | C55: =_xlfn.XLOOKUP(B55,PLANEAMIENTO!A:A,PLANEAMIENTO!C:C) -> CILINDRO DE LEVANTE DE BULLDOZER | D55: =_xlfn.XLOOKUP(B55,PLANEAMIENTO!A:A,PLANEAMIENTO!D:D) -> D475 | E55: PULIDO TAPA Y PISTON | F55: Luis Choque | G55: 2.5 horas | H55: vie 4/10/24 | I55: vie 4/10/24 | J55: 0
B56: 287024 | C56: =_xlfn.XLOOKUP(B56,PLANEAMIENTO!A:A,PLANEAMIENTO!C:C) -> CILINDRO DE LEVANTE DE BULLDOZER | D56: =_xlfn.XLOOKUP(B56,PLANEAMIENTO!A:A,PLANEAMIENTO!D:D) -> D475 | E56: ARMADO | F56: Luis Choque | G56: 2.5 horas | H56: vie 4/10/24 | I56: vie 4/10/24 | J56: 0
B57: 285324 | C57: =_xlfn.XLOOKUP(B57,PLANEAMIENTO!A:A,PLANEAMIENTO!C:C) -> CILINDRO DE DIRECCION | D57: =_xlfn.XLOOKUP(B57,PLANEAMIENTO!A:A,PLANEAMIENTO!D:D) -> 24 | E57: PULIDO TAPA Y PISTON | F57: Jimmy Cuba | G57: 2.5 horas | H57: vie 4/10/24 | I57: vie 4/10/24 | J57: 0
B58: Número1 | C58: DESCRIPCION | D58: MODELO | E58: Nombre de tarea | F58: Nombres de los recursos | G58: Duración | H58: Comienzo | I58: Fin | J58: % trabajo completado
B59: 0 | C59: DESCRIPCION | D59: MODELO | E59: TORNO 1 | F59: Gabriel Anco | G59: 8.53 días | H59: lun 30/09/24 | I59: vie 11/10/24 | J59: 0.33
B60: 287824 | C60: =_xlfn.XLOOKUP(B60,PLANEAMIENTO!A:A,PLANEAMIENTO!C:C) -> CILINDRO DE JACK HYD | D60: =_xlfn.XLOOKUP(B60,PLANEAMIENTO!A:A,PLANEAMIENTO!D:D) -> PITVIPER 351 | E60: Corte de tapa de cilindro | F60: Gabriel Anco | G60: 5.5 horas | H60: lun 7/10/24 | I60: lun 7/10/24 | J60: 0
B61: 286624 | C61: =_xlfn.XLOOKUP(B61,PLANEAMIENTO!A:A,PLANEAMIENTO!C:C) -> CILINDRO DE INCLINACION DE BULLDOZER | D61: =_xlfn.XLOOKUP(B61,PLANEAMIENTO!A:A,PLANEAMIENTO!D:D) -> D11T | E61: Rectificado de diámetro de salida y caras de brida (Cilindro) | F61: Gabriel Anco | G61: 4 horas | H61: lun 7/10/24 | I61: mié 9/10/24 | J61: 0
B62: 288324 | C62: =_xlfn.XLOOKUP(B62,PLANEAMIENTO!A:A,PLANEAMIENTO!C:C) -> CILINDRO DE INCLINACION DE BULLDOZER | D62: =_xlfn.XLOOKUP(B62,PLANEAMIENTO!A:A,PLANEAMIENTO!D:D) -> D11T | E62: Corte de cilindro | F62: Gabriel Anco | G62: 6 horas | H62: mié 9/10/24 | I62: jue 10/10/24 | J62: 0
B63: 288324 | C63: =_xlfn.XLOOKUP(B63,PLANEAMIENTO!A:A,PLANEAMIENTO!C:C) -> CILINDRO DE INCLINACION DE BULLDOZER | D63: =_xlfn.XLOOKUP(B63,PLANEAMIENTO!A:A,PLANEAMIENTO!D:D) -> D11T | E63: Maquinado de encastre de cilindro | F63: Gabriel Anco | G63: 8 horas | H63: jue 10/10/24 | I63: jue 10/10/24 | J63: 0
B64: 287924 | C64: =_xlfn.XLOOKUP(B64,PLANEAMIENTO!A:A,PLANEAMIENTO!C:C) -> CILINDRO DE STICK | D64: =_xlfn.XLOOKUP(B64,PLANEAMIENTO!A:A,PLANEAMIENTO!D:D) -> 390DL | E64: Maquinado de soldadura en tapa posterior de cilindro | F64: Gabriel Anco | G64: 1 día | H64: jue 10/10/24 | I64: vie 11/10/24 | J64: 0
B65: 0 | C65: DESCRIPCION | D65: MODELO | E65: TORNO 2 | F65: Rolando Yaique | G65: 8.41 días | H65: mar 1/10/24 | I65: lun 14/10/24 | J65: 0.21
B66: 286024 | C66: =_xlfn.XLOOKUP(B66,PLANEAMIENTO!A:A,PLANEAMIENTO!C:C) -> CILINDRO DE DIRECCION | D66: =_xlfn.XLOOKUP(B66,PLANEAMIENTO!A:A,PLANEAMIENTO!D:D) -> 930E-4SE | E66: Fabricacion de piston | F66: Rolando Yaique | G66: 1 día | H66: vie 4/10/24 | I66: lun 7/10/24 | J66: 0.1
B67: 286024 | C67: =_xlfn.XLOOKUP(B67,PLANEAMIENTO!A:A,PLANEAMIENTO!C:C) -> CILINDRO DE DIRECCION | D67: =_xlfn.XLOOKUP(B67,PLANEAMIENTO!A:A,PLANEAMIENTO!D:D) -> 930E-4SE | E67: Maquinado de barra cromada | F67: Rolando Yaique | G67: 5 horas | H67: lun 7/10/24 | I67: lun 7/10/24 | J67: 0
B68: 286624 | C68: =_xlfn.XLOOKUP(B68,PLANEAMIENTO!A:A,PLANEAMIENTO!C:C) -> CILINDRO DE INCLINACION DE BULLDOZER | D68: =_xlfn.XLOOKUP(B68,PLANEAMIENTO!A:A,PLANEAMIENTO!D:D) -> D11T | E68: Maquinado de barra cromada | F68: Rolando Yaique | G68: 5 horas | H68: lun 7/10/24 | I68: mié 9/10/24 | J68: 0
B69: 285324 | C69: =_xlfn.XLOOKUP(B69,PLANEAMIENTO!A:A,PLANEAMIENTO!C:C) -> CILINDRO DE DIRECCION | D69: =_xlfn.XLOOKUP(B69,PLANEAMIENTO!A:A,PLANEAMIENTO!D:D) -> 24 | E69: Corte de vastago | F69: Rolando Yaique | G69: 3 horas | H69: mié 9/10/24 | I69: mié 9/10/24 | J69: 0
B70: 286624 | C70: =_xlfn.XLOOKUP(B70,PLANEAMIENTO!A:A,PLANEAMIENTO!C:C) -> CILINDRO DE INCLINACION DE BULLDOZER | D70: =_xlfn.XLOOKUP(B70,PLANEAMIENTO!A:A,PLANEAMIENTO!D:D) -> D11T | E70: Maquinado de soldadura de barra cromada | F70: Rolando Yaique | G70: 2 horas | H70: mié 9/10/24 | I70: jue 10/10/24 | J70: 0
B71: 288424 | C71: =_xlfn.XLOOKUP(B71,PLANEAMIENTO!A:A,PLANEAMIENTO!C:C) -> CILINDRO DE ARTICULACION | D71: =_xlfn.XLOOKUP(B71,PLANEAMIENTO!A:A,PLANEAMIENTO!D:D) -> 24 | E71: Corte de cilindro | F71: Rolando Yaique | G71: 8 horas | H71: jue 10/10/24 | I71: vie 11/10/24 | J71: 0
B72: 288424 | C72: =_xlfn.XLOOKUP(B72,PLANEAMIENTO!A:A,PLANEAMIENTO!C:C) -> CILINDRO DE ARTICULACION | D72: =_xlfn.XLOOKUP(B72,PLANEAMIENTO!A:A,PLANEAMIENTO!D:D) -> 24 | E72: Maquinado de encastre de cilindro | F72: Rolando Yaique | G72: 8 horas | H72: vie 11/10/24 | I72: vie 11/10/24 | J72: 0
B73: 288324 | C73: =_xlfn.XLOOKUP(B73,PLANEAMIENTO!A:A,PLANEAMIENTO!C:C) -> CILINDRO DE INCLINACION DE BULLDOZER | D73: =_xlfn.XLOOKUP(B73,PLANEAMIENTO!A:A,PLANEAMIENTO!D:D) -> D11T | E73: Maquinado de diám de salida de cilindro | F73: Rolando Yaique | G73: 6 horas | H73: lun 14/10/24 | I73: lun 14/10/24 | J73: 0
B74: 0 | C74: DESCRIPCION | D74: MODELO | E74: TORNO 3 | F74: Luis Ramos | G74: 9 días? | H74: lun 30/09/24 | I74: lun 14/10/24 | J74: 0.46
B75: 286024 | C75: =_xlfn.XLOOKUP(B75,PLANEAMIENTO!A:A,PLANEAMIENTO!C:C) -> CILINDRO DE DIRECCION | D75: =_xlfn.XLOOKUP(B75,PLANEAMIENTO!A:A,PLANEAMIENTO!D:D) -> 930E-4SE | E75: Fabricación de cáncamo de vástago | F75: Luis Ramos | G75: 1 día | H75: lun 7/10/24 | I75: mié 9/10/24 | J75: 0
B76: 286024 | C76: =_xlfn.XLOOKUP(B76,PLANEAMIENTO!A:A,PLANEAMIENTO!C:C) -> CILINDRO DE DIRECCION | D76: =_xlfn.XLOOKUP(B76,PLANEAMIENTO!A:A,PLANEAMIENTO!D:D) -> 930E-4SE | E76: Maquinado de barra cromada | F76: Luis Ramos | G76: 4.5 horas | H76: mié 9/10/24 | I76: mié 9/10/24 | J76: 0
B77: 288424 | C77: =_xlfn.XLOOKUP(B77,PLANEAMIENTO!A:A,PLANEAMIENTO!C:C) -> CILINDRO DE ARTICULACION | D77: =_xlfn.XLOOKUP(B77,PLANEAMIENTO!A:A,PLANEAMIENTO!D:D) -> 24 | E77: Maquinado de barra cromada | F77: Luis Ramos | G77: 4.5 horas | H77: mié 9/10/24 | I77: jue 10/10/24 | J77: 0
B78: 288424 | C78: =_xlfn.XLOOKUP(B78,PLANEAMIENTO!A:A,PLANEAMIENTO!C:C) -> CILINDRO DE ARTICULACION | D78: =_xlfn.XLOOKUP(B78,PLANEAMIENTO!A:A,PLANEAMIENTO!D:D) -> 24 | E78: Rectificado de alojamiento de Useal tapa | F78: Luis Ramos | G78: 2 horas | H78: jue 10/10/24 | I78: jue 10/10/24 | J78: 0
B79: 289524 | C79: =_xlfn.XLOOKUP(B79,PLANEAMIENTO!A:A,PLANEAMIENTO!C:C) -> CILINDRO DE LEVANTE DE BULLDOZER | D79: =_xlfn.XLOOKUP(B79,PLANEAMIENTO!A:A,PLANEAMIENTO!D:D) -> 844H | E79: Corte de barra cromada | F79: Luis Ramos | G79: 2 horas | H79: jue 10/10/24 | I79: jue 10/10/24 | J79: 0
B80: 289524 | C80: =_xlfn.XLOOKUP(B80,PLANEAMIENTO!A:A,PLANEAMIENTO!C:C) -> CILINDRO DE LEVANTE DE BULLDOZER | D80: =_xlfn.XLOOKUP(B80,PLANEAMIENTO!A:A,PLANEAMIENTO!D:D) -> 844H | E80: Maquinado de barra | F80: Luis Ramos | G80: 5 horas | H80: jue 10/10/24 | I80: vie 11/10/24 | J80: 0
B81: 289624 | C81: =_xlfn.XLOOKUP(B81,PLANEAMIENTO!A:A,PLANEAMIENTO!C:C) -> CILINDRO DE INCLINACION DE BULLDOZER | D81: =_xlfn.XLOOKUP(B81,PLANEAMIENTO!A:A,PLANEAMIENTO!D:D) -> 844K | E81: Maquinado de barra | F81: Luis Ramos | G81: 5 horas | H81: vie 11/10/24 | I81: vie 11/10/24 | J81: 0
B82: 289724 | C82: =_xlfn.XLOOKUP(B82,PLANEAMIENTO!A:A,PLANEAMIENTO!C:C) -> CILINDRO DE STICK | D82: =_xlfn.XLOOKUP(B82,PLANEAMIENTO!A:A,PLANEAMIENTO!D:D) -> 390DL | E82: Maquinado de barra | F82: Luis Ramos | G82: 5 horas | H82: vie 11/10/24 | I82: lun 14/10/24 | J82: 0
B83: 0 | C83: DESCRIPCION | D83: MODELO | E83: FRESA | F83: Jose Huamani | G83: 2.16 días? | H83: vie 4/10/24 | I83: mié 9/10/24 | J83: 0.17
B84: 286624 | C84: =_xlfn.XLOOKUP(B84,PLANEAMIENTO!A:A,PLANEAMIENTO!C:C) -> CILINDRO DE INCLINACION DE BULLDOZER | D84: =_xlfn.XLOOKUP(B84,PLANEAMIENTO!A:A,PLANEAMIENTO!D:D) -> D11T | E84: Barrenado de cilindro | F84: Jose Huamani | G84: 4 horas | H84: lun 7/10/24 | I84: lun 7/10/24 | J84: 0
B85: 287324 | C85: =_xlfn.XLOOKUP(B85,PLANEAMIENTO!A:A,PLANEAMIENTO!C:C) -> CILINDRO DE DIRECCION | D85: =_xlfn.XLOOKUP(B85,PLANEAMIENTO!A:A,PLANEAMIENTO!D:D) -> 24 | E85: Barrenado de cilindro | F85: Jose Huamani | G85: 4 horas | H85: lun 7/10/24 | I85: mié 9/10/24 | J85: 0
B86: 0 | C86: =_xlfn.XLOOKUP(B86,PLANEAMIENTO!A:A,PLANEAMIENTO!C:C) -> #N/A | D86: =_xlfn.XLOOKUP(B86,PLANEAMIENTO!A:A,PLANEAMIENTO!D:D) -> #N/A | G86: 1 día? | H86: lun 7/10/24 | I86: mié 9/10/24 | J86: 0
B87: 0 | C87: DESCRIPCION | D87: MODELO | E87: SOLDADURA 1 | G87: 9.53 días? | H87: lun 30/09/24 | I87: mar 15/10/24 | J87: 0.47
B88: 279624 | C88: =_xlfn.XLOOKUP(B88,PLANEAMIENTO!A:A,PLANEAMIENTO!C:C) -> CILINDRO DE SUSPENSION POSTERIOR | D88: =_xlfn.XLOOKUP(B88,PLANEAMIENTO!A:A,PLANEAMIENTO!D:D) -> 797F | E88: Soldadura encastre de cilindro | F88: Justo Arocutipa | G88: 1.5 días | H88: lun 7/10/24 | I88: mié 9/10/24 | J88: 0
B89: 287824 | C89: =_xlfn.XLOOKUP(B89,PLANEAMIENTO!A:A,PLANEAMIENTO!C:C) -> CILINDRO DE JACK HYD | D89: =_xlfn.XLOOKUP(B89,PLANEAMIENTO!A:A,PLANEAMIENTO!D:D) -> PITVIPER 351 | E89: Soldadura de cáncamo -cilindro | F89: Justo Arocutipa | G89: 1.5 horas | H89: lun 7/10/24 | I89: lun 7/10/24 | J89: 0
B90: 286624 | C90: =_xlfn.XLOOKUP(B90,PLANEAMIENTO!A:A,PLANEAMIENTO!C:C) -> CILINDRO DE INCLINACION DE BULLDOZER | D90: =_xlfn.XLOOKUP(B90,PLANEAMIENTO!A:A,PLANEAMIENTO!D:D) -> D11T | E90: Soldadura de vástago | F90: Justo Arocutipa | G90: 5 horas | H90: mié 9/10/24 | I90: mié 9/10/24 | J90: 0
B91: 288324 | C91: =_xlfn.XLOOKUP(B91,PLANEAMIENTO!A:A,PLANEAMIENTO!C:C) -> CILINDRO DE INCLINACION DE BULLDOZER | D91: =_xlfn.XLOOKUP(B91,PLANEAMIENTO!A:A,PLANEAMIENTO!D:D) -> D11T | E91: Soldadura de cilindro | F91: Justo Arocutipa | G91: 1.3 días | H91: jue 10/10/24 | I91: lun 14/10/24 | J91: 0
B92: 287924 | C92: =_xlfn.XLOOKUP(B92,PLANEAMIENTO!A:A,PLANEAMIENTO!C:C) -> CILINDRO DE STICK | D92: =_xlfn.XLOOKUP(B92,PLANEAMIENTO!A:A,PLANEAMIENTO!D:D) -> 390DL | E92: Soldadura de cilindro | F92: Justo Arocutipa | G92: 1 día | H92: lun 14/10/24 | I92: mar 15/10/24 | J92: 0
B93: 0 | C93: DESCRIPCION | D93: MODELO | E93: SOLDADURA 2 | G93: 5.58 días? | H93: lun 30/09/24 | I93: lun 7/10/24 | J93: 0
B94: 288724 | C94: =_xlfn.XLOOKUP(B94,PLANEAMIENTO!A:A,PLANEAMIENTO!C:C) -> CILINDRO DE BOOM | D94: =_xlfn.XLOOKUP(B94,PLANEAMIENTO!A:A,PLANEAMIENTO!D:D) -> 390DL | E94: Extraer cojinete de cilindro | F94: Victor Caceres | G94: 2 horas | H94: lun 7/10/24 | I94: lun 7/10/24 | J94: 0
B95: 289024 | C95: =_xlfn.XLOOKUP(B95,PLANEAMIENTO!A:A,PLANEAMIENTO!C:C) -> CILINDRO DE LEVANTE DE BULLDOZER | D95: =_xlfn.XLOOKUP(B95,PLANEAMIENTO!A:A,PLANEAMIENTO!D:D) -> 844H | E95: Extraer cojinete de cilindro | F95: Victor Caceres | G95: 2 horas | H95: lun 7/10/24 | I95: lun 7/10/24 | J95: 0
B96: 289624 | C96: =_xlfn.XLOOKUP(B96,PLANEAMIENTO!A:A,PLANEAMIENTO!C:C) -> CILINDRO DE INCLINACION DE BULLDOZER | D96: =_xlfn.XLOOKUP(B96,PLANEAMIENTO!A:A,PLANEAMIENTO!D:D) -> 844K | E96: Extraer cojinete de cilindro | F96: Victor Caceres | G96: 2 horas | H96: lun 7/10/24 | I96: lun 7/10/24 | J96: 0
B97: 289724 | C97: =_xlfn.XLOOKUP(B97,PLANEAMIENTO!A:A,PLANEAMIENTO!C:C) -> CILINDRO DE STICK | D97: =_xlfn.XLOOKUP(B97,PLANEAMIENTO!A:A,PLANEAMIENTO!D:D) -> 390DL | E97: Extraer cojinete de cilindro | F97: Victor Caceres | G97: 2 horas | H97: lun 7/10/24 | I97: lun 7/10/24 | J97: 0
B98: 289024 | C98: =_xlfn.XLOOKUP(B98,PLANEAMIENTO!A:A,PLANEAMIENTO!C:C) -> CILINDRO DE LEVANTE DE BULLDOZER | D98: =_xlfn.XLOOKUP(B98,PLANEAMIENTO!A:A,PLANEAMIENTO!D:D) -> 844H | E98: Relleno de ojo cilindro | F98: Victor Caceres | G98: 1 día? | H98: lun 7/10/24 | I98: mié 9/10/24 | J98: 0
B99: 290624 | C99: =_xlfn.XLOOKUP(B99,PLANEAMIENTO!A:A,PLANEAMIENTO!C:C) -> CILINDRO DE BLADETIP | D99: =_xlfn.XLOOKUP(B99,PLANEAMIENTO!A:A,PLANEAMIENTO!D:D) -> 24M | E99: Relleno de ojo cilindro | F99: Victor Caceres | G99: 1 día? | H99: mié 9/10/24 | I99: jue 10/10/24 | J99: 0
B100: 290724 | C100: =_xlfn.XLOOKUP(B100,PLANEAMIENTO!A:A,PLANEAMIENTO!C:C) -> CILINDRO DE DIRECCION | D100: =_xlfn.XLOOKUP(B100,PLANEAMIENTO!A:A,PLANEAMIENTO!D:D) -> 834K | E100: Extraer cojinete de cilindro | F100: Victor Caceres | G100: 1 hora | H100: jue 10/10/24 | I100: jue 10/10/24 | J100: 0
B101: 290824 | C101: =_xlfn.XLOOKUP(B101,PLANEAMIENTO!A:A,PLANEAMIENTO!C:C) -> CILINDRO DE DIRECCION | D101: =_xlfn.XLOOKUP(B101,PLANEAMIENTO!A:A,PLANEAMIENTO!D:D) -> 834K | E101: Extraer cojinete de cilindro | F101: Victor Caceres | G101: 1 hora | H101: jue 10/10/24 | I101: jue 10/10/24 | J101: 0
...

Sheet Programacion
F2: CRONOGRAMA DE ACTIVIDADES
E4: PROYECTO | F4: TALLER HPK | I4: FECHA ACTUAL | J4: =TODAY() -> 46045 | N4: FECHA INICIO | Q4: 45555 | V4: FECHA FIN | Y4: 45656
M13: 1 | N13: =M13+1 -> 2 | O13: =N13+1 -> 3 | P13: =O13+1 -> 4 | Q13: =P13+1 -> 5 | R13: =Q13+1 -> 6 | S13: =R13+1 -> 7 | T13: =S13+1 -> 8 | U13: =T13+1 -> 9 | ... SX13: =SW13+1 -> 506
E14: CROMOGRAMA | M14: =TEXT(M16,"MMM") -> Set | N14: =IFERROR(IF(MONTH(N16)=MONTH(M16),"",TEXT(N16,"MMM")),"") | O14: =IFERROR(IF(MONTH(O16)=MONTH(N16),"",TEXT(O16,"MMM")),"") | P14: =IFERROR(IF(MONTH(P16)=MONTH(O16),"",TEXT(P16,"MMM")),"") | Q14: =IFERROR(IF(MONTH(Q16)=MONTH(P16),"",TEXT(Q16,"MMM")),"") | R14: =IFERROR(IF(MONTH(R16)=MONTH(Q16),"",TEXT(R16,"MMM")),"") | S14: =IFERROR(IF(MONTH(S16)=MONTH(R16),"",TEXT(S16,"MMM")),"") | T14: =IFERROR(IF(MONTH(T16)=MONTH(S16),"",TEXT(T16,"MMM")),"") -> Oct | U14: =IFERROR(IF(MONTH(U16)=MONTH(T16),"",TEXT(U16,"MMM")),"") | ... SX14: =IFERROR(IF(MONTH(SX16)=MONTH(SW16),"",TEXT(SX16,"MMM")),"")
M15: =TEXT(M16,"ddd") -> vie | N15: =TEXT(N16,"ddd") -> lun | O15: =TEXT(O16,"ddd") -> mar | P15: =TEXT(P16,"ddd") -> mié | Q15: =TEXT(Q16,"ddd") -> jue | R15: =TEXT(R16,"ddd") -> vie | S15: =TEXT(S16,"ddd") -> lun | T15: =TEXT(T16,"ddd") -> mar | ... SX15: =TEXT(SX16,"ddd")
B16: AREA | C16: OT | E16: ACTIVIDADES | F16: RESPONSABLE | G16: FECHA INI | H16: Nº DÍAS | I16: FECHA FIN | J16: AVANCE | K16: ESTADO | M16: 45555 | N16: 45558 | O16: 45559 | P16: 45560 | Q16: 45561 | R16: 45562 | S16: 45565 | T16: 45566 | U16: 45567 | V16: 45568 | W16: 45569 | X16: 45572 | Y16: 45573 | Z16: 45574 | AA16: 45575 | AB16: 45576 | AC16: 45579 | AD16: 45580 | AE16: 45581 | AF16: 45582 | AG16: 45583 | AH16: 45586 | AI16: 45587 | AJ16: 45588 | AK16: 45589 | AL16: 45590 | AM16: 45593 | AN16: 45594 | AO16: 45595 | AP16: 45596 | AQ16: 45597 | AR16: 45600 | AS16: 45601 | AT16: 45602 | AU16: 45603 | AV16: 45604 | AW16: 45607 | AX16: 45608 | AY16: 45609 | AZ16: 45610 | BA16: 45611 | BB16: 45614 | BC16: 45615 | BD16: 45616 | BE16: 45617 | BF16: 45618 | BG16: 45621 | BH16: 45622 | BI16: 45623 | BJ16: 45624 | BK16: 45625 | BL16: 45628 | BM16: 45629 | BN16: 45630 | BO16: 45631 | BP16: 45632 | BQ16: 45635 | BR16: 45636 | BS16: 45637 | BT16: 45638 | BU16: 45639 | BV16: 45642 | BW16: 45643 | BX16: 45644 | BY16: 45645 | BZ16: 45646 | CA16: 45649 | CB16: 45650 | CC16: 45651 | CD16: 45652 | CE16: 45653 | CF16: 45656
E18: MAQUINADO
B19: TORNO 1 | C19: 273924 | D19: 1 | E19: Maquinado de encastre de cilindro y medida final OD | F19: Gabriel Anco | G19: 45565 | H19: 1 | I19: =(G19+H19)-1 -> 45565 | J19: 1 | K19: Completado | M19: =IF($J19>0%,IF(AND(M$16>=$G19,M$16<$G19+($H19*$J19)),"➤",""),"") | N19: =IF($J19>0%,IF(AND(N$16>=$G19,N$16<$G19+($H19*$J19)),"➤",""),"") | O19: =IF($J19>0%,IF(AND(O$16>=$G19,O$16<$G19+($H19*$J19)),"➤",""),"") | P19: =IF($J19>0%,IF(AND(P$16>=$G19,P$16<$G19+($H19*$J19)),"➤",""),"") | Q19: =IF($J19>0%,IF(AND(Q$16>=$G19,Q$16<$G19+($H19*$J19)),"➤",""),"") | R19: =IF($J19>0%,IF(AND(R$16>=$G19,R$16<$G19+($H19*$J19)),"➤",""),"") | S19: =IF($J19>0%,IF(AND(S$16>=$G19,S$16<$G19+($H19*$J19)),"➤",""),"") -> ➤ | T19: =IF($J19>0%,IF(AND(T$16>=$G19,T$16<$G19+($H19*$J19)),"➤",""),"") | ... SX19: =IF($J19>0%,IF(AND(SX$16>=$G19,SX$16<$G19+($H19*$J19)),"➤",""),"")
C20: 288724 | D20: 1 | E20: Maquinado de espiga | F20: Gabriel Anco | G20: 45566 | H20: 2 | I20: =(G20+H20)-1 -> 45567 | J20: 0.6 | K20: En Proceso | M20: =IF($J20>0%,IF(AND(M$16>=$G20,M$16<$G20+($H20*$J20)),"➤",""),"") | N20: =IF($J20>0%,IF(AND(N$16>=$G20,N$16<$G20+($H20*$J20)),"➤",""),"") | O20: =IF($J20>0%,IF(AND(O$16>=$G20,O$16<$G20+($H20*$J20)),"➤",""),"") | P20: =IF($J20>0%,IF(AND(P$16>=$G20,P$16<$G20+($H20*$J20)),"➤",""),"") | Q20: =IF($J20>0%,IF(AND(Q$16>=$G20,Q$16<$G20+($H20*$J20)),"➤",""),"") | R20: =IF($J20>0%,IF(AND(R$16>=$G20,R$16<$G20+($H20*$J20)),"➤",""),"") | S20: =IF($J20>0%,IF(AND(S$16>=$G20,S$16<$G20+($H20*$J20)),"➤",""),"") | T20: =IF($J20>0%,IF(AND(T$16>=$G20,T$16<$G20+($H20*$J20)),"➤",""),"") -> ➤ | ... SX20: =IF($J20>0%,IF(AND(SX$16>=$G20,SX$16<$G20+($H20*$J20)),"➤",""),"")
C21: 285724 | D21: 1 | E21: Maquinado de soldadura de tapa posterior de cilindro | F21: Gabriel Anco | G21: 45567 | H21: 1 | I21: =(G21+H21)-1 -> 45567 | J21: 0 | K21: Sin Empezar | M21: =IF($J21>0%,IF(AND(M$16>=$G21,M$16<$G21+($H21*$J21)),"➤",""),"") | N21: =IF($J21>0%,IF(AND(N$16>=$G21,N$16<$G21+($H21*$J21)),"➤",""),"") | O21: =IF($J21>0%,IF(AND(O$16>=$G21,O$16<$G21+($H21*$J21)),"➤",""),"") | P21: =IF($J21>0%,IF(AND(P$16>=$G21,P$16<$G21+($H21*$J21)),"➤",""),"") | Q21: =IF($J21>0%,IF(AND(Q$16>=$G21,Q$16<$G21+($H21*$J21)),"➤",""),"") | R21: =IF($J21>0%,IF(AND(R$16>=$G21,R$16<$G21+($H21*$J21)),"➤",""),"") | S21: =IF($J21>0%,IF(AND(S$16>=$G21,S$16<$G21+($H21*$J21)),"➤",""),"") | T21: =IF($J21>0%,IF(AND(T$16>=$G21,T$16<$G21+($H21*$J21)),"➤",""),"") | ... SX21: =IF($J21>0%,IF(AND(SX$16>=$G21,SX$16<$G21+($H21*$J21)),"➤",""),"")
C22: 285724 | D22: 1 | E22: Montaje de cilindro con tapa posterior para soldadura | F22: Gabriel Anco | G22: 45567 | H22: 1 | I22: =(G22+H22)-1 -> 45567 | J22: 0 | K22: Sin Empezar | M22: =IF($J22>0%,IF(AND(M$16>=$G22,M$16<$G22+($H22*$J22)),"➤",""),"") | N22: =IF($J22>0%,IF(AND(N$16>=$G22,N$16<$G22+($H22*$J22)),"➤",""),"") | O22: =IF($J22>0%,IF(AND(O$16>=$G22,O$16<$G22+($H22*$J22)),"➤",""),"") | P22: =IF($J22>0%,IF(AND(P$16>=$G22,P$16<$G22+($H22*$J22)),"➤",""),"") | Q22: =IF($J22>0%,IF(AND(Q$16>=$G22,Q$16<$G22+($H22*$J22)),"➤",""),"") | R22: =IF($J22>0%,IF(AND(R$16>=$G22,R$16<$G22+($H22*$J22)),"➤",""),"") | S22: =IF($J22>0%,IF(AND(S$16>=$G22,S$16<$G22+($H22*$J22)),"➤",""),"") | T22: =IF($J22>0%,IF(AND(T$16>=$G22,T$16<$G22+($H22*$J22)),"➤",""),"") | ... SX22: =IF($J22>0%,IF(AND(SX$16>=$G22,SX$16<$G22+($H22*$J22)),"➤",""),"")
C23: 286624 | D23: 1 | E23: Maquinado de barra cromada | F23: Gabriel Anco | G23: 45568 | H23: 1 | I23: =(G23+H23)-1 -> 45568 | J23: 0 | K23: Sin Empezar | M23: =IF($J23>0%,IF(AND(M$16>=$G23,M$16<$G23+($H23*$J23)),"➤",""),"") | N23: =IF($J23>0%,IF(AND(N$16>=$G23,N$16<$G23+($H23*$J23)),"➤",""),"") | O23: =IF($J23>0%,IF(AND(O$16>=$G23,O$16<$G23+($H23*$J23)),"➤",""),"") | P23: =IF($J23>0%,IF(AND(P$16>=$G23,P$16<$G23+($H23*$J23)),"➤",""),"") | Q23: =IF($J23>0%,IF(AND(Q$16>=$G23,Q$16<$G23+($H23*$J23)),"➤",""),"") | R23: =IF($J23>0%,IF(AND(R$16>=$G23,R$16<$G23+($H23*$J23)),"➤",""),"") | S23: =IF($J23>0%,IF(AND(S$16>=$G23,S$16<$G23+($H23*$J23)),"➤",""),"") | T23: =IF($J23>0%,IF(AND(T$16>=$G23,T$16<$G23+($H23*$J23)),"➤",""),"") | ... SX23: =IF($J23>0%,IF(AND(SX$16>=$G23,SX$16<$G23+($H23*$J23)),"➤",""),"")
C24: 289224 | E24: Fabricar planchas escalonadas | F24: Gabriel Anco | G24: 45568 | H24: 1 | I24: =(G24+H24)-1 -> 45568 | J24: 0 | K24: Sin Empezar | M24: =IF($J24>0%,IF(AND(M$16>=$G24,M$16<$G24+($H24*$J24)),"➤",""),"") | N24: =IF($J24>0%,IF(AND(N$16>=$G24,N$16<$G24+($H24*$J24)),"➤",""),"") | O24: =IF($J24>0%,IF(AND(O$16>=$G24,O$16<$G24+($H24*$J24)),"➤",""),"") | P24: =IF($J24>0%,IF(AND(P$16>=$G24,P$16<$G24+($H24*$J24)),"➤",""),"") | Q24: =IF($J24>0%,IF(AND(Q$16>=$G24,Q$16<$G24+($H24*$J24)),"➤",""),"") | R24: =IF($J24>0%,IF(AND(R$16>=$G24,R$16<$G24+($H24*$J24)),"➤",""),"") | S24: =IF($J24>0%,IF(AND(S$16>=$G24,S$16<$G24+($H24*$J24)),"➤",""),"") | T24: =IF($J24>0%,IF(AND(T$16>=$G24,T$16<$G24+($H24*$J24)),"➤",""),"") | ... SX24: =IF($J24>0%,IF(AND(SX$16>=$G24,SX$16<$G24+($H24*$J24)),"➤",""),"")
B25: TORNO 2 | C25: 286624 | E25: Corte de cilindro | F25: Rolando Yaique | G25: 45565 | H25: 1 | I25: =(G25+H25)-1 -> 45565 | J25: 1 | K25: Completado | M25: =IF($J25>0%,IF(AND(M$16>=$G25,M$16<$G25+($H25*$J25)),"➤",""),"") | N25: =IF($J25>0%,IF(AND(N$16>=$G25,N$16<$G25+($H25*$J25)),"➤",""),"") | O25: =IF($J25>0%,IF(AND(O$16>=$G25,O$16<$G25+($H25*$J25)),"➤",""),"") | P25: =IF($J25>0%,IF(AND(P$16>=$G25,P$16<$G25+($H25*$J25)),"➤",""),"") | Q25: =IF($J25>0%,IF(AND(Q$16>=$G25,Q$16<$G25+($H25*$J25)),"➤",""),"") | R25: =IF($J25>0%,IF(AND(R$16>=$G25,R$16<$G25+($H25*$J25)),"➤",""),"") | S25: =IF($J25>0%,IF(AND(S$16>=$G25,S$16<$G25+($H25*$J25)),"➤",""),"") -> ➤ | T25: =IF($J25>0%,IF(AND(T$16>=$G25,T$16<$G25+($H25*$J25)),"➤",""),"") | ... SX25: =IF($J25>0%,IF(AND(SX$16>=$G25,SX$16<$G25+($H25*$J25)),"➤",""),"")
C26: 284724 | E26: Rectificado de diámetro de salida | F26: Rolando Yaique | G26: 45565 | H26: 1 | I26: =(G26+H26)-1 -> 45565 | J26: 1 | K26: Completado | M26: =IF($J26>0%,IF(AND(M$16>=$G26,M$16<$G26+($H26*$J26)),"➤",""),"") | N26: =IF($J26>0%,IF(AND(N$16>=$G26,N$16<$G26+($H26*$J26)),"➤",""),"") | O26: =IF($J26>0%,IF(AND(O$16>=$G26,O$16<$G26+($H26*$J26)),"➤",""),"") | P26: =IF($J26>0%,IF(AND(P$16>=$G26,P$16<$G26+($H26*$J26)),"➤",""),"") | Q26: =IF($J26>0%,IF(AND(Q$16>=$G26,Q$16<$G26+($H26*$J26)),"➤",""),"") | R26: =IF($J26>0%,IF(AND(R$16>=$G26,R$16<$G26+($H26*$J26)),"➤",""),"") | S26: =IF($J26>0%,IF(AND(S$16>=$G26,S$16<$G26+($H26*$J26)),"➤",""),"") -> ➤ | T26: =IF($J26>0%,IF(AND(T$16>=$G26,T$16<$G26+($H26*$J26)),"➤",""),"") | ... SX26: =IF($J26>0%,IF(AND(SX$16>=$G26,SX$16<$G26+($H26*$J26)),"➤",""),"")
C27: 286624 | E27: Maquinado de encastre de cilindro y medida final OD | F27: Rolando Yaique | G27: 45566 | H27: 2 | I27: =(G27+H27)-1 -> 45567 | J27: 1 | K27: Completado | M27: =IF($J27>0%,IF(AND(M$16>=$G27,M$16<$G27+($H27*$J27)),"➤",""),"") | N27: =IF($J27>0%,IF(AND(N$16>=$G27,N$16<$G27+($H27*$J27)),"➤",""),"") | O27: =IF($J27>0%,IF(AND(O$16>=$G27,O$16<$G27+($H27*$J27)),"➤",""),"") | P27: =IF($J27>0%,IF(AND(P$16>=$G27,P$16<$G27+($H27*$J27)),"➤",""),"") | Q27: =IF($J27>0%,IF(AND(Q$16>=$G27,Q$16<$G27+($H27*$J27)),"➤",""),"") | R27: =IF($J27>0%,IF(AND(R$16>=$G27,R$16<$G27+($H27*$J27)),"➤",""),"") | S27: =IF($J27>0%,IF(AND(S$16>=$G27,S$16<$G27+($H27*$J27)),"➤",""),"") | T27: =IF($J27>0%,IF(AND(T$16>=$G27,T$16<$G27+($H27*$J27)),"➤",""),"") -> ➤ | ... SX27: =IF($J27>0%,IF(AND(SX$16>=$G27,SX$16<$G27+($H27*$J27)),"➤",""),"")
C28: 288024 | E28: Fabricacion de cojinete | F28: Rolando Yaique | G28: 45566 | H28: 2 | I28: =(G28+H28)-1 -> 45567 | J28: 0 | K28: En Proceso | M28: =IF($J28>0%,IF(AND(M$16>=$G28,M$16<$G28+($H28*$J28)),"➤",""),"") | N28: =IF($J28>0%,IF(AND(N$16>=$G28,N$16<$G28+($H28*$J28)),"➤",""),"") | O28: =IF($J28>0%,IF(AND(O$16>=$G28,O$16<$G28+($H28*$J28)),"➤",""),"") | P28: =IF($J28>0%,IF(AND(P$16>=$G28,P$16<$G28+($H28*$J28)),"➤",""),"") | Q28: =IF($J28>0%,IF(AND(Q$16>=$G28,Q$16<$G28+($H28*$J28)),"➤",""),"") | R28: =IF($J28>0%,IF(AND(R$16>=$G28,R$16<$G28+($H28*$J28)),"➤",""),"") | S28: =IF($J28>0%,IF(AND(S$16>=$G28,S$16<$G28+($H28*$J28)),"➤",""),"") | T28: =IF($J28>0%,IF(AND(T$16>=$G28,T$16<$G28+($H28*$J28)),"➤",""),"") | ... SX28: =IF($J28>0%,IF(AND(SX$16>=$G28,SX$16<$G28+($H28*$J28)),"➤",""),"")
C29: 288324 | E29: Corte cilindro | F29: Rolando Yaique | G29: 45567 | H29: 1 | I29: =(G29+H29)-1 -> 45567 | J29: 0 | K29: Sin Empezar | M29: =IF($J29>0%,IF(AND(M$16>=$G29,M$16<$G29+($H29*$J29)),"➤",""),"") | N29: =IF($J29>0%,IF(AND(N$16>=$G29,N$16<$G29+($H29*$J29)),"➤",""),"") | O29: =IF($J29>0%,IF(AND(O$16>=$G29,O$16<$G29+($H29*$J29)),"➤",""),"") | P29: =IF($J29>0%,IF(AND(P$16>=$G29,P$16<$G29+($H29*$J29)),"➤",""),"") | Q29: =IF($J29>0%,IF(AND(Q$16>=$G29,Q$16<$G29+($H29*$J29)),"➤",""),"") | R29: =IF($J29>0%,IF(AND(R$16>=$G29,R$16<$G29+($H29*$J29)),"➤",""),"") | S29: =IF($J29>0%,IF(AND(S$16>=$G29,S$16<$G29+($H29*$J29)),"➤",""),"") | T29: =IF($J29>0%,IF(AND(T$16>=$G29,T$16<$G29+($H29*$J29)),"➤",""),"") | ... SX29: =IF($J29>0%,IF(AND(SX$16>=$G29,SX$16<$G29+($H29*$J29)),"➤",""),"")
C30: 288324 | E30: Maquinado de encastre | F30: Rolando Yaique | G30: 45568 | H30: 1 | I30: =(G30+H30)-1 -> 45568 | J30: 0 | K30: Sin Empezar | M30: =IF($J30>0%,IF(AND(M$16>=$G30,M$16<$G30+($H30*$J30)),"➤",""),"") | N30: =IF($J30>0%,IF(AND(N$16>=$G30,N$16<$G30+($H30*$J30)),"➤",""),"") | O30: =IF($J30>0%,IF(AND(O$16>=$G30,O$16<$G30+($H30*$J30)),"➤",""),"") | P30: =IF($J30>0%,IF(AND(P$16>=$G30,P$16<$G30+($H30*$J30)),"➤",""),"") | Q30: =IF($J30>0%,IF(AND(Q$16>=$G30,Q$16<$G30+($H30*$J30)),"➤",""),"") | R30: =IF($J30>0%,IF(AND(R$16>=$G30,R$16<$G30+($H30*$J30)),"➤",""),"") | S30: =IF($J30>0%,IF(AND(S$16>=$G30,S$16<$G30+($H30*$J30)),"➤",""),"") | T30: =IF($J30>0%,IF(AND(T$16>=$G30,T$16<$G30+($H30*$J30)),"➤",""),"") | ... SX30: =IF($J30>0%,IF(AND(SX$16>=$G30,SX$16<$G30+($H30*$J30)),"➤",""),"")
M32: =IF($J32>0%,IF(AND(M$16>=$G32,M$16<$G32+($H32*$J32)),"➤",""),"") | N32: =IF($J32>0%,IF(AND(N$16>=$G32,N$16<$G32+($H32*$J32)),"➤",""),"") | O32: =IF($J32>0%,IF(AND(O$16>=$G32,O$16<$G32+($H32*$J32)),"➤",""),"") | P32: =IF($J32>0%,IF(AND(P$16>=$G32,P$16<$G32+($H32*$J32)),"➤",""),"") | Q32: =IF($J32>0%,IF(AND(Q$16>=$G32,Q$16<$G32+($H32*$J32)),"➤",""),"") | R32: =IF($J32>0%,IF(AND(R$16>=$G32,R$16<$G32+($H32*$J32)),"➤",""),"") | S32: =IF($J32>0%,IF(AND(S$16>=$G32,S$16<$G32+($H32*$J32)),"➤",""),"") | T32: =IF($J32>0%,IF(AND(T$16>=$G32,T$16<$G32+($H32*$J32)),"➤",""),"") | ... SX32: =IF($J32>0%,IF(AND(SX$16>=$G32,SX$16<$G32+($H32*$J32)),"➤",""),"")
B33: TORNO 3 | C33: 287024 | E33: Corte de barra - cancamo | F33: Luis Ramos | G33: 45565 | H33: 1 | I33: =(G33+H33)-1 -> 45565 | J33: 1 | K33: Completado | M33: =IF($J33>0%,IF(AND(M$16>=$G33,M$16<$G33+($H33*$J33)),"➤",""),"") | N33: =IF($J33>0%,IF(AND(N$16>=$G33,N$16<$G33+($H33*$J33)),"➤",""),"") | O33: =IF($J33>0%,IF(AND(O$16>=$G33,O$16<$G33+($H33*$J33)),"➤",""),"") | P33: =IF($J33>0%,IF(AND(P$16>=$G33,P$16<$G33+($H33*$J33)),"➤",""),"") | Q33: =IF($J33>0%,IF(AND(Q$16>=$G33,Q$16<$G33+($H33*$J33)),"➤",""),"") | R33: =IF($J33>0%,IF(AND(R$16>=$G33,R$16<$G33+($H33*$J33)),"➤",""),"") | S33: =IF($J33>0%,IF(AND(S$16>=$G33,S$16<$G33+($H33*$J33)),"➤",""),"") -> ➤ | T33: =IF($J33>0%,IF(AND(T$16>=$G33,T$16<$G33+($H33*$J33)),"➤",""),"") | ... SX33: =IF($J33>0%,IF(AND(SX$16>=$G33,SX$16<$G33+($H33*$J33)),"➤",""),"")
C34: 287024 | E34: Maquinado de vástago | F34: Luis Ramos | G34: 45565 | H34: 1 | I34: =(G34+H34)-1 -> 45565 | J34: 1 | K34: Completado | M34: =IF($J34>0%,IF(AND(M$16>=$G34,M$16<$G34+($H34*$J34)),"➤",""),"") | N34: =IF($J34>0%,IF(AND(N$16>=$G34,N$16<$G34+($H34*$J34)),"➤",""),"") | O34: =IF($J34>0%,IF(AND(O$16>=$G34,O$16<$G34+($H34*$J34)),"➤",""),"") | P34: =IF($J34>0%,IF(AND(P$16>=$G34,P$16<$G34+($H34*$J34)),"➤",""),"") | Q34: =IF($J34>0%,IF(AND(Q$16>=$G34,Q$16<$G34+($H34*$J34)),"➤",""),"") | R34: =IF($J34>0%,IF(AND(R$16>=$G34,R$16<$G34+($H34*$J34)),"➤",""),"") | S34: =IF($J34>0%,IF(AND(S$16>=$G34,S$16<$G34+($H34*$J34)),"➤",""),"") -> ➤ | T34: =IF($J34>0%,IF(AND(T$16>=$G34,T$16<$G34+($H34*$J34)),"➤",""),"") | ... AF34: =IF($J34>0%,IF(AND(AF$16>=$G34,AF$16<$G34+($H34*$J34)),"➤",""),"") | AG34: =IF($J34>0%,IF(AND(AG$16>=$G37,AG$16<$G37+($H34*$J34)),"➤",""),"") | AH34: =IF($J34>0%,IF(AND(AH$16>=$G37,AH$16<$G37+($H34*$J34)),"➤",""),"") | AI34: =IF($J34>0%,IF(AND(AI$16>=$G37,AI$16<$G37+($H34*$J34)),"➤",""),"") | AJ34: =IF($J34>0%,IF(AND(AJ$16>=$G37,AJ$16<$G37+($H34*$J34)),"➤",""),"") | AK34: =IF($J34>0%,IF(AND(AK$16>=$G37,AK$16<$G37+($H34*$J34)),"➤",""),"") | AL34: =IF($J34>0%,IF(AND(AL$16>=$G37,AL$16<$G37+($H34*$J34)),"➤",""),"") | AM34: =IF($J34>0%,IF(AND(AM$16>=$G37,AM$16<$G37+($H34*$J34)),"➤",""),"") | AN34: =IF($J34>0%,IF(AND(AN$16>=$G37,AN$16<$G37+($H34*$J34)),"➤",""),"") | ... SX34: =IF($J34>0%,IF(AND(SX$16>=$G37,SX$16<$G37+($H34*$J34)),"➤",""),"")
C35: 285324 | E35: Maquinado de rosca de tapa | F35: Luis Ramos | G35: 45566 | H35: 1 | I35: =(G35+H35)-1 -> 45566 | J35: 1 | K35: Completado | M35: =IF($J35>0%,IF(AND(M$16>=$G35,M$16<$G35+($H35*$J35)),"➤",""),"") | N35: =IF($J35>0%,IF(AND(N$16>=$G35,N$16<$G35+($H35*$J35)),"➤",""),"") | O35: =IF($J35>0%,IF(AND(O$16>=$G35,O$16<$G35+($H35*$J35)),"➤",""),"") | P35: =IF($J35>0%,IF(AND(P$16>=$G35,P$16<$G35+($H35*$J35)),"➤",""),"") | Q35: =IF($J35>0%,IF(AND(Q$16>=$G35,Q$16<$G35+($H35*$J35)),"➤",""),"") | R35: =IF($J35>0%,IF(AND(R$16>=$G35,R$16<$G35+($H35*$J35)),"➤",""),"") | S35: =IF($J35>0%,IF(AND(S$16>=$G35,S$16<$G35+($H35*$J35)),"➤",""),"") | T35: =IF($J35>0%,IF(AND(T$16>=$G35,T$16<$G35+($H35*$J35)),"➤",""),"") -> ➤ | ... AF35: =IF($J35>0%,IF(AND(AF$16>=$G35,AF$16<$G35+($H35*$J35)),"➤",""),"") | AG35: =IF($J35>0%,IF(AND(AG$16>=$G39,AG$16<$G39+($H35*$J35)),"➤",""),"") | AH35: =IF($J35>0%,IF(AND(AH$16>=$G39,AH$16<$G39+($H35*$J35)),"➤",""),"") | AI35: =IF($J35>0%,IF(AND(AI$16>=$G39,AI$16<$G39+($H35*$J35)),"➤",""),"") | AJ35: =IF($J35>0%,IF(AND(AJ$16>=$G39,AJ$16<$G39+($H35*$J35)),"➤",""),"") | AK35: =IF($J35>0%,IF(AND(AK$16>=$G39,AK$16<$G39+($H35*$J35)),"➤",""),"") | AL35: =IF($J35>0%,IF(AND(AL$16>=$G39,AL$16<$G39+($H35*$J35)),"➤",""),"") | AM35: =IF($J35>0%,IF(AND(AM$16>=$G39,AM$16<$G39+($H35*$J35)),"➤",""),"") | AN35: =IF($J35>0%,IF(AND(AN$16>=$G39,AN$16<$G39+($H35*$J35)),"➤",""),"") | ... SX35: =IF($J35>0%,IF(AND(SX$16>=$G39,SX$16<$G39+($H35*$J35)),"➤",""),"")
C36: 288024 | E36: Maquinado de bocinas | F36: Luis Ramos | G36: 45566 | H36: 2 | I36: =(G36+H36)-1 -> 45567 | J36: 0.25 | K36: En Proceso | M36: =IF($J36>0%,IF(AND(M$16>=$G39,M$16<$G39+($H36*$J36)),"➤",""),"") | N36: =IF($J36>0%,IF(AND(N$16>=$G39,N$16<$G39+($H36*$J36)),"➤",""),"") | O36: =IF($J36>0%,IF(AND(O$16>=$G39,O$16<$G39+($H36*$J36)),"➤",""),"") | P36: =IF($J36>0%,IF(AND(P$16>=$G39,P$16<$G39+($H36*$J36)),"➤",""),"") | Q36: =IF($J36>0%,IF(AND(Q$16>=$G39,Q$16<$G39+($H36*$J36)),"➤",""),"") | R36: =IF($J36>0%,IF(AND(R$16>=$G39,R$16<$G39+($H36*$J36)),"➤",""),"") | S36: =IF($J36>0%,IF(AND(S$16>=$G36,S$16<$G36+($H36*$J36)),"➤",""),"") | T36: =IF($J36>0%,IF(AND(T$16>=$G36,T$16<$G36+($H36*$J36)),"➤",""),"") -> ➤ | U36: =IF($J36>0%,IF(AND(U$16>=$G36,U$16<$G36+($H36*$J36)),"➤",""),"") | V36: =IF($J36>0%,IF(AND(V$16>=$G36,V$16<$G36+($H36*$J36)),"➤",""),"") | W36: =IF($J36>0%,IF(AND(W$16>=$G36,W$16<$G36+($H36*$J36)),"➤",""),"") | X36: =IF($J36>0%,IF(AND(X$16>=$G36,X$16<$G36+($H36*$J36)),"➤",""),"") | Y36: =IF($J36>0%,IF(AND(Y$16>=$G36,Y$16<$G36+($H36*$J36)),"➤",""),"") | Z36: =IF($J36>0%,IF(AND(Z$16>=$G36,Z$16<$G36+($H36*$J36)),"➤",""),"") | ... AF36: =IF($J36>0%,IF(AND(AF$16>=$G36,AF$16<$G36+($H36*$J36)),"➤",""),"") | AG36: =IF($J36>0%,IF(AND(AG$16>=$G39,AG$16<$G39+($H36*$J36)),"➤",""),"") | AH36: =IF($J36>0%,IF(AND(AH$16>=$G39,AH$16<$G39+($H36*$J36)),"➤",""),"") | AI36: =IF($J36>0%,IF(AND(AI$16>=$G39,AI$16<$G39+($H36*$J36)),"➤",""),"") | AJ36: =IF($J36>0%,IF(AND(AJ$16>=$G39,AJ$16<$G39+($H36*$J36)),"➤",""),"") | AK36: =IF($J36>0%,IF(AND(AK$16>=$G39,AK$16<$G39+($H36*$J36)),"➤",""),"") | AL36: =IF($J36>0%,IF(AND(AL$16>=$G39,AL$16<$G39+($H36*$J36)),"➤",""),"") | AM36: =IF($J36>0%,IF(AND(AM$16>=$G39,AM$16<$G39+($H36*$J36)),"➤",""),"") | AN36: =IF($J36>0%,IF(AND(AN$16>=$G39,AN$16<$G39+($H36*$J36)),"➤",""),"") | ... SX36: =IF($J36>0%,IF(AND(SX$16>=$G39,SX$16<$G39+($H36*$J36)),"➤",""),"")
C37: 287024 | E37: Maquinado de bocinas | F37: Luis Ramos | G37: 45568 | H37: 2 | I37: =(G37+H37)-1 -> 45569 | J37: 0 | K37: Sin Empezar | M37: =IF($J37>0%,IF(AND(M$16>=$G40,M$16<$G40+($H37*$J37)),"➤",""),"") | N37: =IF($J37>0%,IF(AND(N$16>=$G40,N$16<$G40+($H37*$J37)),"➤",""),"") | O37: =IF($J37>0%,IF(AND(O$16>=$G40,O$16<$G40+($H37*$J37)),"➤",""),"") | P37: =IF($J37>0%,IF(AND(P$16>=$G40,P$16<$G40+($H37*$J37)),"➤",""),"") | Q37: =IF($J37>0%,IF(AND(Q$16>=$G40,Q$16<$G40+($H37*$J37)),"➤",""),"") | R37: =IF($J37>0%,IF(AND(R$16>=$G40,R$16<$G40+($H37*$J37)),"➤",""),"") | S37: =IF($J37>0%,IF(AND(S$16>=$G37,S$16<$G37+($H37*$J37)),"➤",""),"") | T37: =IF($J37>0%,IF(AND(T$16>=$G37,T$16<$G37+($H37*$J37)),"➤",""),"") | U37: =IF($J37>0%,IF(AND(U$16>=$G37,U$16<$G37+($H37*$J37)),"➤",""),"") | V37: =IF($J37>0%,IF(AND(V$16>=$G37,V$16<$G37+($H37*$J37)),"➤",""),"") | W37: =IF($J37>0%,IF(AND(W$16>=$G37,W$16<$G37+($H37*$J37)),"➤",""),"") | X37: =IF($J37>0%,IF(AND(X$16>=$G37,X$16<$G37+($H37*$J37)),"➤",""),"") | Y37: =IF($J37>0%,IF(AND(Y$16>=$G37,Y$16<$G37+($H37*$J37)),"➤",""),"") | Z37: =IF($J37>0%,IF(AND(Z$16>=$G37,Z$16<$G37+($H37*$J37)),"➤",""),"") | ... AF37: =IF($J37>0%,IF(AND(AF$16>=$G37,AF$16<$G37+($H37*$J37)),"➤",""),"") | AG37: =IF($J37>0%,IF(AND(AG$16>=$G40,AG$16<$G40+($H37*$J37)),"➤",""),"") | AH37: =IF($J37>0%,IF(AND(AH$16>=$G40,AH$16<$G40+($H37*$J37)),"➤",""),"") | AI37: =IF($J37>0%,IF(AND(AI$16>=$G40,AI$16<$G40+($H37*$J37)),"➤",""),"") | AJ37: =IF($J37>0%,IF(AND(AJ$16>=$G40,AJ$16<$G40+($H37*$J37)),"➤",""),"") | AK37: =IF($J37>0%,IF(AND(AK$16>=$G40,AK$16<$G40+($H37*$J37)),"➤",""),"") | AL37: =IF($J37>0%,IF(AND(AL$16>=$G40,AL$16<$G40+($H37*$J37)),"➤",""),"") | AM37: =IF($J37>0%,IF(AND(AM$16>=$G40,AM$16<$G40+($H37*$J37)),"➤",""),"") | AN37: =IF($J37>0%,IF(AND(AN$16>=$G40,AN$16<$G40+($H37*$J37)),"➤",""),"") | ... SX37: =IF($J37>0%,IF(AND(SX$16>=$G40,SX$16<$G40+($H37*$J37)),"➤",""),"")
C38: 287324 | E38: Corte de cilindro | F38: Luis Ramos | G38: 45569 | H38: 1 | I38: =(G38+H38)-1 -> 45569 | J38: 0 | K38: Sin Empezar | M38: =IF($J38>0%,IF(AND(M$16>=$G38,M$16<$G38+($H38*$J38)),"➤",""),"") | N38: =IF($J38>0%,IF(AND(N$16>=$G38,N$16<$G38+($H38*$J38)),"➤",""),"") | O38: =IF($J38>0%,IF(AND(O$16>=$G38,O$16<$G38+($H38*$J38)),"➤",""),"") | P38: =IF($J38>0%,IF(AND(P$16>=$G38,P$16<$G38+($H38*$J38)),"➤",""),"") | Q38: =IF($J38>0%,IF(AND(Q$16>=$G38,Q$16<$G38+($H38*$J38)),"➤",""),"") | R38: =IF($J38>0%,IF(AND(R$16>=$G38,R$16<$G38+($H38*$J38)),"➤",""),"") | S38: =IF($J38>0%,IF(AND(S$16>=$G38,S$16<$G38+($H38*$J38)),"➤",""),"") | T38: =IF($J38>0%,IF(AND(T$16>=$G38,T$16<$G38+($H38*$J38)),"➤",""),"") | ... SX38: =IF($J38>0%,IF(AND(SX$16>=$G38,SX$16<$G38+($H38*$J38)),"➤",""),"")
C39: 287324 | E39: Maquinado de encastre de cilindro y medida final OD | F39: Luis Ramos | G39: 45569 | H39: 1 | I39: =(G39+H39)-1 -> 45569 | J39: 0 | K39: Sin Empezar | M39: =IF($J39>0%,IF(AND(M$16>=$G39,M$16<$G39+($H39*$J39)),"➤",""),"") | N39: =IF($J39>0%,IF(AND(N$16>=$G39,N$16<$G39+($H39*$J39)),"➤",""),"") | O39: =IF($J39>0%,IF(AND(O$16>=$G39,O$16<$G39+($H39*$J39)),"➤",""),"") | P39: =IF($J39>0%,IF(AND(P$16>=$G39,P$16<$G39+($H39*$J39)),"➤",""),"") | Q39: =IF($J39>0%,IF(AND(Q$16>=$G39,Q$16<$G39+($H39*$J39)),"➤",""),"") | R39: =IF($J39>0%,IF(AND(R$16>=$G39,R$16<$G39+($H39*$J39)),"➤",""),"") | S39: =IF($J39>0%,IF(AND(S$16>=$G39,S$16<$G39+($H39*$J39)),"➤",""),"") | T39: =IF($J39>0%,IF(AND(T$16>=$G39,T$16<$G39+($H39*$J39)),"➤",""),"") | ... SX39: =IF($J39>0%,IF(AND(SX$16>=$G39,SX$16<$G39+($H39*$J39)),"➤",""),"")
C40: 286024 | E40: Revisar acero para maquinado de cáncamo | F40: Luis Ramos | H40: 1 | I40: =(G40+H40)-1 -> 0 | J40: 0 | K40: Sin Empezar | M40: =IF($J40>0%,IF(AND(M$16>=$G41,M$16<$G41+($H40*$J40)),"➤",""),"") | N40: =IF($J40>0%,IF(AND(N$16>=$G41,N$16<$G41+($H40*$J40)),"➤",""),"") | O40: =IF($J40>0%,IF(AND(O$16>=$G41,O$16<$G41+($H40*$J40)),"➤",""),"") | P40: =IF($J40>0%,IF(AND(P$16>=$G41,P$16<$G41+($H40*$J40)),"➤",""),"") | Q40: =IF($J40>0%,IF(AND(Q$16>=$G41,Q$16<$G41+($H40*$J40)),"➤",""),"") | R40: =IF($J40>0%,IF(AND(R$16>=$G41,R$16<$G41+($H40*$J40)),"➤",""),"") | S40: =IF($J40>0%,IF(AND(S$16>=$G40,S$16<$G40+($H40*$J40)),"➤",""),"") | T40: =IF($J40>0%,IF(AND(T$16>=$G40,T$16<$G40+($H40*$J40)),"➤",""),"") | U40: =IF($J40>0%,IF(AND(U$16>=$G40,U$16<$G40+($H40*$J40)),"➤",""),"") | V40: =IF($J40>0%,IF(AND(V$16>=$G40,V$16<$G40+($H40*$J40)),"➤",""),"") | W40: =IF($J40>0%,IF(AND(W$16>=$G40,W$16<$G40+($H40*$J40)),"➤",""),"") | X40: =IF($J40>0%,IF(AND(X$16>=$G40,X$16<$G40+($H40*$J40)),"➤",""),"") | Y40: =IF($J40>0%,IF(AND(Y$16>=$G40,Y$16<$G40+($H40*$J40)),"➤",""),"") | Z40: =IF($J40>0%,IF(AND(Z$16>=$G40,Z$16<$G40+($H40*$J40)),"➤",""),"") | ... AF40: =IF($J40>0%,IF(AND(AF$16>=$G40,AF$16<$G40+($H40*$J40)),"➤",""),"") | AG40: =IF($J40>0%,IF(AND(AG$16>=$G41,AG$16<$G41+($H40*$J40)),"➤",""),"") | AH40: =IF($J40>0%,IF(AND(AH$16>=$G41,AH$16<$G41+($H40*$J40)),"➤",""),"") | AI40: =IF($J40>0%,IF(AND(AI$16>=$G41,AI$16<$G41+($H40*$J40)),"➤",""),"") | AJ40: =IF($J40>0%,IF(AND(AJ$16>=$G41,AJ$16<$G41+($H40*$J40)),"➤",""),"") | AK40: =IF($J40>0%,IF(AND(AK$16>=$G41,AK$16<$G41+($H40*$J40)),"➤",""),"") | AL40: =IF($J40>0%,IF(AND(AL$16>=$G41,AL$16<$G41+($H40*$J40)),"➤",""),"") | AM40: =IF($J40>0%,IF(AND(AM$16>=$G41,AM$16<$G41+($H40*$J40)),"➤",""),"") | AN40: =IF($J40>0%,IF(AND(AN$16>=$G41,AN$16<$G41+($H40*$J40)),"➤",""),"") | ... SX40: =IF($J40>0%,IF(AND(SX$16>=$G41,SX$16<$G41+($H40*$J40)),"➤",""),"")
C41: 286024 | E41: Fabricacion de pistón | F41: Luis Ramos | G41: 45572 | H41: 2 | I41: =(G41+H41)-1 -> 45573 | J41: 0 | K41: Sin Empezar | M41: =IF($J41>0%,IF(AND(M$16>=$G42,M$16<$G42+($H41*$J41)),"➤",""),"") | N41: =IF($J41>0%,IF(AND(N$16>=$G42,N$16<$G42+($H41*$J41)),"➤",""),"") | O41: =IF($J41>0%,IF(AND(O$16>=$G42,O$16<$G42+($H41*$J41)),"➤",""),"") | P41: =IF($J41>0%,IF(AND(P$16>=$G42,P$16<$G42+($H41*$J41)),"➤",""),"") | Q41: =IF($J41>0%,IF(AND(Q$16>=$G42,Q$16<$G42+($H41*$J41)),"➤",""),"") | R41: =IF($J41>0%,IF(AND(R$16>=$G42,R$16<$G42+($H41*$J41)),"➤",""),"") | S41: =IF($J41>0%,IF(AND(S$16>=$G41,S$16<$G41+($H41*$J41)),"➤",""),"") | T41: =IF($J41>0%,IF(AND(T$16>=$G41,T$16<$G41+($H41*$J41)),"➤",""),"") | U41: =IF($J41>0%,IF(AND(U$16>=$G41,U$16<$G41+($H41*$J41)),"➤",""),"") | V41: =IF($J41>0%,IF(AND(V$16>=$G41,V$16<$G41+($H41*$J41)),"➤",""),"") | W41: =IF($J41>0%,IF(AND(W$16>=$G41,W$16<$G41+($H41*$J41)),"➤",""),"") | X41: =IF($J41>0%,IF(AND(X$16>=$G41,X$16<$G41+($H41*$J41)),"➤",""),"") | Y41: =IF($J41>0%,IF(AND(Y$16>=$G41,Y$16<$G41+($H41*$J41)),"➤",""),"") | Z41: =IF($J41>0%,IF(AND(Z$16>=$G41,Z$16<$G41+($H41*$J41)),"➤",""),"") | ... AF41: =IF($J41>0%,IF(AND(AF$16>=$G41,AF$16<$G41+($H41*$J41)),"➤",""),"") | AG41: =IF($J41>0%,IF(AND(AG$16>=$G42,AG$16<$G42+($H41*$J41)),"➤",""),"") | AH41: =IF($J41>0%,IF(AND(AH$16>=$G42,AH$16<$G42+($H41*$J41)),"➤",""),"") | AI41: =IF($J41>0%,IF(AND(AI$16>=$G42,AI$16<$G42+($H41*$J41)),"➤",""),"") | AJ41: =IF($J41>0%,IF(AND(AJ$16>=$G42,AJ$16<$G42+($H41*$J41)),"➤",""),"") | AK41: =IF($J41>0%,IF(AND(AK$16>=$G42,AK$16<$G42+($H41*$J41)),"➤",""),"") | AL41: =IF($J41>0%,IF(AND(AL$16>=$G42,AL$16<$G42+($H41*$J41)),"➤",""),"") | AM41: =IF($J41>0%,IF(AND(AM$16>=$G42,AM$16<$G42+($H41*$J41)),"➤",""),"") | AN41: =IF($J41>0%,IF(AND(AN$16>=$G42,AN$16<$G42+($H41*$J41)),"➤",""),"") | ... SX41: =IF($J41>0%,IF(AND(SX$16>=$G42,SX$16<$G42+($H41*$J41)),"➤",""),"")
C42: 286024 | E42: Fabricación de cáncamo | F42: Luis Ramos | G42: 45573 | H42: 2 | I42: =(G42+H42)-1 -> 45574 | J42: 0 | K42: Sin Empezar | M42: =IF($J42>0%,IF(AND(M$16>=#REF!,M$16<#REF!+($H42*$J42)),"➤",""),"") | N42: =IF($J42>0%,IF(AND(N$16>=#REF!,N$16<#REF!+($H42*$J42)),"➤",""),"") | O42: =IF($J42>0%,IF(AND(O$16>=#REF!,O$16<#REF!+($H42*$J42)),"➤",""),"") | P42: =IF($J42>0%,IF(AND(P$16>=#REF!,P$16<#REF!+($H42*$J42)),"➤",""),"") | Q42: =IF($J42>0%,IF(AND(Q$16>=#REF!,Q$16<#REF!+($H42*$J42)),"➤",""),"") | R42: =IF($J42>0%,IF(AND(R$16>=#REF!,R$16<#REF!+($H42*$J42)),"➤",""),"") | S42: =IF($J42>0%,IF(AND(S$16>=$G42,S$16<$G42+($H42*$J42)),"➤",""),"") | T42: =IF($J42>0%,IF(AND(T$16>=$G42,T$16<$G42+($H42*$J42)),"➤",""),"") | U42: =IF($J42>0%,IF(AND(U$16>=$G42,U$16<$G42+($H42*$J42)),"➤",""),"") | V42: =IF($J42>0%,IF(AND(V$16>=$G42,V$16<$G42+($H42*$J42)),"➤",""),"") | W42: =IF($J42>0%,IF(AND(W$16>=$G42,W$16<$G42+($H42*$J42)),"➤",""),"") | X42: =IF($J42>0%,IF(AND(X$16>=$G42,X$16<$G42+($H42*$J42)),"➤",""),"") | Y42: =IF($J42>0%,IF(AND(Y$16>=$G42,Y$16<$G42+($H42*$J42)),"➤",""),"") | Z42: =IF($J42>0%,IF(AND(Z$16>=$G42,Z$16<$G42+($H42*$J42)),"➤",""),"") | ... AE42: =IF($J42>0%,IF(AND(AE$16>=$G42,AE$16<$G42+($H42*$J42)),"➤",""),"") | AF42: =IF($J42>0%,IF(AND(AF$16>=#REF!,AF$16<#REF!+($H42*$J42)),"➤",""),"") | AG42: =IF($J42>0%,IF(AND(AG$16>=#REF!,AG$16<#REF!+($H42*$J42)),"➤",""),"") | AH42: =IF($J42>0%,IF(AND(AH$16>=#REF!,AH$16<#REF!+($H42*$J42)),"➤",""),"") | AI42: =IF($J42>0%,IF(AND(AI$16>=#REF!,AI$16<#REF!+($H42*$J42)),"➤",""),"") | AJ42: =IF($J42>0%,IF(AND(AJ$16>=#REF!,AJ$16<#REF!+($H42*$J42)),"➤",""),"") | AK42: =IF($J42>0%,IF(AND(AK$16>=#REF!,AK$16<#REF!+($H42*$J42)),"➤",""),"") | AL42: =IF($J42>0%,IF(AND(AL$16>=#REF!,AL$16<#REF!+($H42*$J42)),"➤",""),"") | AM42: =IF($J42>0%,IF(AND(AM$16>=#REF!,AM$16<#REF!+($H42*$J42)),"➤",""),"") | ... SX42: =IF($J42>0%,IF(AND(SX$16>=#REF!,SX$16<#REF!+($H42*$J42)),"➤",""),"")
M43: =IF($J43>0%,IF(AND(M$16>=$G43,M$16<$G43+($H43*$J43)),"➤",""),"") | N43: =IF($J43>0%,IF(AND(N$16>=$G43,N$16<$G43+($H43*$J43)),"➤",""),"") | O43: =IF($J43>0%,IF(AND(O$16>=$G43,O$16<$G43+($H43*$J43)),"➤",""),"") | P43: =IF($J43>0%,IF(AND(P$16>=$G43,P$16<$G43+($H43*$J43)),"➤",""),"") | Q43: =IF($J43>0%,IF(AND(Q$16>=$G43,Q$16<$G43+($H43*$J43)),"➤",""),"") | R43: =IF($J43>0%,IF(AND(R$16>=$G43,R$16<$G43+($H43*$J43)),"➤",""),"") | S43: =IF($J43>0%,IF(AND(S$16>=$G43,S$16<$G43+($H43*$J43)),"➤",""),"") | T43: =IF($J43>0%,IF(AND(T$16>=$G43,T$16<$G43+($H43*$J43)),"➤",""),"") | ... SX43: =IF($J43>0%,IF(AND(SX$16>=$G43,SX$16<$G43+($H43*$J43)),"➤",""),"")
M44: =IF($J44>0%,IF(AND(M$16>=$G44,M$16<$G44+($H44*$J44)),"➤",""),"") | N44: =IF($J44>0%,IF(AND(N$16>=$G44,N$16<$G44+($H44*$J44)),"➤",""),"") | O44: =IF($J44>0%,IF(AND(O$16>=$G44,O$16<$G44+($H44*$J44)),"➤",""),"") | P44: =IF($J44>0%,IF(AND(P$16>=$G44,P$16<$G44+($H44*$J44)),"➤",""),"") | Q44: =IF($J44>0%,IF(AND(Q$16>=$G44,Q$16<$G44+($H44*$J44)),"➤",""),"") | R44: =IF($J44>0%,IF(AND(R$16>=$G44,R$16<$G44+($H44*$J44)),"➤",""),"") | S44: =IF($J44>0%,IF(AND(S$16>=$G44,S$16<$G44+($H44*$J44)),"➤",""),"") | T44: =IF($J44>0%,IF(AND(T$16>=$G44,T$16<$G44+($H44*$J44)),"➤",""),"") | ... SX44: =IF($J44>0%,IF(AND(SX$16>=$G44,SX$16<$G44+($H44*$J44)),"➤",""),"")
M45: =IF($J45>0%,IF(AND(M$16>=$G45,M$16<$G45+($H45*$J45)),"➤",""),"") | N45: =IF($J45>0%,IF(AND(N$16>=$G45,N$16<$G45+($H45*$J45)),"➤",""),"") | O45: =IF($J45>0%,IF(AND(O$16>=$G45,O$16<$G45+($H45*$J45)),"➤",""),"") | P45: =IF($J45>0%,IF(AND(P$16>=$G45,P$16<$G45+($H45*$J45)),"➤",""),"") | Q45: =IF($J45>0%,IF(AND(Q$16>=$G45,Q$16<$G45+($H45*$J45)),"➤",""),"") | R45: =IF($J45>0%,IF(AND(R$16>=$G45,R$16<$G45+($H45*$J45)),"➤",""),"") | S45: =IF($J45>0%,IF(AND(S$16>=$G45,S$16<$G45+($H45*$J45)),"➤",""),"") | T45: =IF($J45>0%,IF(AND(T$16>=$G45,T$16<$G45+($H45*$J45)),"➤",""),"") | ... SX45: =IF($J45>0%,IF(AND(SX$16>=$G45,SX$16<$G45+($H45*$J45)),"➤",""),"")
E46: SOLDADURA | S46: =IF($J46>0%,IF(AND(S$16>=$G46,S$16<$G46+($H46*$J46)),"➤",""),"") | T46: =IF($J46>0%,IF(AND(T$16>=$G46,T$16<$G46+($H46*$J46)),"➤",""),"") | U46: =IF($J46>0%,IF(AND(U$16>=$G46,U$16<$G46+($H46*$J46)),"➤",""),"") | V46: =IF($J46>0%,IF(AND(V$16>=$G46,V$16<$G46+($H46*$J46)),"➤",""),"") | W46: =IF($J46>0%,IF(AND(W$16>=$G46,W$16<$G46+($H46*$J46)),"➤",""),"") | X46: =IF($J46>0%,IF(AND(X$16>=$G46,X$16<$G46+($H46*$J46)),"➤",""),"") | Y46: =IF($J46>0%,IF(AND(Y$16>=$G46,Y$16<$G46+($H46*$J46)),"➤",""),"") | Z46: =IF($J46>0%,IF(AND(Z$16>=$G46,Z$16<$G46+($H46*$J46)),"➤",""),"") | ... AE46: =IF($J46>0%,IF(AND(AE$16>=$G46,AE$16<$G46+($H46*$J46)),"➤",""),"")
C47: 285324 | E47: Soldadura de cilindro | F47: Justo Arocutipa | G47: 45565 | H47: 1 | I47: =(G47+H47)-1 -> 45565 | J47: 1 | K47: Completado | M47: =IF($J47>0%,IF(AND(M$16>=$G47,M$16<$G47+($H47*$J47)),"➤",""),"") | N47: =IF($J47>0%,IF(AND(N$16>=$G47,N$16<$G47+($H47*$J47)),"➤",""),"") | O47: =IF($J47>0%,IF(AND(O$16>=$G47,O$16<$G47+($H47*$J47)),"➤",""),"") | P47: =IF($J47>0%,IF(AND(P$16>=$G47,P$16<$G47+($H47*$J47)),"➤",""),"") | Q47: =IF($J47>0%,IF(AND(Q$16>=$G47,Q$16<$G47+($H47*$J47)),"➤",""),"") | R47: =IF($J47>0%,IF(AND(R$16>=$G47,R$16<$G47+($H47*$J47)),"➤",""),"") | S47: =IF($J47>0%,IF(AND(S$16>=$G47,S$16<$G47+($H47*$J47)),"➤",""),"") -> ➤ | T47: =IF($J47>0%,IF(AND(T$16>=$G47,T$16<$G47+($H47*$J47)),"➤",""),"") | ... SX47: =IF($J47>0%,IF(AND(SX$16>=$G47,SX$16<$G47+($H47*$J47)),"➤",""),"")
C48: 285724 | E48: Recuperar con soldadura alojamiento de tapa posterior de cilindro | F48: Justo Arocutipa | G48: 45565 | H48: 2 | I48: =(G48+H48)-1 -> 45566 | J48: 1 | K48: Completado | M48: =IF($J48>0%,IF(AND(M$16>=$G48,M$16<$G48+($H48*$J48)),"➤",""),"") | N48: =IF($J48>0%,IF(AND(N$16>=$G48,N$16<$G48+($H48*$J48)),"➤",""),"") | O48: =IF($J48>0%,IF(AND(O$16>=$G48,O$16<$G48+($H48*$J48)),"➤",""),"") | P48: =IF($J48>0%,IF(AND(P$16>=$G48,P$16<$G48+($H48*$J48)),"➤",""),"") | Q48: =IF($J48>0%,IF(AND(Q$16>=$G48,Q$16<$G48+($H48*$J48)),"➤",""),"") | R48: =IF($J48>0%,IF(AND(R$16>=$G48,R$16<$G48+($H48*$J48)),"➤",""),"") | S48: =IF($J48>0%,IF(AND(S$16>=$G48,S$16<$G48+($H48*$J48)),"➤",""),"") -> ➤ | T48: =IF($J48>0%,IF(AND(T$16>=$G48,T$16<$G48+($H48*$J48)),"➤",""),"") -> ➤ | ... SX48: =IF($J48>0%,IF(AND(SX$16>=$G48,SX$16<$G48+($H48*$J48)),"➤",""),"")
C49: 285224 | E49: Soldadura de cilindro | F49: Justo Arocutipa | G49: 45566 | H49: 1 | I49: =(G49+H49)-1 -> 45566 | J49: 0.2 | K49: En Proceso | M49: =IF($J49>0%,IF(AND(M$16>=$G49,M$16<$G49+($H49*$J49)),"➤",""),"") | N49: =IF($J49>0%,IF(AND(N$16>=$G49,N$16<$G49+($H49*$J49)),"➤",""),"") | O49: =IF($J49>0%,IF(AND(O$16>=$G49,O$16<$G49+($H49*$J49)),"➤",""),"") | P49: =IF($J49>0%,IF(AND(P$16>=$G49,P$16<$G49+($H49*$J49)),"➤",""),"") | Q49: =IF($J49>0%,IF(AND(Q$16>=$G49,Q$16<$G49+($H49*$J49)),"➤",""),"") | R49: =IF($J49>0%,IF(AND(R$16>=$G49,R$16<$G49+($H49*$J49)),"➤",""),"") | S49: =IF($J49>0%,IF(AND(S$16>=$G49,S$16<$G49+($H49*$J49)),"➤",""),"") | T49: =IF($J49>0%,IF(AND(T$16>=$G49,T$16<$G49+($H49*$J49)),"➤",""),"") -> ➤ | ... SX49: =IF($J49>0%,IF(AND(SX$16>=$G49,SX$16<$G49+($H49*$J49)),"➤",""),"")
C50: 273924 | E50: Soldadura encastre de cilindro | F50: Justo Arocutipa | G50: 45567 | H50: 1 | I50: =(G50+H50)-1 -> 45567 | J50: 0 | K50: Sin Empezar | S50: =IF($J50>0%,IF(AND(S$16>=$G50,S$16<$G50+($H50*$J50)),"➤",""),"") | T50: =IF($J50>0%,IF(AND(T$16>=$G50,T$16<$G50+($H50*$J50)),"➤",""),"") | U50: =IF($J50>0%,IF(AND(U$16>=$G50,U$16<$G50+($H50*$J50)),"➤",""),"") | V50: =IF($J50>0%,IF(AND(V$16>=$G50,V$16<$G50+($H50*$J50)),"➤",""),"") | W50: =IF($J50>0%,IF(AND(W$16>=$G50,W$16<$G50+($H50*$J50)),"➤",""),"") | X50: =IF($J50>0%,IF(AND(X$16>=$G50,X$16<$G50+($H50*$J50)),"➤",""),"") | Y50: =IF($J50>0%,IF(AND(Y$16>=$G50,Y$16<$G50+($H50*$J50)),"➤",""),"") | Z50: =IF($J50>0%,IF(AND(Z$16>=$G50,Z$16<$G50+($H50*$J50)),"➤",""),"") | ... AE50: =IF($J50>0%,IF(AND(AE$16>=$G50,AE$16<$G50+($H50*$J50)),"➤",""),"")
C51: 273924 | E51: Relleno Ojo de cilindro | F51: Justo Arocutipa | G51: 45567 | H51: 2 | I51: =(G51+H51)-1 -> 45568 | J51: 0 | K51: Sin Empezar | S51: =IF($J51>0%,IF(AND(S$16>=$G51,S$16<$G51+($H51*$J51)),"➤",""),"") | T51: =IF($J51>0%,IF(AND(T$16>=$G51,T$16<$G51+($H51*$J51)),"➤",""),"") | U51: =IF($J51>0%,IF(AND(U$16>=$G51,U$16<$G51+($H51*$J51)),"➤",""),"") | V51: =IF($J51>0%,IF(AND(V$16>=$G51,V$16<$G51+($H51*$J51)),"➤",""),"") | W51: =IF($J51>0%,IF(AND(W$16>=$G51,W$16<$G51+($H51*$J51)),"➤",""),"") | X51: =IF($J51>0%,IF(AND(X$16>=$G51,X$16<$G51+($H51*$J51)),"➤",""),"") | Y51: =IF($J51>0%,IF(AND(Y$16>=$G51,Y$16<$G51+($H51*$J51)),"➤",""),"") | Z51: =IF($J51>0%,IF(AND(Z$16>=$G51,Z$16<$G51+($H51*$J51)),"➤",""),"") | ... AE51: =IF($J51>0%,IF(AND(AE$16>=$G51,AE$16<$G51+($H51*$J51)),"➤",""),"")
C52: 286624 | E52: Soldadura de cilindro | F52: Justo Arocutipa | G52: 45568 | H52: 2 | I52: =(G52+H52)-1 -> 45569 | J52: 0 | K52: Sin Empezar | M52: =IF($J52>0%,IF(AND(M$16>=$G52,M$16<$G52+($H52*$J52)),"➤",""),"") | N52: =IF($J52>0%,IF(AND(N$16>=$G52,N$16<$G52+($H52*$J52)),"➤",""),"") | O52: =IF($J52>0%,IF(AND(O$16>=$G52,O$16<$G52+($H52*$J52)),"➤",""),"") | P52: =IF($J52>0%,IF(AND(P$16>=$G52,P$16<$G52+($H52*$J52)),"➤",""),"") | Q52: =IF($J52>0%,IF(AND(Q$16>=$G52,Q$16<$G52+($H52*$J52)),"➤",""),"") | R52: =IF($J52>0%,IF(AND(R$16>=$G52,R$16<$G52+($H52*$J52)),"➤",""),"") | S52: =IF($J52>0%,IF(AND(S$16>=$G52,S$16<$G52+($H52*$J52)),"➤",""),"") | T52: =IF($J52>0%,IF(AND(T$16>=$G52,T$16<$G52+($H52*$J52)),"➤",""),"") | ... SX52: =IF($J52>0%,IF(AND(SX$16>=$G52,SX$16<$G52+($H52*$J52)),"➤",""),"")
C53: 283924 | E53: Soldadura de cilindro | F53: Justo Arocutipa | G53: 45569 | H53: 1 | I53: =(G53+H53)-1 -> 45569 | J53: 0 | K53: Sin Empezar | M53: =IF($J53>0%,IF(AND(M$16>=$G53,M$16<$G53+($H53*$J53)),"➤",""),"") | N53: =IF($J53>0%,IF(AND(N$16>=$G53,N$16<$G53+($H53*$J53)),"➤",""),"") | O53: =IF($J53>0%,IF(AND(O$16>=$G53,O$16<$G53+($H53*$J53)),"➤",""),"") | P53: =IF($J53>0%,IF(AND(P$16>=$G53,P$16<$G53+($H53*$J53)),"➤",""),"") | Q53: =IF($J53>0%,IF(AND(Q$16>=$G53,Q$16<$G53+($H53*$J53)),"➤",""),"") | R53: =IF($J53>0%,IF(AND(R$16>=$G53,R$16<$G53+($H53*$J53)),"➤",""),"") | S53: =IF($J53>0%,IF(AND(S$16>=$G53,S$16<$G53+($H53*$J53)),"➤",""),"") | T53: =IF($J53>0%,IF(AND(T$16>=$G53,T$16<$G53+($H53*$J53)),"➤",""),"") | ... SX53: =IF($J53>0%,IF(AND(SX$16>=$G53,SX$16<$G53+($H53*$J53)),"➤",""),"")
C54: 286624 | E54: Soldadura de vastago | F54: Justo Arocutipa | G54: 45568 | H54: 1 | I54: =(G54+H54)-1 -> 45568 | J54: 0 | K54: Sin Empezar | M54: =IF($J54>0%,IF(AND(M$16>=$G54,M$16<$G54+($H54*$J54)),"➤",""),"") | N54: =IF($J54>0%,IF(AND(N$16>=$G54,N$16<$G54+($H54*$J54)),"➤",""),"") | O54: =IF($J54>0%,IF(AND(O$16>=$G54,O$16<$G54+($H54*$J54)),"➤",""),"") | P54: =IF($J54>0%,IF(AND(P$16>=$G54,P$16<$G54+($H54*$J54)),"➤",""),"") | Q54: =IF($J54>0%,IF(AND(Q$16>=$G54,Q$16<$G54+($H54*$J54)),"➤",""),"") | R54: =IF($J54>0%,IF(AND(R$16>=$G54,R$16<$G54+($H54*$J54)),"➤",""),"") | S54: =IF($J54>0%,IF(AND(S$16>=$G54,S$16<$G54+($H54*$J54)),"➤",""),"") | T54: =IF($J54>0%,IF(AND(T$16>=$G54,T$16<$G54+($H54*$J54)),"➤",""),"") | ... SX54: =IF($J54>0%,IF(AND(SX$16>=$G54,SX$16<$G54+($H54*$J54)),"➤",""),"")
C55: 285724 | E55: Soldadura de cilindro | F55: Justo Arocutipa | G55: 45569 | H55: 1 | I55: =(G55+H55)-1 -> 45569 | J55: 0 | K55: Sin Empezar | S55: =IF($J55>0%,IF(AND(S$16>=$G55,S$16<$G55+($H55*$J55)),"➤",""),"") | T55: =IF($J55>0%,IF(AND(T$16>=$G55,T$16<$G55+($H55*$J55)),"➤",""),"") | U55: =IF($J55>0%,IF(AND(U$16>=$G55,U$16<$G55+($H55*$J55)),"➤",""),"") | V55: =IF($J55>0%,IF(AND(V$16>=$G55,V$16<$G55+($H55*$J55)),"➤",""),"") | W55: =IF($J55>0%,IF(AND(W$16>=$G55,W$16<$G55+($H55*$J55)),"➤",""),"") | X55: =IF($J55>0%,IF(AND(X$16>=$G55,X$16<$G55+($H55*$J55)),"➤",""),"") | Y55: =IF($J55>0%,IF(AND(Y$16>=$G55,Y$16<$G55+($H55*$J55)),"➤",""),"") | Z55: =IF($J55>0%,IF(AND(Z$16>=$G55,Z$16<$G55+($H55*$J55)),"➤",""),"") | ... AE55: =IF($J55>0%,IF(AND(AE$16>=$G55,AE$16<$G55+($H55*$J55)),"➤",""),"")
C56: 291224 | E56: Relleno ojo vástago | F56: Victor Caceres | G56: 45565 | H56: 1 | I56: =(G56+H56)-1 -> 45565 | J56: 0 | K56: Sin Empezar | M56: =IF($J56>0%,IF(AND(M$16>=$G56,M$16<$G56+($H56*$J56)),"➤",""),"") | N56: =IF($J56>0%,IF(AND(N$16>=$G56,N$16<$G56+($H56*$J56)),"➤",""),"") | O56: =IF($J56>0%,IF(AND(O$16>=$G56,O$16<$G56+($H56*$J56)),"➤",""),"") | P56: =IF($J56>0%,IF(AND(P$16>=$G56,P$16<$G56+($H56*$J56)),"➤",""),"") | Q56: =IF($J56>0%,IF(AND(Q$16>=$G56,Q$16<$G56+($H56*$J56)),"➤",""),"") | R56: =IF($J56>0%,IF(AND(R$16>=$G56,R$16<$G56+($H56*$J56)),"➤",""),"") | S56: =IF($J56>0%,IF(AND(S$16>=$G56,S$16<$G56+($H56*$J56)),"➤",""),"") | T56: =IF($J56>0%,IF(AND(T$16>=$G56,T$16<$G56+($H56*$J56)),"➤",""),"") | ... SX56: =IF($J56>0%,IF(AND(SX$16>=$G56,SX$16<$G56+($H56*$J56)),"➤",""),"")
C57: 291424 | E57: Relleno ojo vástago | F57: Victor Caceres | G57: 45565 | H57: 1 | I57: =(G57+H57)-1 -> 45565 | J57: 0 | K57: Sin Empezar | M57: =IF($J57>0%,IF(AND(M$16>=$G57,M$16<$G57+($H57*$J57)),"➤",""),"") | N57: =IF($J57>0%,IF(AND(N$16>=$G57,N$16<$G57+($H57*$J57)),"➤",""),"") | O57: =IF($J57>0%,IF(AND(O$16>=$G57,O$16<$G57+($H57*$J57)),"➤",""),"") | P57: =IF($J57>0%,IF(AND(P$16>=$G57,P$16<$G57+($H57*$J57)),"➤",""),"") | Q57: =IF($J57>0%,IF(AND(Q$16>=$G57,Q$16<$G57+($H57*$J57)),"➤",""),"") | R57: =IF($J57>0%,IF(AND(R$16>=$G57,R$16<$G57+($H57*$J57)),"➤",""),"") | S57: =IF($J57>0%,IF(AND(S$16>=$G57,S$16<$G57+($H57*$J57)),"➤",""),"") | T57: =IF($J57>0%,IF(AND(T$16>=$G57,T$16<$G57+($H57*$J57)),"➤",""),"") | ... SX57: =IF($J57>0%,IF(AND(SX$16>=$G57,SX$16<$G57+($H57*$J57)),"➤",""),"")
C58: 291524 | E58: Relleno ojo vástago | F58: Victor Caceres | G58: 45565 | H58: 1 | I58: =(G58+H58)-1 -> 45565 | J58: 0 | K58: Sin Empezar | M58: =IF($J58>0%,IF(AND(M$16>=$G58,M$16<$G58+($H58*$J58)),"➤",""),"") | N58: =IF($J58>0%,IF(AND(N$16>=$G58,N$16<$G58+($H58*$J58)),"➤",""),"") | O58: =IF($J58>0%,IF(AND(O$16>=$G58,O$16<$G58+($H58*$J58)),"➤",""),"") | P58: =IF($J58>0%,IF(AND(P$16>=$G58,P$16<$G58+($H58*$J58)),"➤",""),"") | Q58: =IF($J58>0%,IF(AND(Q$16>=$G58,Q$16<$G58+($H58*$J58)),"➤",""),"") | R58: =IF($J58>0%,IF(AND(R$16>=$G58,R$16<$G58+($H58*$J58)),"➤",""),"") | S58: =IF($J58>0%,IF(AND(S$16>=$G58,S$16<$G58+($H58*$J58)),"➤",""),"") | T58: =IF($J58>0%,IF(AND(T$16>=$G58,T$16<$G58+($H58*$J58)),"➤",""),"") | ... SX58: =IF($J58>0%,IF(AND(SX$16>=$G58,SX$16<$G58+($H58*$J58)),"➤",""),"")
C59: 291924 | E59: Relleno ojo vástago | F59: Victor Caceres | G59: 45566 | H59: 1 | I59: =(G59+H59)-1 -> 45566 | J59: 0 | K59: Sin Empezar | M59: =IF($J59>0%,IF(AND(M$16>=$G59,M$16<$G59+($H59*$J59)),"➤",""),"") | N59: =IF($J59>0%,IF(AND(N$16>=$G59,N$16<$G59+($H59*$J59)),"➤",""),"") | O59: =IF($J59>0%,IF(AND(O$16>=$G59,O$16<$G59+($H59*$J59)),"➤",""),"") | P59: =IF($J59>0%,IF(AND(P$16>=$G59,P$16<$G59+($H59*$J59)),"➤",""),"") | Q59: =IF($J59>0%,IF(AND(Q$16>=$G59,Q$16<$G59+($H59*$J59)),"➤",""),"") | R59: =IF($J59>0%,IF(AND(R$16>=$G59,R$16<$G59+($H59*$J59)),"➤",""),"") | S59: =IF($J59>0%,IF(AND(S$16>=$G59,S$16<$G59+($H59*$J59)),"➤",""),"") | T59: =IF($J59>0%,IF(AND(T$16>=$G59,T$16<$G59+($H59*$J59)),"➤",""),"") | ... SX59: =IF($J59>0%,IF(AND(SX$16>=$G59,SX$16<$G59+($H59*$J59)),"➤",""),"")
C60: 291924 | E60: Relleno ojo vástago | F60: Victor Caceres | G60: 45566 | H60: 1 | I60: =(G60+H60)-1 -> 45566 | J60: 0 | K60: Sin Empezar | M60: =IF($J60>0%,IF(AND(M$16>=$G60,M$16<$G60+($H60*$J60)),"➤",""),"") | N60: =IF($J60>0%,IF(AND(N$16>=$G60,N$16<$G60+($H60*$J60)),"➤",""),"") | O60: =IF($J60>0%,IF(AND(O$16>=$G60,O$16<$G60+($H60*$J60)),"➤",""),"") | P60: =IF($J60>0%,IF(AND(P$16>=$G60,P$16<$G60+($H60*$J60)),"➤",""),"") | Q60: =IF($J60>0%,IF(AND(Q$16>=$G60,Q$16<$G60+($H60*$J60)),"➤",""),"") | R60: =IF($J60>0%,IF(AND(R$16>=$G60,R$16<$G60+($H60*$J60)),"➤",""),"") | S60: =IF($J60>0%,IF(AND(S$16>=$G60,S$16<$G60+($H60*$J60)),"➤",""),"") | T60: =IF($J60>0%,IF(AND(T$16>=$G60,T$16<$G60+($H60*$J60)),"➤",""),"") | ... SX60: =IF($J60>0%,IF(AND(SX$16>=$G60,SX$16<$G60+($H60*$J60)),"➤",""),"")
C61: 292524 | E61: Relleno ojo vástago | F61: Victor Caceres | G61: 45566 | H61: 1 | I61: =(G61+H61)-1 -> 45566 | J61: 0 | K61: Sin Empezar | M61: =IF($J61>0%,IF(AND(M$16>=$G61,M$16<$G61+($H61*$J61)),"➤",""),"") | N61: =IF($J61>0%,IF(AND(N$16>=$G61,N$16<$G61+($H61*$J61)),"➤",""),"") | O61: =IF($J61>0%,IF(AND(O$16>=$G61,O$16<$G61+($H61*$J61)),"➤",""),"") | P61: =IF($J61>0%,IF(AND(P$16>=$G61,P$16<$G61+($H61*$J61)),"➤",""),"") | Q61: =IF($J61>0%,IF(AND(Q$16>=$G61,Q$16<$G61+($H61*$J61)),"➤",""),"") | R61: =IF($J61>0%,IF(AND(R$16>=$G61,R$16<$G61+($H61*$J61)),"➤",""),"") | S61: =IF($J61>0%,IF(AND(S$16>=$G61,S$16<$G61+($H61*$J61)),"➤",""),"") | T61: =IF($J61>0%,IF(AND(T$16>=$G61,T$16<$G61+($H61*$J61)),"➤",""),"") | ... SX61: =IF($J61>0%,IF(AND(SX$16>=$G61,SX$16<$G61+($H61*$J61)),"➤",""),"")
C62: 287024 | D62: 1 | E62: Soldadura de encastre de vástago | F62: Victor Caceres | G62: 45566 | H62: 2 | I62: =(G62+H62)-1 -> 45567 | J62: 0 | K62: Sin Empezar | M62: =IF($J62>0%,IF(AND(M$16>=$G62,M$16<$G62+($H62*$J62)),"➤",""),"") | N62: =IF($J62>0%,IF(AND(N$16>=$G62,N$16<$G62+($H62*$J62)),"➤",""),"") | O62: =IF($J62>0%,IF(AND(O$16>=$G62,O$16<$G62+($H62*$J62)),"➤",""),"") | P62: =IF($J62>0%,IF(AND(P$16>=$G62,P$16<$G62+($H62*$J62)),"➤",""),"") | Q62: =IF($J62>0%,IF(AND(Q$16>=$G62,Q$16<$G62+($H62*$J62)),"➤",""),"") | R62: =IF($J62>0%,IF(AND(R$16>=$G62,R$16<$G62+($H62*$J62)),"➤",""),"") | S62: =IF($J62>0%,IF(AND(S$16>=$G62,S$16<$G62+($H62*$J62)),"➤",""),"") | T62: =IF($J62>0%,IF(AND(T$16>=$G62,T$16<$G62+($H62*$J62)),"➤",""),"") | ... SX62: =IF($J62>0%,IF(AND(SX$16>=$G62,SX$16<$G62+($H62*$J62)),"➤",""),"")
C63: 287024 | D63: 1 | E63: Relleno de ojo de vástago | F63: Victor Caceres | G63: 45567 | H63: 1 | I63: =(G63+H63)-1 -> 45567 | J63: 0 | K63: Sin Empezar | M63: =IF($J63>0%,IF(AND(M$16>=$G63,M$16<$G63+($H63*$J63)),"➤",""),"") | N63: =IF($J63>0%,IF(AND(N$16>=$G63,N$16<$G63+($H63*$J63)),"➤",""),"") | O63: =IF($J63>0%,IF(AND(O$16>=$G63,O$16<$G63+($H63*$J63)),"➤",""),"") | P63: =IF($J63>0%,IF(AND(P$16>=$G63,P$16<$G63+($H63*$J63)),"➤",""),"") | Q63: =IF($J63>0%,IF(AND(Q$16>=$G63,Q$16<$G63+($H63*$J63)),"➤",""),"") | R63: =IF($J63>0%,IF(AND(R$16>=$G63,R$16<$G63+($H63*$J63)),"➤",""),"") | S63: =IF($J63>0%,IF(AND(S$16>=$G63,S$16<$G63+($H63*$J63)),"➤",""),"") | T63: =IF($J63>0%,IF(AND(T$16>=$G63,T$16<$G63+($H63*$J63)),"➤",""),"") | ... SX63: =IF($J63>0%,IF(AND(SX$16>=$G63,SX$16<$G63+($H63*$J63)),"➤",""),"")
C64: 287624 | D64: 1 | E64: Soldadura de trunnion | F64: Victor Caceres | G64: 45567 | H64: 1 | I64: =(G64+H64)-1 -> 45567 | J64: 0 | K64: Sin Empezar | M64: =IF($J64>0%,IF(AND(M$16>=$G64,M$16<$G64+($H64*$J64)),"➤",""),"") | N64: =IF($J64>0%,IF(AND(N$16>=$G64,N$16<$G64+($H64*$J64)),"➤",""),"") | O64: =IF($J64>0%,IF(AND(O$16>=$G64,O$16<$G64+($H64*$J64)),"➤",""),"") | P64: =IF($J64>0%,IF(AND(P$16>=$G64,P$16<$G64+($H64*$J64)),"➤",""),"") | Q64: =IF($J64>0%,IF(AND(Q$16>=$G64,Q$16<$G64+($H64*$J64)),"➤",""),"") | R64: =IF($J64>0%,IF(AND(R$16>=$G64,R$16<$G64+($H64*$J64)),"➤",""),"") | S64: =IF($J64>0%,IF(AND(S$16>=$G64,S$16<$G64+($H64*$J64)),"➤",""),"") | T64: =IF($J64>0%,IF(AND(T$16>=$G64,T$16<$G64+($H64*$J64)),"➤",""),"") | ... SX64: =IF($J64>0%,IF(AND(SX$16>=$G64,SX$16<$G64+($H64*$J64)),"➤",""),"")
C65: 279624 | D65: 1 | E65: Extraer rótula | F65: Victor Caceres | G65: 45567 | H65: 1 | I65: =(G65+H65)-1 -> 45567 | J65: 0 | K65: Sin Empezar | M65: =IF($J65>0%,IF(AND(M$16>=$G65,M$16<$G65+($H65*$J65)),"➤",""),"") | N65: =IF($J65>0%,IF(AND(N$16>=$G65,N$16<$G65+($H65*$J65)),"➤",""),"") | O65: =IF($J65>0%,IF(AND(O$16>=$G65,O$16<$G65+($H65*$J65)),"➤",""),"") | P65: =IF($J65>0%,IF(AND(P$16>=$G65,P$16<$G65+($H65*$J65)),"➤",""),"") | Q65: =IF($J65>0%,IF(AND(Q$16>=$G65,Q$16<$G65+($H65*$J65)),"➤",""),"") | R65: =IF($J65>0%,IF(AND(R$16>=$G65,R$16<$G65+($H65*$J65)),"➤",""),"") | S65: =IF($J65>0%,IF(AND(S$16>=$G65,S$16<$G65+($H65*$J65)),"➤",""),"") | T65: =IF($J65>0%,IF(AND(T$16>=$G65,T$16<$G65+($H65*$J65)),"➤",""),"") | ... SX65: =IF($J65>0%,IF(AND(SX$16>=$G65,SX$16<$G65+($H65*$J65)),"➤",""),"")
C66: 279624 | D66: 1 | E66: Relleno ojo vástago | F66: Victor Caceres | G66: 45567 | H66: 2 | I66: =(G66+H66)-1 -> 45568 | J66: 0 | K66: Sin Empezar | M66: =IF($J66>0%,IF(AND(M$16>=$G66,M$16<$G66+($H66*$J66)),"➤",""),"") | N66: =IF($J66>0%,IF(AND(N$16>=$G66,N$16<$G66+($H66*$J66)),"➤",""),"") | O66: =IF($J66>0%,IF(AND(O$16>=$G66,O$16<$G66+($H66*$J66)),"➤",""),"") | P66: =IF($J66>0%,IF(AND(P$16>=$G66,P$16<$G66+($H66*$J66)),"➤",""),"") | Q66: =IF($J66>0%,IF(AND(Q$16>=$G66,Q$16<$G66+($H66*$J66)),"➤",""),"") | R66: =IF($J66>0%,IF(AND(R$16>=$G66,R$16<$G66+($H66*$J66)),"➤",""),"") | S66: =IF($J66>0%,IF(AND(S$16>=$G66,S$16<$G66+($H66*$J66)),"➤",""),"") | T66: =IF($J66>0%,IF(AND(T$16>=$G66,T$16<$G66+($H66*$J66)),"➤",""),"") | ... SX66: =IF($J66>0%,IF(AND(SX$16>=$G66,SX$16<$G66+($H66*$J66)),"➤",""),"")
C67: 287324 | E67: Relleno ojo cilindro | F67: Victor Caceres | G67: 45567 | H67: 1 | I67: =(G67+H67)-1 -> 45567 | J67: 0 | K67: Sin Empezar | M67: =IF($J67>0%,IF(AND(M$16>=$G67,M$16<$G67+($H67*$J67)),"➤",""),"") | N67: =IF($J67>0%,IF(AND(N$16>=$G67,N$16<$G67+($H67*$J67)),"➤",""),"") | O67: =IF($J67>0%,IF(AND(O$16>=$G67,O$16<$G67+($H67*$J67)),"➤",""),"") | P67: =IF($J67>0%,IF(AND(P$16>=$G67,P$16<$G67+($H67*$J67)),"➤",""),"") | Q67: =IF($J67>0%,IF(AND(Q$16>=$G67,Q$16<$G67+($H67*$J67)),"➤",""),"") | R67: =IF($J67>0%,IF(AND(R$16>=$G67,R$16<$G67+($H67*$J67)),"➤",""),"") | S67: =IF($J67>0%,IF(AND(S$16>=$G67,S$16<$G67+($H67*$J67)),"➤",""),"") | T67: =IF($J67>0%,IF(AND(T$16>=$G67,T$16<$G67+($H67*$J67)),"➤",""),"") | ... SX67: =IF($J67>0%,IF(AND(SX$16>=$G67,SX$16<$G67+($H67*$J67)),"➤",""),"")
C68: 287524 | E68: Relleno ojo cilindro | F68: Victor Caceres | G68: 45566 | H68: 1 | I68: =(G68+H68)-1 -> 45566 | J68: 0 | K68: Siguiente | M68: =IF($J68>0%,IF(AND(M$16>=$G68,M$16<$G68+($H68*$J68)),"➤",""),"") | N68: =IF($J68>0%,IF(AND(N$16>=$G68,N$16<$G68+($H68*$J68)),"➤",""),"") | O68: =IF($J68>0%,IF(AND(O$16>=$G68,O$16<$G68+($H68*$J68)),"➤",""),"") | P68: =IF($J68>0%,IF(AND(P$16>=$G68,P$16<$G68+($H68*$J68)),"➤",""),"") | Q68: =IF($J68>0%,IF(AND(Q$16>=$G68,Q$16<$G68+($H68*$J68)),"➤",""),"") | R68: =IF($J68>0%,IF(AND(R$16>=$G68,R$16<$G68+($H68*$J68)),"➤",""),"") | S68: =IF($J68>0%,IF(AND(S$16>=$G68,S$16<$G68+($H68*$J68)),"➤",""),"") | T68: =IF($J68>0%,IF(AND(T$16>=$G68,T$16<$G68+($H68*$J68)),"➤",""),"") | ... SX68: =IF($J68>0%,IF(AND(SX$16>=$G68,SX$16<$G68+($H68*$J68)),"➤",""),"")
C69: 287924 | E69: Relleno ojo cilindro | F69: Victor Caceres | G69: 45568 | H69: 1 | I69: =(G69+H69)-1 -> 45568 | J69: 0 | K69: Sin Empezar | M69: =IF($J69>0%,IF(AND(M$16>=$G69,M$16<$G69+($H69*$J69)),"➤",""),"") | N69: =IF($J69>0%,IF(AND(N$16>=$G69,N$16<$G69+($H69*$J69)),"➤",""),"") | O69: =IF($J69>0%,IF(AND(O$16>=$G69,O$16<$G69+($H69*$J69)),"➤",""),"") | P69: =IF($J69>0%,IF(AND(P$16>=$G69,P$16<$G69+($H69*$J69)),"➤",""),"") | Q69: =IF($J69>0%,IF(AND(Q$16>=$G69,Q$16<$G69+($H69*$J69)),"➤",""),"") | R69: =IF($J69>0%,IF(AND(R$16>=$G69,R$16<$G69+($H69*$J69)),"➤",""),"") | S69: =IF($J69>0%,IF(AND(S$16>=$G69,S$16<$G69+($H69*$J69)),"➤",""),"") | T69: =IF($J69>0%,IF(AND(T$16>=$G69,T$16<$G69+($H69*$J69)),"➤",""),"") | ... SX69: =IF($J69>0%,IF(AND(SX$16>=$G69,SX$16<$G69+($H69*$J69)),"➤",""),"")
C70: 288024 | E70: Relleno ojo cilindro | F70: Victor Caceres | G70: 45568 | H70: 1 | I70: =(G70+H70)-1 -> 45568 | J70: 0 | K70: Sin Empezar | M70: =IF($J70>0%,IF(AND(M$16>=$G70,M$16<$G70+($H70*$J70)),"➤",""),"") | N70: =IF($J70>0%,IF(AND(N$16>=$G70,N$16<$G70+($H70*$J70)),"➤",""),"") | O70: =IF($J70>0%,IF(AND(O$16>=$G70,O$16<$G70+($H70*$J70)),"➤",""),"") | P70: =IF($J70>0%,IF(AND(P$16>=$G70,P$16<$G70+($H70*$J70)),"➤",""),"") | Q70: =IF($J70>0%,IF(AND(Q$16>=$G70,Q$16<$G70+($H70*$J70)),"➤",""),"") | R70: =IF($J70>0%,IF(AND(R$16>=$G70,R$16<$G70+($H70*$J70)),"➤",""),"") | S70: =IF($J70>0%,IF(AND(S$16>=$G70,S$16<$G70+($H70*$J70)),"➤",""),"") | T70: =IF($J70>0%,IF(AND(T$16>=$G70,T$16<$G70+($H70*$J70)),"➤",""),"") | ... SX70: =IF($J70>0%,IF(AND(SX$16>=$G70,SX$16<$G70+($H70*$J70)),"➤",""),"")
I71: =(G71+H71)-1 -> -1 | M71: =IF($J71>0%,IF(AND(M$16>=$G71,M$16<$G71+($H71*$J71)),"➤",""),"") | N71: =IF($J71>0%,IF(AND(N$16>=$G71,N$16<$G71+($H71*$J71)),"➤",""),"") | O71: =IF($J71>0%,IF(AND(O$16>=$G71,O$16<$G71+($H71*$J71)),"➤",""),"") | P71: =IF($J71>0%,IF(AND(P$16>=$G71,P$16<$G71+($H71*$J71)),"➤",""),"") | Q71: =IF($J71>0%,IF(AND(Q$16>=$G71,Q$16<$G71+($H71*$J71)),"➤",""),"") | R71: =IF($J71>0%,IF(AND(R$16>=$G71,R$16<$G71+($H71*$J71)),"➤",""),"") | S71: =IF($J71>0%,IF(AND(S$16>=$G71,S$16<$G71+($H71*$J71)),"➤",""),"") | T71: =IF($J71>0%,IF(AND(T$16>=$G71,T$16<$G71+($H71*$J71)),"➤",""),"") | ... SX71: =IF($J71>0%,IF(AND(SX$16>=$G71,SX$16<$G71+($H71*$J71)),"➤",""),"")
E72: BRUÑIDO | S72: =IF($J72>0%,IF(AND(S$16>=$G72,S$16<$G72+($H72*$J72)),"➤",""),"") | T72: =IF($J72>0%,IF(AND(T$16>=$G72,T$16<$G72+($H72*$J72)),"➤",""),"") | U72: =IF($J72>0%,IF(AND(U$16>=$G72,U$16<$G72+($H72*$J72)),"➤",""),"") | V72: =IF($J72>0%,IF(AND(V$16>=$G72,V$16<$G72+($H72*$J72)),"➤",""),"") | W72: =IF($J72>0%,IF(AND(W$16>=$G72,W$16<$G72+($H72*$J72)),"➤",""),"") | X72: =IF($J72>0%,IF(AND(X$16>=$G72,X$16<$G72+($H72*$J72)),"➤",""),"") | Y72: =IF($J72>0%,IF(AND(Y$16>=$G72,Y$16<$G72+($H72*$J72)),"➤",""),"") | Z72: =IF($J72>0%,IF(AND(Z$16>=$G72,Z$16<$G72+($H72*$J72)),"➤",""),"") | ... AE72: =IF($J72>0%,IF(AND(AE$16>=$G72,AE$16<$G72+($H72*$J72)),"➤",""),"")
C73: 293724 | E73: Bruñido | F73: Gabriel Gallegos | G73: 45565 | H73: 1 | I73: 45565 | J73: 1 | K73: Completado | M73: =IF($J73>0%,IF(AND(M$16>=$G73,M$16<$G73+($H73*$J73)),"➤",""),"") | N73: =IF($J73>0%,IF(AND(N$16>=$G73,N$16<$G73+($H73*$J73)),"➤",""),"") | O73: =IF($J73>0%,IF(AND(O$16>=$G73,O$16<$G73+($H73*$J73)),"➤",""),"") | P73: =IF($J73>0%,IF(AND(P$16>=$G73,P$16<$G73+($H73*$J73)),"➤",""),"") | Q73: =IF($J73>0%,IF(AND(Q$16>=$G73,Q$16<$G73+($H73*$J73)),"➤",""),"") | R73: =IF($J73>0%,IF(AND(R$16>=$G73,R$16<$G73+($H73*$J73)),"➤",""),"") | S73: =IF($J73>0%,IF(AND(S$16>=$G73,S$16<$G73+($H73*$J73)),"➤",""),"") -> ➤ | T73: =IF($J73>0%,IF(AND(T$16>=$G73,T$16<$G73+($H73*$J73)),"➤",""),"") | ... SX73: =IF($J73>0%,IF(AND(SX$16>=$G73,SX$16<$G73+($H73*$J73)),"➤",""),"")
C74: 284724 | E74: Bruñido | F74: Gabriel Gallegos | G74: 45565 | H74: 1 | I74: 45565 | J74: 1 | K74: Completado | M74: =IF($J74>0%,IF(AND(M$16>=$G74,M$16<$G74+($H74*$J74)),"➤",""),"") | N74: =IF($J74>0%,IF(AND(N$16>=$G74,N$16<$G74+($H74*$J74)),"➤",""),"") | O74: =IF($J74>0%,IF(AND(O$16>=$G74,O$16<$G74+($H74*$J74)),"➤",""),"") | P74: =IF($J74>0%,IF(AND(P$16>=$G74,P$16<$G74+($H74*$J74)),"➤",""),"") | Q74: =IF($J74>0%,IF(AND(Q$16>=$G74,Q$16<$G74+($H74*$J74)),"➤",""),"") | R74: =IF($J74>0%,IF(AND(R$16>=$G74,R$16<$G74+($H74*$J74)),"➤",""),"") | S74: =IF($J74>0%,IF(AND(S$16>=$G74,S$16<$G74+($H74*$J74)),"➤",""),"") -> ➤ | T74: =IF($J74>0%,IF(AND(T$16>=$G74,T$16<$G74+($H74*$J74)),"➤",""),"") | ... SX74: =IF($J74>0%,IF(AND(SX$16>=$G74,SX$16<$G74+($H74*$J74)),"➤",""),"")
C75: 287024 | E75: Bruñido | F75: Gabriel Gallegos | G75: 45566 | H75: 1 | I75: =(G75+H75)-1 -> 45566 | J75: 1 | K75: Completado | M75: =IF($J75>0%,IF(AND(M$16>=$G75,M$16<$G75+($H75*$J75)),"➤",""),"") | N75: =IF($J75>0%,IF(AND(N$16>=$G75,N$16<$G75+($H75*$J75)),"➤",""),"") | O75: =IF($J75>0%,IF(AND(O$16>=$G75,O$16<$G75+($H75*$J75)),"➤",""),"") | P75: =IF($J75>0%,IF(AND(P$16>=$G75,P$16<$G75+($H75*$J75)),"➤",""),"") | Q75: =IF($J75>0%,IF(AND(Q$16>=$G75,Q$16<$G75+($H75*$J75)),"➤",""),"") | R75: =IF($J75>0%,IF(AND(R$16>=$G75,R$16<$G75+($H75*$J75)),"➤",""),"") | S75: =IF($J75>0%,IF(AND(S$16>=$G75,S$16<$G75+($H75*$J75)),"➤",""),"") | T75: =IF($J75>0%,IF(AND(T$16>=$G75,T$16<$G75+($H75*$J75)),"➤",""),"") -> ➤ | ... SX75: =IF($J75>0%,IF(AND(SX$16>=$G75,SX$16<$G75+($H75*$J75)),"➤",""),"")
C76: 285324 | E76: Bruñido | F76: Gabriel Gallegos | G76: 45566 | H76: 1 | I76: =(G76+H76)-1 -> 45566 | J76: 1 | K76: Completado | M76: =IF($J76>0%,IF(AND(M$16>=$G76,M$16<$G76+($H76*$J76)),"➤",""),"") | N76: =IF($J76>0%,IF(AND(N$16>=$G76,N$16<$G76+($H76*$J76)),"➤",""),"") | O76: =IF($J76>0%,IF(AND(O$16>=$G76,O$16<$G76+($H76*$J76)),"➤",""),"") | P76: =IF($J76>0%,IF(AND(P$16>=$G76,P$16<$G76+($H76*$J76)),"➤",""),"") | Q76: =IF($J76>0%,IF(AND(Q$16>=$G76,Q$16<$G76+($H76*$J76)),"➤",""),"") | R76: =IF($J76>0%,IF(AND(R$16>=$G76,R$16<$G76+($H76*$J76)),"➤",""),"") | S76: =IF($J76>0%,IF(AND(S$16>=$G76,S$16<$G76+($H76*$J76)),"➤",""),"") | T76: =IF($J76>0%,IF(AND(T$16>=$G76,T$16<$G76+($H76*$J76)),"➤",""),"") -> ➤ | ... SX76: =IF($J76>0%,IF(AND(SX$16>=$G76,SX$16<$G76+($H76*$J76)),"➤",""),"")
C77: 288024 | E77: Bruñido | F77: Gabriel Gallegos | G77: 45566 | H77: 1 | I77: =(G77+H77)-1 -> 45566 | J77: 1 | K77: Completado | M77: =IF($J77>0%,IF(AND(M$16>=$G77,M$16<$G77+($H77*$J77)),"➤",""),"") | N77: =IF($J77>0%,IF(AND(N$16>=$G77,N$16<$G77+($H77*$J77)),"➤",""),"") | O77: =IF($J77>0%,IF(AND(O$16>=$G77,O$16<$G77+($H77*$J77)),"➤",""),"") | P77: =IF($J77>0%,IF(AND(P$16>=$G77,P$16<$G77+($H77*$J77)),"➤",""),"") | Q77: =IF($J77>0%,IF(AND(Q$16>=$G77,Q$16<$G77+($H77*$J77)),"➤",""),"") | R77: =IF($J77>0%,IF(AND(R$16>=$G77,R$16<$G77+($H77*$J77)),"➤",""),"") | S77: =IF($J77>0%,IF(AND(S$16>=$G77,S$16<$G77+($H77*$J77)),"➤",""),"") | T77: =IF($J77>0%,IF(AND(T$16>=$G77,T$16<$G77+($H77*$J77)),"➤",""),"") -> ➤ | ... SX77: =IF($J77>0%,IF(AND(SX$16>=$G77,SX$16<$G77+($H77*$J77)),"➤",""),"")
C78: 287524 | D78: 1 | E78: Bruñido | F78: Gabriel Gallegos | G78: 45567 | H78: 1 | I78: =(G78+H78)-1 -> 45567 | J78: 0 | K78: Sin Empezar | M78: =IF($J78>0%,IF(AND(M$16>=$G78,M$16<$G78+($H78*$J78)),"➤",""),"") | N78: =IF($J78>0%,IF(AND(N$16>=$G78,N$16<$G78+($H78*$J78)),"➤",""),"") | O78: =IF($J78>0%,IF(AND(O$16>=$G78,O$16<$G78+($H78*$J78)),"➤",""),"") | P78: =IF($J78>0%,IF(AND(P$16>=$G78,P$16<$G78+($H78*$J78)),"➤",""),"") | Q78: =IF($J78>0%,IF(AND(Q$16>=$G78,Q$16<$G78+($H78*$J78)),"➤",""),"") | R78: =IF($J78>0%,IF(AND(R$16>=$G78,R$16<$G78+($H78*$J78)),"➤",""),"") | S78: =IF($J78>0%,IF(AND(S$16>=$G78,S$16<$G78+($H78*$J78)),"➤",""),"") | T78: =IF($J78>0%,IF(AND(T$16>=$G78,T$16<$G78+($H78*$J78)),"➤",""),"") | ... SX78: =IF($J78>0%,IF(AND(SX$16>=$G78,SX$16<$G78+($H78*$J78)),"➤",""),"")
C79: 285224 | D79: 1 | E79: Bruñido | F79: Gabriel Gallegos | G79: 45567 | H79: 1 | I79: =(G79+H79)-1 -> 45567 | J79: 0 | K79: Sin Empezar | M79: =IF($J79>0%,IF(AND(M$16>=$G79,M$16<$G79+($H79*$J79)),"➤",""),"") | N79: =IF($J79>0%,IF(AND(N$16>=$G79,N$16<$G79+($H79*$J79)),"➤",""),"") | O79: =IF($J79>0%,IF(AND(O$16>=$G79,O$16<$G79+($H79*$J79)),"➤",""),"") | P79: =IF($J79>0%,IF(AND(P$16>=$G79,P$16<$G79+($H79*$J79)),"➤",""),"") | Q79: =IF($J79>0%,IF(AND(Q$16>=$G79,Q$16<$G79+($H79*$J79)),"➤",""),"") | R79: =IF($J79>0%,IF(AND(R$16>=$G79,R$16<$G79+($H79*$J79)),"➤",""),"") | S79: =IF($J79>0%,IF(AND(S$16>=$G79,S$16<$G79+($H79*$J79)),"➤",""),"") | T79: =IF($J79>0%,IF(AND(T$16>=$G79,T$16<$G79+($H79*$J79)),"➤",""),"") | ... SX79: =IF($J79>0%,IF(AND(SX$16>=$G79,SX$16<$G79+($H79*$J79)),"➤",""),"")
C80: 288524 | D80: 1 | E80: Bruñido | F80: Gabriel Gallegos | G80: 45567 | H80: 1 | I80: =(G80+H80)-1 -> 45567 | J80: 0 | K80: Sin Empezar | M80: =IF($J80>0%,IF(AND(M$16>=$G80,M$16<$G80+($H80*$J80)),"➤",""),"") | N80: =IF($J80>0%,IF(AND(N$16>=$G80,N$16<$G80+($H80*$J80)),"➤",""),"") | O80: =IF($J80>0%,IF(AND(O$16>=$G80,O$16<$G80+($H80*$J80)),"➤",""),"") | P80: =IF($J80>0%,IF(AND(P$16>=$G80,P$16<$G80+($H80*$J80)),"➤",""),"") | Q80: =IF($J80>0%,IF(AND(Q$16>=$G80,Q$16<$G80+($H80*$J80)),"➤",""),"") | R80: =IF($J80>0%,IF(AND(R$16>=$G80,R$16<$G80+($H80*$J80)),"➤",""),"") | S80: =IF($J80>0%,IF(AND(S$16>=$G80,S$16<$G80+($H80*$J80)),"➤",""),"") | T80: =IF($J80>0%,IF(AND(T$16>=$G80,T$16<$G80+($H80*$J80)),"➤",""),"") | ... SX80: =IF($J80>0%,IF(AND(SX$16>=$G80,SX$16<$G80+($H80*$J80)),"➤",""),"")
C81: 286024 | D81: 1 | E81: Bruñido | F81: Gabriel Gallegos | G81: 45567 | H81: 1 | I81: =(G81+H81)-1 -> 45567 | J81: 0 | K81: Sin Empezar | M81: =IF($J81>0%,IF(AND(M$16>=$G81,M$16<$G81+($H81*$J81)),"➤",""),"") | N81: =IF($J81>0%,IF(AND(N$16>=$G81,N$16<$G81+($H81*$J81)),"➤",""),"") | O81: =IF($J81>0%,IF(AND(O$16>=$G81,O$16<$G81+($H81*$J81)),"➤",""),"") | P81: =IF($J81>0%,IF(AND(P$16>=$G81,P$16<$G81+($H81*$J81)),"➤",""),"") | Q81: =IF($J81>0%,IF(AND(Q$16>=$G81,Q$16<$G81+($H81*$J81)),"➤",""),"") | R81: =IF($J81>0%,IF(AND(R$16>=$G81,R$16<$G81+($H81*$J81)),"➤",""),"") | S81: =IF($J81>0%,IF(AND(S$16>=$G81,S$16<$G81+($H81*$J81)),"➤",""),"") | T81: =IF($J81>0%,IF(AND(T$16>=$G81,T$16<$G81+($H81*$J81)),"➤",""),"") | ... SX81: =IF($J81>0%,IF(AND(SX$16>=$G81,SX$16<$G81+($H81*$J81)),"➤",""),"")
C82: 288724 | D82: 1 | E82: Bruñido | F82: Gabriel Gallegos | G82: 45568 | H82: 1 | I82: =(G82+H82)-1 -> 45568 | J82: 0 | K82: Sin Empezar | M82: =IF($J82>0%,IF(AND(M$16>=$G82,M$16<$G82+($H82*$J82)),"➤",""),"") | N82: =IF($J82>0%,IF(AND(N$16>=$G82,N$16<$G82+($H82*$J82)),"➤",""),"") | O82: =IF($J82>0%,IF(AND(O$16>=$G82,O$16<$G82+($H82*$J82)),"➤",""),"") | P82: =IF($J82>0%,IF(AND(P$16>=$G82,P$16<$G82+($H82*$J82)),"➤",""),"") | Q82: =IF($J82>0%,IF(AND(Q$16>=$G82,Q$16<$G82+($H82*$J82)),"➤",""),"") | R82: =IF($J82>0%,IF(AND(R$16>=$G82,R$16<$G82+($H82*$J82)),"➤",""),"") | S82: =IF($J82>0%,IF(AND(S$16>=$G82,S$16<$G82+($H82*$J82)),"➤",""),"") | T82: =IF($J82>0%,IF(AND(T$16>=$G82,T$16<$G82+($H82*$J82)),"➤",""),"") | ... SX82: =IF($J82>0%,IF(AND(SX$16>=$G82,SX$16<$G82+($H82*$J82)),"➤",""),"")
C83: 288624 | D83: 1 | E83: Bruñido | F83: Gabriel Gallegos | G83: 45567 | H83: 2 | I83: =(G83+H83)-1 -> 45568 | J83: 0 | K83: Sin Empezar | M83: =IF($J83>0%,IF(AND(M$16>=$G83,M$16<$G83+($H83*$J83)),"➤",""),"") | N83: =IF($J83>0%,IF(AND(N$16>=$G83,N$16<$G83+($H83*$J83)),"➤",""),"") | O83: =IF($J83>0%,IF(AND(O$16>=$G83,O$16<$G83+($H83*$J83)),"➤",""),"") | P83: =IF($J83>0%,IF(AND(P$16>=$G83,P$16<$G83+($H83*$J83)),"➤",""),"") | Q83: =IF($J83>0%,IF(AND(Q$16>=$G83,Q$16<$G83+($H83*$J83)),"➤",""),"") | R83: =IF($J83>0%,IF(AND(R$16>=$G83,R$16<$G83+($H83*$J83)),"➤",""),"") | S83: =IF($J83>0%,IF(AND(S$16>=$G83,S$16<$G83+($H83*$J83)),"➤",""),"") | T83: =IF($J83>0%,IF(AND(T$16>=$G83,T$16<$G83+($H83*$J83)),"➤",""),"") | ... SX83: =IF($J83>0%,IF(AND(SX$16>=$G83,SX$16<$G83+($H83*$J83)),"➤",""),"")
C84: 290724 | E84: Bruñido | F84: Gabriel Gallegos | G84: 45567 | H84: 1 | I84: =(G84+H84)-1 -> 45567 | J84: 0 | K84: Sin Empezar | M84: =IF($J84>0%,IF(AND(M$16>=$G84,M$16<$G84+($H84*$J84)),"➤",""),"") | N84: =IF($J84>0%,IF(AND(N$16>=$G84,N$16<$G84+($H84*$J84)),"➤",""),"") | O84: =IF($J84>0%,IF(AND(O$16>=$G84,O$16<$G84+($H84*$J84)),"➤",""),"") | P84: =IF($J84>0%,IF(AND(P$16>=$G84,P$16<$G84+($H84*$J84)),"➤",""),"") | Q84: =IF($J84>0%,IF(AND(Q$16>=$G84,Q$16<$G84+($H84*$J84)),"➤",""),"") | R84: =IF($J84>0%,IF(AND(R$16>=$G84,R$16<$G84+($H84*$J84)),"➤",""),"") | S84: =IF($J84>0%,IF(AND(S$16>=$G84,S$16<$G84+($H84*$J84)),"➤",""),"") | T84: =IF($J84>0%,IF(AND(T$16>=$G84,T$16<$G84+($H84*$J84)),"➤",""),"") | ... SX84: =IF($J84>0%,IF(AND(SX$16>=$G84,SX$16<$G84+($H84*$J84)),"➤",""),"")
C85: 273924 | E85: Bruñido | F85: Gabriel Gallegos | G85: 45568 | H85: 1 | I85: =(G85+H85)-1 -> 45568 | J85: 0 | K85: Sin Empezar | M85: =IF($J85>0%,IF(AND(M$16>=$G85,M$16<$G85+($H85*$J85)),"➤",""),"") | N85: =IF($J85>0%,IF(AND(N$16>=$G85,N$16<$G85+($H85*$J85)),"➤",""),"") | O85: =IF($J85>0%,IF(AND(O$16>=$G85,O$16<$G85+($H85*$J85)),"➤",""),"") | P85: =IF($J85>0%,IF(AND(P$16>=$G85,P$16<$G85+($H85*$J85)),"➤",""),"") | Q85: =IF($J85>0%,IF(AND(Q$16>=$G85,Q$16<$G85+($H85*$J85)),"➤",""),"") | R85: =IF($J85>0%,IF(AND(R$16>=$G85,R$16<$G85+($H85*$J85)),"➤",""),"") | S85: =IF($J85>0%,IF(AND(S$16>=$G85,S$16<$G85+($H85*$J85)),"➤",""),"") | T85: =IF($J85>0%,IF(AND(T$16>=$G85,T$16<$G85+($H85*$J85)),"➤",""),"") | ... SX85: =IF($J85>0%,IF(AND(SX$16>=$G85,SX$16<$G85+($H85*$J85)),"➤",""),"")
C86: 290824 | E86: Bruñido | F86: Gabriel Gallegos | G86: 45568 | H86: 1 | I86: =(G86+H86)-1 -> 45568 | J86: 0 | K86: Sin Empezar | M86: =IF($J86>0%,IF(AND(M$16>=$G86,M$16<$G86+($H86*$J86)),"➤",""),"") | N86: =IF($J86>0%,IF(AND(N$16>=$G86,N$16<$G86+($H86*$J86)),"➤",""),"") | O86: =IF($J86>0%,IF(AND(O$16>=$G86,O$16<$G86+($H86*$J86)),"➤",""),"") | P86: =IF($J86>0%,IF(AND(P$16>=$G86,P$16<$G86+($H86*$J86)),"➤",""),"") | Q86: =IF($J86>0%,IF(AND(Q$16>=$G86,Q$16<$G86+($H86*$J86)),"➤",""),"") | R86: =IF($J86>0%,IF(AND(R$16>=$G86,R$16<$G86+($H86*$J86)),"➤",""),"") | S86: =IF($J86>0%,IF(AND(S$16>=$G86,S$16<$G86+($H86*$J86)),"➤",""),"") | T86: =IF($J86>0%,IF(AND(T$16>=$G86,T$16<$G86+($H86*$J86)),"➤",""),"") | ... SX86: =IF($J86>0%,IF(AND(SX$16>=$G86,SX$16<$G86+($H86*$J86)),"➤",""),"")
C87: 291024 | E87: Bruñido | F87: Gabriel Gallegos | G87: 45569 | H87: 1 | I87: =(G87+H87)-1 -> 45569 | J87: 0 | K87: Sin Empezar | M87: =IF($J87>0%,IF(AND(M$16>=$G87,M$16<$G87+($H87*$J87)),"➤",""),"") | N87: =IF($J87>0%,IF(AND(N$16>=$G87,N$16<$G87+($H87*$J87)),"➤",""),"") | O87: =IF($J87>0%,IF(AND(O$16>=$G87,O$16<$G87+($H87*$J87)),"➤",""),"") | P87: =IF($J87>0%,IF(AND(P$16>=$G87,P$16<$G87+($H87*$J87)),"➤",""),"") | Q87: =IF($J87>0%,IF(AND(Q$16>=$G87,Q$16<$G87+($H87*$J87)),"➤",""),"") | R87: =IF($J87>0%,IF(AND(R$16>=$G87,R$16<$G87+($H87*$J87)),"➤",""),"") | S87: =IF($J87>0%,IF(AND(S$16>=$G87,S$16<$G87+($H87*$J87)),"➤",""),"") | T87: =IF($J87>0%,IF(AND(T$16>=$G87,T$16<$G87+($H87*$J87)),"➤",""),"") | ... SX87: =IF($J87>0%,IF(AND(SX$16>=$G87,SX$16<$G87+($H87*$J87)),"➤",""),"")
C88: 291224 | E88: Bruñido | F88: Gabriel Gallegos | G88: 45569 | H88: 1 | I88: =(G88+H88)-1 -> 45569 | J88: 0 | K88: Sin Empezar | M88: =IF($J88>0%,IF(AND(M$16>=$G88,M$16<$G88+($H88*$J88)),"➤",""),"") | N88: =IF($J88>0%,IF(AND(N$16>=$G88,N$16<$G88+($H88*$J88)),"➤",""),"") | O88: =IF($J88>0%,IF(AND(O$16>=$G88,O$16<$G88+($H88*$J88)),"➤",""),"") | P88: =IF($J88>0%,IF(AND(P$16>=$G88,P$16<$G88+($H88*$J88)),"➤",""),"") | Q88: =IF($J88>0%,IF(AND(Q$16>=$G88,Q$16<$G88+($H88*$J88)),"➤",""),"") | R88: =IF($J88>0%,IF(AND(R$16>=$G88,R$16<$G88+($H88*$J88)),"➤",""),"") | S88: =IF($J88>0%,IF(AND(S$16>=$G88,S$16<$G88+($H88*$J88)),"➤",""),"") | T88: =IF($J88>0%,IF(AND(T$16>=$G88,T$16<$G88+($H88*$J88)),"➤",""),"") | ... SX88: =IF($J88>0%,IF(AND(SX$16>=$G88,SX$16<$G88+($H88*$J88)),"➤",""),"")
H89: 6 | I89: =(G89+H89)-1 -> 5 | J89: 0 | M89: =IF($J89>0%,IF(AND(M$16>=$G89,M$16<$G89+($H89*$J89)),"➤",""),"") | N89: =IF($J89>0%,IF(AND(N$16>=$G89,N$16<$G89+($H89*$J89)),"➤",""),"") | O89: =IF($J89>0%,IF(AND(O$16>=$G89,O$16<$G89+($H89*$J89)),"➤",""),"") | P89: =IF($J89>0%,IF(AND(P$16>=$G89,P$16<$G89+($H89*$J89)),"➤",""),"") | Q89: =IF($J89>0%,IF(AND(Q$16>=$G89,Q$16<$G89+($H89*$J89)),"➤",""),"") | R89: =IF($J89>0%,IF(AND(R$16>=$G89,R$16<$G89+($H89*$J89)),"➤",""),"") | S89: =IF($J89>0%,IF(AND(S$16>=$G89,S$16<$G89+($H89*$J89)),"➤",""),"") | T89: =IF($J89>0%,IF(AND(T$16>=$G89,T$16<$G89+($H89*$J89)),"➤",""),"") | ... SX89: =IF($J89>0%,IF(AND(SX$16>=$G89,SX$16<$G89+($H89*$J89)),"➤",""),"")
E90: EVALUACION | S90: =IF($J90>0%,IF(AND(S$16>=$G90,S$16<$G90+($H90*$J90)),"➤",""),"") | T90: =IF($J90>0%,IF(AND(T$16>=$G90,T$16<$G90+($H90*$J90)),"➤",""),"") | U90: =IF($J90>0%,IF(AND(U$16>=$G90,U$16<$G90+($H90*$J90)),"➤",""),"") | V90: =IF($J90>0%,IF(AND(V$16>=$G90,V$16<$G90+($H90*$J90)),"➤",""),"") | W90: =IF($J90>0%,IF(AND(W$16>=$G90,W$16<$G90+($H90*$J90)),"➤",""),"") | X90: =IF($J90>0%,IF(AND(X$16>=$G90,X$16<$G90+($H90*$J90)),"➤",""),"") | Y90: =IF($J90>0%,IF(AND(Y$16>=$G90,Y$16<$G90+($H90*$J90)),"➤",""),"") | Z90: =IF($J90>0%,IF(AND(Z$16>=$G90,Z$16<$G90+($H90*$J90)),"➤",""),"") | ... AE90: =IF($J90>0%,IF(AND(AE$16>=$G90,AE$16<$G90+($H90*$J90)),"➤",""),"")
C91: 284524 | E91: Armado | G91: 45565 | H91: 1 | I91: =(G91+H91)-1 -> 45565 | J91: 0 | K91: Sin Empezar | M91: =IF($J91>0%,IF(AND(M$16>=$G91,M$16<$G91+($H91*$J91)),"➤",""),"") | N91: =IF($J91>0%,IF(AND(N$16>=$G91,N$16<$G91+($H91*$J91)),"➤",""),"") | O91: =IF($J91>0%,IF(AND(O$16>=$G91,O$16<$G91+($H91*$J91)),"➤",""),"") | P91: =IF($J91>0%,IF(AND(P$16>=$G91,P$16<$G91+($H91*$J91)),"➤",""),"") | Q91: =IF($J91>0%,IF(AND(Q$16>=$G91,Q$16<$G91+($H91*$J91)),"➤",""),"") | R91: =IF($J91>0%,IF(AND(R$16>=$G91,R$16<$G91+($H91*$J91)),"➤",""),"") | S91: =IF($J91>0%,IF(AND(S$16>=$G91,S$16<$G91+($H91*$J91)),"➤",""),"") | T91: =IF($J91>0%,IF(AND(T$16>=$G91,T$16<$G91+($H91*$J91)),"➤",""),"") | ... SX91: =IF($J91>0%,IF(AND(SX$16>=$G91,SX$16<$G91+($H91*$J91)),"➤",""),"")
C92: 284724 | E92: Armado | G92: 45566 | H92: 1 | I92: =(G92+H92)-1 -> 45566 | J92: 0 | K92: Sin Empezar | M92: =IF($J92>0%,IF(AND(M$16>=$G92,M$16<$G92+($H92*$J92)),"➤",""),"") | N92: =IF($J92>0%,IF(AND(N$16>=$G92,N$16<$G92+($H92*$J92)),"➤",""),"") | O92: =IF($J92>0%,IF(AND(O$16>=$G92,O$16<$G92+($H92*$J92)),"➤",""),"") | P92: =IF($J92>0%,IF(AND(P$16>=$G92,P$16<$G92+($H92*$J92)),"➤",""),"") | Q92: =IF($J92>0%,IF(AND(Q$16>=$G92,Q$16<$G92+($H92*$J92)),"➤",""),"") | R92: =IF($J92>0%,IF(AND(R$16>=$G92,R$16<$G92+($H92*$J92)),"➤",""),"") | S92: =IF($J92>0%,IF(AND(S$16>=$G92,S$16<$G92+($H92*$J92)),"➤",""),"") | T92: =IF($J92>0%,IF(AND(T$16>=$G92,T$16<$G92+($H92*$J92)),"➤",""),"") | ... SX92: =IF($J92>0%,IF(AND(SX$16>=$G92,SX$16<$G92+($H92*$J92)),"➤",""),"")
C93: 283724 | E93: Armado | G93: 45568 | H93: 1 | I93: =(G93+H93)-1 -> 45568 | J93: 0 | K93: Sin Empezar | S93: =IF($J93>0%,IF(AND(S$16>=$G93,S$16<$G93+($H93*$J93)),"➤",""),"") | T93: =IF($J93>0%,IF(AND(T$16>=$G93,T$16<$G93+($H93*$J93)),"➤",""),"") | U93: =IF($J93>0%,IF(AND(U$16>=$G93,U$16<$G93+($H93*$J93)),"➤",""),"") | V93: =IF($J93>0%,IF(AND(V$16>=$G93,V$16<$G93+($H93*$J93)),"➤",""),"") | W93: =IF($J93>0%,IF(AND(W$16>=$G93,W$16<$G93+($H93*$J93)),"➤",""),"") | X93: =IF($J93>0%,IF(AND(X$16>=$G93,X$16<$G93+($H93*$J93)),"➤",""),"") | Y93: =IF($J93>0%,IF(AND(Y$16>=$G93,Y$16<$G93+($H93*$J93)),"➤",""),"") | Z93: =IF($J93>0%,IF(AND(Z$16>=$G93,Z$16<$G93+($H93*$J93)),"➤",""),"") | ... AE93: =IF($J93>0%,IF(AND(AE$16>=$G93,AE$16<$G93+($H93*$J93)),"➤",""),"")
C94: 285724 | E94: Armado | G94: 45569 | H94: 1 | I94: =(G94+H94)-1 -> 45569 | J94: 0 | K94: Sin Empezar | S94: =IF($J94>0%,IF(AND(S$16>=$G94,S$16<$G94+($H94*$J94)),"➤",""),"") | T94: =IF($J94>0%,IF(AND(T$16>=$G94,T$16<$G94+($H94*$J94)),"➤",""),"") | U94: =IF($J94>0%,IF(AND(U$16>=$G94,U$16<$G94+($H94*$J94)),"➤",""),"") | V94: =IF($J94>0%,IF(AND(V$16>=$G94,V$16<$G94+($H94*$J94)),"➤",""),"") | W94: =IF($J94>0%,IF(AND(W$16>=$G94,W$16<$G94+($H94*$J94)),"➤",""),"") | X94: =IF($J94>0%,IF(AND(X$16>=$G94,X$16<$G94+($H94*$J94)),"➤",""),"") | Y94: =IF($J94>0%,IF(AND(Y$16>=$G94,Y$16<$G94+($H94*$J94)),"➤",""),"") | Z94: =IF($J94>0%,IF(AND(Z$16>=$G94,Z$16<$G94+($H94*$J94)),"➤",""),"") | ... AE94: =IF($J94>0%,IF(AND(AE$16>=$G94,AE$16<$G94+($H94*$J94)),"➤",""),"")
C95: 289524 | E95: EVALUACION | H95: 1 | I95: =(G95+H95)-1 -> 0 | J95: 0 | K95: En Proceso | M95: =IF($J95>0%,IF(AND(M$16>=$G95,M$16<$G95+($H95*$J95)),"➤",""),"") | N95: =IF($J95>0%,IF(AND(N$16>=$G95,N$16<$G95+($H95*$J95)),"➤",""),"") | O95: =IF($J95>0%,IF(AND(O$16>=$G95,O$16<$G95+($H95*$J95)),"➤",""),"") | P95: =IF($J95>0%,IF(AND(P$16>=$G95,P$16<$G95+($H95*$J95)),"➤",""),"") | Q95: =IF($J95>0%,IF(AND(Q$16>=$G95,Q$16<$G95+($H95*$J95)),"➤",""),"") | R95: =IF($J95>0%,IF(AND(R$16>=$G95,R$16<$G95+($H95*$J95)),"➤",""),"") | S95: =IF($J95>0%,IF(AND(S$16>=$G95,S$16<$G95+($H95*$J95)),"➤",""),"") | T95: =IF($J95>0%,IF(AND(T$16>=$G95,T$16<$G95+($H95*$J95)),"➤",""),"") | ... SX95: =IF($J95>0%,IF(AND(SX$16>=$G95,SX$16<$G95+($H95*$J95)),"➤",""),"")
C96: 289624 | E96: EVALUACION | H96: 1 | I96: =(G96+H96)-1 -> 0 | J96: 0 | K96: En Proceso | M96: =IF($J96>0%,IF(AND(M$16>=$G96,M$16<$G96+($H96*$J96)),"➤",""),"") | N96: =IF($J96>0%,IF(AND(N$16>=$G96,N$16<$G96+($H96*$J96)),"➤",""),"") | O96: =IF($J96>0%,IF(AND(O$16>=$G96,O$16<$G96+($H96*$J96)),"➤",""),"") | P96: =IF($J96>0%,IF(AND(P$16>=$G96,P$16<$G96+($H96*$J96)),"➤",""),"") | Q96: =IF($J96>0%,IF(AND(Q$16>=$G96,Q$16<$G96+($H96*$J96)),"➤",""),"") | R96: =IF($J96>0%,IF(AND(R$16>=$G96,R$16<$G96+($H96*$J96)),"➤",""),"") | S96: =IF($J96>0%,IF(AND(S$16>=$G96,S$16<$G96+($H96*$J96)),"➤",""),"") | T96: =IF($J96>0%,IF(AND(T$16>=$G96,T$16<$G96+($H96*$J96)),"➤",""),"") | ... SX96: =IF($J96>0%,IF(AND(SX$16>=$G96,SX$16<$G96+($H96*$J96)),"➤",""),"")
C97: 289724 | E97: EVALUACION | H97: 1 | I97: =(G97+H97)-1 -> 0 | J97: 0 | K97: En Proceso | M97: =IF($J97>0%,IF(AND(M$16>=$G97,M$16<$G97+($H97*$J97)),"➤",""),"") | N97: =IF($J97>0%,IF(AND(N$16>=$G97,N$16<$G97+($H97*$J97)),"➤",""),"") | O97: =IF($J97>0%,IF(AND(O$16>=$G97,O$16<$G97+($H97*$J97)),"➤",""),"") | P97: =IF($J97>0%,IF(AND(P$16>=$G97,P$16<$G97+($H97*$J97)),"➤",""),"") | Q97: =IF($J97>0%,IF(AND(Q$16>=$G97,Q$16<$G97+($H97*$J97)),"➤",""),"") | R97: =IF($J97>0%,IF(AND(R$16>=$G97,R$16<$G97+($H97*$J97)),"➤",""),"") | S97: =IF($J97>0%,IF(AND(S$16>=$G97,S$16<$G97+($H97*$J97)),"➤",""),"") | T97: =IF($J97>0%,IF(AND(T$16>=$G97,T$16<$G97+($H97*$J97)),"➤",""),"") | ... SX97: =IF($J97>0%,IF(AND(SX$16>=$G97,SX$16<$G97+($H97*$J97)),"➤",""),"")
C98: 290324 | E98: EVALUACION | H98: 1 | I98: =(G98+H98)-1 -> 0 | J98: 0 | K98: En Proceso | M98: =IF($J98>0%,IF(AND(M$16>=$G98,M$16<$G98+($H98*$J98)),"➤",""),"") | N98: =IF($J98>0%,IF(AND(N$16>=$G98,N$16<$G98+($H98*$J98)),"➤",""),"") | O98: =IF($J98>0%,IF(AND(O$16>=$G98,O$16<$G98+($H98*$J98)),"➤",""),"") | P98: =IF($J98>0%,IF(AND(P$16>=$G98,P$16<$G98+($H98*$J98)),"➤",""),"") | Q98: =IF($J98>0%,IF(AND(Q$16>=$G98,Q$16<$G98+($H98*$J98)),"➤",""),"") | R98: =IF($J98>0%,IF(AND(R$16>=$G98,R$16<$G98+($H98*$J98)),"➤",""),"") | S98: =IF($J98>0%,IF(AND(S$16>=$G98,S$16<$G98+($H98*$J98)),"➤",""),"") | T98: =IF($J98>0%,IF(AND(T$16>=$G98,T$16<$G98+($H98*$J98)),"➤",""),"") | ... SX98: =IF($J98>0%,IF(AND(SX$16>=$G98,SX$16<$G98+($H98*$J98)),"➤",""),"")
C99: 290424 | E99: EVALUACION | H99: 1 | I99: =(G99+H99)-1 -> 0 | J99: 0 | K99: En Proceso | M99: =IF($J99>0%,IF(AND(M$16>=$G99,M$16<$G99+($H99*$J99)),"➤",""),"") | N99: =IF($J99>0%,IF(AND(N$16>=$G99,N$16<$G99+($H99*$J99)),"➤",""),"") | O99: =IF($J99>0%,IF(AND(O$16>=$G99,O$16<$G99+($H99*$J99)),"➤",""),"") | P99: =IF($J99>0%,IF(AND(P$16>=$G99,P$16<$G99+($H99*$J99)),"➤",""),"") | Q99: =IF($J99>0%,IF(AND(Q$16>=$G99,Q$16<$G99+($H99*$J99)),"➤",""),"") | R99: =IF($J99>0%,IF(AND(R$16>=$G99,R$16<$G99+($H99*$J99)),"➤",""),"") | S99: =IF($J99>0%,IF(AND(S$16>=$G99,S$16<$G99+($H99*$J99)),"➤",""),"") | T99: =IF($J99>0%,IF(AND(T$16>=$G99,T$16<$G99+($H99*$J99)),"➤",""),"") | ... SX99: =IF($J99>0%,IF(AND(SX$16>=$G99,SX$16<$G99+($H99*$J99)),"➤",""),"")
C100: 290524 | E100: EVALUACION | H100: 1 | I100: =(G100+H100)-1 -> 0 | J100: 0 | K100: En Proceso | M100: =IF($J100>0%,IF(AND(M$16>=$G100,M$16<$G100+($H100*$J100)),"➤",""),"") | N100: =IF($J100>0%,IF(AND(N$16>=$G100,N$16<$G100+($H100*$J100)),"➤",""),"") | O100: =IF($J100>0%,IF(AND(O$16>=$G100,O$16<$G100+($H100*$J100)),"➤",""),"") | P100: =IF($J100>0%,IF(AND(P$16>=$G100,P$16<$G100+($H100*$J100)),"➤",""),"") | Q100: =IF($J100>0%,IF(AND(Q$16>=$G100,Q$16<$G100+($H100*$J100)),"➤",""),"") | R100: =IF($J100>0%,IF(AND(R$16>=$G100,R$16<$G100+($H100*$J100)),"➤",""),"") | S100: =IF($J100>0%,IF(AND(S$16>=$G100,S$16<$G100+($H100*$J100)),"➤",""),"") | T100: =IF($J100>0%,IF(AND(T$16>=$G100,T$16<$G100+($H100*$J100)),"➤",""),"") | ... SX100: =IF($J100>0%,IF(AND(SX$16>=$G100,SX$16<$G100+($H100*$J100)),"➤",""),"")
C101: 290624 | E101: EVALUACION | H101: 1 | I101: =(G101+H101)-1 -> 0 | J101: 0 | K101: En Proceso | M101: =IF($J101>0%,IF(AND(M$16>=$G101,M$16<$G101+($H101*$J101)),"➤",""),"") | N101: =IF($J101>0%,IF(AND(N$16>=$G101,N$16<$G101+($H101*$J101)),"➤",""),"") | O101: =IF($J101>0%,IF(AND(O$16>=$G101,O$16<$G101+($H101*$J101)),"➤",""),"") | P101: =IF($J101>0%,IF(AND(P$16>=$G101,P$16<$G101+($H101*$J101)),"➤",""),"") | Q101: =IF($J101>0%,IF(AND(Q$16>=$G101,Q$16<$G101+($H101*$J101)),"➤",""),"") | R101: =IF($J101>0%,IF(AND(R$16>=$G101,R$16<$G101+($H101*$J101)),"➤",""),"") | S101: =IF($J101>0%,IF(AND(S$16>=$G101,S$16<$G101+($H101*$J101)),"➤",""),"") | T101: =IF($J101>0%,IF(AND(T$16>=$G101,T$16<$G101+($H101*$J101)),"➤",""),"") | ... SX101: =IF($J101>0%,IF(AND(SX$16>=$G101,SX$16<$G101+($H101*$J101)),"➤",""),"")
C102: 290924 | E102: EVALUACION | H102: 1 | I102: =(G102+H102)-1 -> 0 | J102: 0 | K102: En Proceso | M102: =IF($J102>0%,IF(AND(M$16>=$G102,M$16<$G102+($H102*$J102)),"➤",""),"") | N102: =IF($J102>0%,IF(AND(N$16>=$G102,N$16<$G102+($H102*$J102)),"➤",""),"") | O102: =IF($J102>0%,IF(AND(O$16>=$G102,O$16<$G102+($H102*$J102)),"➤",""),"") | P102: =IF($J102>0%,IF(AND(P$16>=$G102,P$16<$G102+($H102*$J102)),"➤",""),"") | Q102: =IF($J102>0%,IF(AND(Q$16>=$G102,Q$16<$G102+($H102*$J102)),"➤",""),"") | R102: =IF($J102>0%,IF(AND(R$16>=$G102,R$16<$G102+($H102*$J102)),"➤",""),"") | S102: =IF($J102>0%,IF(AND(S$16>=$G102,S$16<$G102+($H102*$J102)),"➤",""),"") | T102: =IF($J102>0%,IF(AND(T$16>=$G102,T$16<$G102+($H102*$J102)),"➤",""),"") | ... SX102: =IF($J102>0%,IF(AND(SX$16>=$G102,SX$16<$G102+($H102*$J102)),"➤",""),"")
C103: 291124 | E103: EVALUACION | H103: 1 | I103: =G103+H103 -> 1 | J103: 0 | K103: En Proceso | M103: =IF($J103>0%,IF(AND(M$16>=$G103,M$16<$G103+($H103*$J103)),"➤",""),"") | N103: =IF($J103>0%,IF(AND(N$16>=$G103,N$16<$G103+($H103*$J103)),"➤",""),"") | O103: =IF($J103>0%,IF(AND(O$16>=$G103,O$16<$G103+($H103*$J103)),"➤",""),"") | P103: =IF($J103>0%,IF(AND(P$16>=$G103,P$16<$G103+($H103*$J103)),"➤",""),"") | Q103: =IF($J103>0%,IF(AND(Q$16>=$G103,Q$16<$G103+($H103*$J103)),"➤",""),"") | R103: =IF($J103>0%,IF(AND(R$16>=$G103,R$16<$G103+($H103*$J103)),"➤",""),"") | S103: =IF($J103>0%,IF(AND(S$16>=$G103,S$16<$G103+($H103*$J103)),"➤",""),"") | T103: =IF($J103>0%,IF(AND(T$16>=$G103,T$16<$G103+($H103*$J103)),"➤",""),"") | ... SX103: =IF($J103>0%,IF(AND(SX$16>=$G103,SX$16<$G103+($H103*$J103)),"➤",""),"")
C104: 291324 | E104: EVALUACION | H104: 1 | I104: =(G104+H104)-1 -> 0 | J104: 0 | K104: En Proceso | M104: =IF($J104>0%,IF(AND(M$16>=$G104,M$16<$G104+($H104*$J104)),"➤",""),"") | N104: =IF($J104>0%,IF(AND(N$16>=$G104,N$16<$G104+($H104*$J104)),"➤",""),"") | O104: =IF($J104>0%,IF(AND(O$16>=$G104,O$16<$G104+($H104*$J104)),"➤",""),"") | P104: =IF($J104>0%,IF(AND(P$16>=$G104,P$16<$G104+($H104*$J104)),"➤",""),"") | Q104: =IF($J104>0%,IF(AND(Q$16>=$G104,Q$16<$G104+($H104*$J104)),"➤",""),"") | R104: =IF($J104>0%,IF(AND(R$16>=$G104,R$16<$G104+($H104*$J104)),"➤",""),"") | S104: =IF($J104>0%,IF(AND(S$16>=$G104,S$16<$G104+($H104*$J104)),"➤",""),"") | T104: =IF($J104>0%,IF(AND(T$16>=$G104,T$16<$G104+($H104*$J104)),"➤",""),"") | ... SX104: =IF($J104>0%,IF(AND(SX$16>=$G104,SX$16<$G104+($H104*$J104)),"➤",""),"")
C105: 291724 | E105: EVALUACION | H105: 1 | I105: =(G105+H105)-1 -> 0 | J105: 0 | K105: En Proceso | M105: =IF($J105>0%,IF(AND(M$16>=$G105,M$16<$G105+($H105*$J105)),"➤",""),"") | N105: =IF($J105>0%,IF(AND(N$16>=$G105,N$16<$G105+($H105*$J105)),"➤",""),"") | O105: =IF($J105>0%,IF(AND(O$16>=$G105,O$16<$G105+($H105*$J105)),"➤",""),"") | P105: =IF($J105>0%,IF(AND(P$16>=$G105,P$16<$G105+($H105*$J105)),"➤",""),"") | Q105: =IF($J105>0%,IF(AND(Q$16>=$G105,Q$16<$G105+($H105*$J105)),"➤",""),"") | R105: =IF($J105>0%,IF(AND(R$16>=$G105,R$16<$G105+($H105*$J105)),"➤",""),"") | S105: =IF($J105>0%,IF(AND(S$16>=$G105,S$16<$G105+($H105*$J105)),"➤",""),"") | T105: =IF($J105>0%,IF(AND(T$16>=$G105,T$16<$G105+($H105*$J105)),"➤",""),"") | ... SX105: =IF($J105>0%,IF(AND(SX$16>=$G105,SX$16<$G105+($H105*$J105)),"➤",""),"")
C106: 291824 | E106: EVALUACION | H106: 1 | I106: =(G106+H106)-1 -> 0 | J106: 0 | K106: En Proceso | M106: =IF($J106>0%,IF(AND(M$16>=$G106,M$16<$G106+($H106*$J106)),"➤",""),"") | N106: =IF($J106>0%,IF(AND(N$16>=$G106,N$16<$G106+($H106*$J106)),"➤",""),"") | O106: =IF($J106>0%,IF(AND(O$16>=$G106,O$16<$G106+($H106*$J106)),"➤",""),"") | P106: =IF($J106>0%,IF(AND(P$16>=$G106,P$16<$G106+($H106*$J106)),"➤",""),"") | Q106: =IF($J106>0%,IF(AND(Q$16>=$G106,Q$16<$G106+($H106*$J106)),"➤",""),"") | R106: =IF($J106>0%,IF(AND(R$16>=$G106,R$16<$G106+($H106*$J106)),"➤",""),"") | S106: =IF($J106>0%,IF(AND(S$16>=$G106,S$16<$G106+($H106*$J106)),"➤",""),"") | T106: =IF($J106>0%,IF(AND(T$16>=$G106,T$16<$G106+($H106*$J106)),"➤",""),"") | ... SX106: =IF($J106>0%,IF(AND(SX$16>=$G106,SX$16<$G106+($H106*$J106)),"➤",""),"")
C107: 292024 | E107: EVALUACION | H107: 1 | I107: =(G107+H107)-1 -> 0 | J107: 0 | K107: En Proceso | M107: =IF($J107>0%,IF(AND(M$16>=$G107,M$16<$G107+($H107*$J107)),"➤",""),"") | N107: =IF($J107>0%,IF(AND(N$16>=$G107,N$16<$G107+($H107*$J107)),"➤",""),"") | O107: =IF($J107>0%,IF(AND(O$16>=$G107,O$16<$G107+($H107*$J107)),"➤",""),"") | P107: =IF($J107>0%,IF(AND(P$16>=$G107,P$16<$G107+($H107*$J107)),"➤",""),"") | Q107: =IF($J107>0%,IF(AND(Q$16>=$G107,Q$16<$G107+($H107*$J107)),"➤",""),"") | R107: =IF($J107>0%,IF(AND(R$16>=$G107,R$16<$G107+($H107*$J107)),"➤",""),"") | S107: =IF($J107>0%,IF(AND(S$16>=$G107,S$16<$G107+($H107*$J107)),"➤",""),"") | T107: =IF($J107>0%,IF(AND(T$16>=$G107,T$16<$G107+($H107*$J107)),"➤",""),"") | ... SX107: =IF($J107>0%,IF(AND(SX$16>=$G107,SX$16<$G107+($H107*$J107)),"➤",""),"")
C108: 292124 | E108: EVALUACION | H108: 1 | I108: =(G108+H108)-1 -> 0 | J108: 0 | K108: En Proceso | M108: =IF($J108>0%,IF(AND(M$16>=$G108,M$16<$G108+($H108*$J108)),"➤",""),"") | N108: =IF($J108>0%,IF(AND(N$16>=$G108,N$16<$G108+($H108*$J108)),"➤",""),"") | O108: =IF($J108>0%,IF(AND(O$16>=$G108,O$16<$G108+($H108*$J108)),"➤",""),"") | P108: =IF($J108>0%,IF(AND(P$16>=$G108,P$16<$G108+($H108*$J108)),"➤",""),"") | Q108: =IF($J108>0%,IF(AND(Q$16>=$G108,Q$16<$G108+($H108*$J108)),"➤",""),"") | R108: =IF($J108>0%,IF(AND(R$16>=$G108,R$16<$G108+($H108*$J108)),"➤",""),"") | S108: =IF($J108>0%,IF(AND(S$16>=$G108,S$16<$G108+($H108*$J108)),"➤",""),"") | T108: =IF($J108>0%,IF(AND(T$16>=$G108,T$16<$G108+($H108*$J108)),"➤",""),"") | ... SX108: =IF($J108>0%,IF(AND(SX$16>=$G108,SX$16<$G108+($H108*$J108)),"➤",""),"")
C109: 292324 | E109: EVALUACION | H109: 1 | I109: =(G109+H109)-1 -> 0 | J109: 0 | K109: En Proceso | M109: =IF($J109>0%,IF(AND(M$16>=$G109,M$16<$G109+($H109*$J109)),"➤",""),"") | N109: =IF($J109>0%,IF(AND(N$16>=$G109,N$16<$G109+($H109*$J109)),"➤",""),"") | O109: =IF($J109>0%,IF(AND(O$16>=$G109,O$16<$G109+($H109*$J109)),"➤",""),"") | P109: =IF($J109>0%,IF(AND(P$16>=$G109,P$16<$G109+($H109*$J109)),"➤",""),"") | Q109: =IF($J109>0%,IF(AND(Q$16>=$G109,Q$16<$G109+($H109*$J109)),"➤",""),"") | R109: =IF($J109>0%,IF(AND(R$16>=$G109,R$16<$G109+($H109*$J109)),"➤",""),"") | S109: =IF($J109>0%,IF(AND(S$16>=$G109,S$16<$G109+($H109*$J109)),"➤",""),"") | T109: =IF($J109>0%,IF(AND(T$16>=$G109,T$16<$G109+($H109*$J109)),"➤",""),"") | ... SX109: =IF($J109>0%,IF(AND(SX$16>=$G109,SX$16<$G109+($H109*$J109)),"➤",""),"")
C110: 292424 | E110: EVALUACION | H110: 1 | I110: =(G110+H110)-1 -> 0 | J110: 0 | K110: En Proceso | M110: =IF($J110>0%,IF(AND(M$16>=$G110,M$16<$G110+($H110*$J110)),"➤",""),"") | N110: =IF($J110>0%,IF(AND(N$16>=$G110,N$16<$G110+($H110*$J110)),"➤",""),"") | O110: =IF($J110>0%,IF(AND(O$16>=$G110,O$16<$G110+($H110*$J110)),"➤",""),"") | P110: =IF($J110>0%,IF(AND(P$16>=$G110,P$16<$G110+($H110*$J110)),"➤",""),"") | Q110: =IF($J110>0%,IF(AND(Q$16>=$G110,Q$16<$G110+($H110*$J110)),"➤",""),"") | R110: =IF($J110>0%,IF(AND(R$16>=$G110,R$16<$G110+($H110*$J110)),"➤",""),"") | S110: =IF($J110>0%,IF(AND(S$16>=$G110,S$16<$G110+($H110*$J110)),"➤",""),"") | T110: =IF($J110>0%,IF(AND(T$16>=$G110,T$16<$G110+($H110*$J110)),"➤",""),"") | ... SX110: =IF($J110>0%,IF(AND(SX$16>=$G110,SX$16<$G110+($H110*$J110)),"➤",""),"")
C111: 292724 | E111: EVALUACION | H111: 1 | I111: =(G111+H111)-1 -> 0 | J111: 0 | K111: En Proceso | M111: =IF($J111>0%,IF(AND(M$16>=$G111,M$16<$G111+($H111*$J111)),"➤",""),"") | N111: =IF($J111>0%,IF(AND(N$16>=$G111,N$16<$G111+($H111*$J111)),"➤",""),"") | O111: =IF($J111>0%,IF(AND(O$16>=$G111,O$16<$G111+($H111*$J111)),"➤",""),"") | P111: =IF($J111>0%,IF(AND(P$16>=$G111,P$16<$G111+($H111*$J111)),"➤",""),"") | Q111: =IF($J111>0%,IF(AND(Q$16>=$G111,Q$16<$G111+($H111*$J111)),"➤",""),"") | R111: =IF($J111>0%,IF(AND(R$16>=$G111,R$16<$G111+($H111*$J111)),"➤",""),"") | S111: =IF($J111>0%,IF(AND(S$16>=$G111,S$16<$G111+($H111*$J111)),"➤",""),"") | T111: =IF($J111>0%,IF(AND(T$16>=$G111,T$16<$G111+($H111*$J111)),"➤",""),"") | ... SX111: =IF($J111>0%,IF(AND(SX$16>=$G111,SX$16<$G111+($H111*$J111)),"➤",""),"")

Sheet Programa (2)
M509: Nombre de tarea
M1245: % trabajo completado
M1246: 0.96
M1247: 0.65
M1248: 0
M1249: % trabajo completado
M1250: 0.38
M1251: 0
M1252: 0
M1253: 0
M1254: 0
M1255: 0
M1256: % trabajo completado
M1257: 0.41
M1258: 0.3
M1259: 0
M1260: 0
M1261: % trabajo completado
M1262: 0.18
M1263: 0
M1264: 0
M1265: 0
M1266: % trabajo completado
M1267: 0.21
M1268: 0.8
M1269: 0
M1270: 0
M1271: % trabajo completado
M1272: 0.34
M1273: 0
M1274: 0
M1275: 0
M1276: % trabajo completado
M1277: 0
M1278: 0
M1279: 0
M1280: 0
M1282: 0
M1283: 0
M1284: 0
M1285: 0
M1286: 0
M1290: % trabajo completado
M1291: 0.97
M1292: 0.32
M1293: 0
M1294: % trabajo completado
M1295: 0.39
M1296: 0.25
M1297: 0
M1298: 0
M1299: % trabajo completado
M1300: 0.42
M1301: 0.55
M1302: % trabajo completado
M1303: 0.19
M1304: 0
M1305: 0
M1306: % trabajo completado
M1307: 0.21
M1308: 0
M1309: 0
M1310: % trabajo completado
M1311: 0.35
M1312: 0
M1313: 0
M1314: 0
M1315: 0
M1316: % trabajo completado
M1317: 0
M1318: 0.65
M1319: 0
M1320: 0
M1321: % trabajo completado
M1322: 0
M1323: 0
M1324: 0
M1325: 0
M1326: 0
M1333: % trabajo completado
M1334: 0.96
M1335: 0.7
M1336: 0
M1337: 0
M1338: % trabajo completado
M1339: 0.39
M1340: 0
M1341: 0
M1342: 0
M1343: 0
M1344: % trabajo completado
M1345: 0.42
M1346: 0
M1347: 0
M1348: 0
M1349: % trabajo completado
M1350: 0.19
M1351: 0
M1352: 0
M1353: 0
...

Sheet Horas extra
B2: REPORTE DE TRABAJOS OT 286624 (EMERGENCIA) | J2: CUADRO COMPARATIVO DE PRECIOS - CÁNCAMO DE VÁSTAGO CIL. INCLINACIÓN DE BULLDOZER CAT D11T
B3: # | C3: NOMBRES | D3: AREA | E3: TRABAJOS | F3: FECHA Y HORA SALIDA | G3: TOTAL HORAS EXTRA | J3: FABRICACION TALLER HPK | P3: FUNDICION - FUNDTEC
B4: 1 | C4: LUIS HUERTA | D4: Evaluación | E4: Supervisión / Armado | F4: 45573.042 | G4: =(F4-#REF!)*24 -> #REF! | K4: DESC. | L4: # | M4: UNIDAD | N4: MONTO | O4: TOTAL | P4: DESC. | Q4: # | R4: MONTO | S4: TOTAL
B5: 2 | C5: ROLANDO LLAIQUE | D5: Maquinado | E5: Maquinado de diámetro de salida de cilindro | F5: 45573.042 | G5: =(F5-#REF!)*24 -> #REF! | J5: ACERO H1045 | K5: 13" X 16" X 4-1/2" | L5: 1 | N5: 680 | O5: =N5*L5 -> 680 | P5: FUNDICION EN ACERO H1045 | Q5: 50 | R5: 24 | S5: =R5*Q5 -> 1200
B6: 3 | C6: JUSTO AROCUTIPA | D6: Soldadura | E6: Corte / Soldadura de dado de anclaje | F6: 45572.819 | G6: =(F6-#REF!)*24 -> #REF! | J6: HORA MAQUINA | K6: - | L6: 21 | N6: 40 | O6: =N6*L6 -> 840 | P6: FAB. DE MOLDE (SOLO 1 VEZ) | Q6: 1 | R6: 1000 | S6: =R6*Q6 -> 1000
B7: 4 | C7: GABRIEL GALLEGOS | D7: Pintura | E7: Pintura y embalado de cilindro | F7: 45573.399 | G7: =(F7-#REF!)*24 -> #REF! | J7: HORA HOMBRE | K7: - | L7: 21 | N7: 13.020833 | O7: 62.15 | P7: TRANSPORTE | Q7: 50 | R7: 0.7 | S7: =R7*Q7 -> 35
J8: TOTAL DOLARES | O8: =SUM(O5:O7) -> 1582.15 | P8: HORA MAQUINA | Q8: 4.5 | R8: 150.86 | S8: =R8*Q8 -> 678.87 | T8: 40 USD HORA
P9: HORA HOMBRE | Q9: 4.5 | R9: 13.020833 | S9: =R9*Q9 -> 58.59375
P10: TOTAL SOLES | S10: =SUM(S5:S9) -> 2972.4637
P11: TOTAL DOLARES | S11: 788.14
B15: # | C15: NOMBRES | D15: AREA | E15: TRABAJOS | F15: FECHA Y HORA SALIDA | G15: MONTO
B16: 1 | C16: GABRIEL ANCO | D16: Maquinado | F16: 45577.625 | G16: 25
B17: 2 | C17: ROLANDO LLAIQUE | D17: Maquinado | F17: 45577.625 | G17: 25
B18: 3 | C18: LUIS RAMOS | D18: Maquinado | F18: 45577.542 | G18: 10
B19: 4 | C19: JOSE HUAMANI | D19: Maquinado | F19: 45577.542 | G19: 10
B20: 5 | C20: JUSTO AROCUTIPA | D20: Soldadura | F20: 45577.625 | G20: 25
B21: 6 | C21: GABRIEL GALLEGOS | D21: Bruñido | F21: 45577.542 | G21: 10
B22: 7 | C22: LUIS CHOQUE | D22: Evaluación | F22: 45577.542 | G22: 10
B23: 8 | C23: JIMMY CUBA | D23: Evaluación | F23: 45577.521 | G23: 10
B24: 9 | C24: KEVIN | D24: Pintura | F24: 45577.583 | G24: 10
B27: REPORTE DE TRABAJOS OT 292024 (EMERGENCIA) - 22/10
B28: # | C28: NOMBRES | D28: AREA | E28: TRABAJOS | F28: FECHA Y HORA SALIDA | G28: TOTAL HORAS EXTRA
B29: 1 | C29: JUSTO AROCUTIPA | D29: Soldadura | E29: Supervisión / Armado | F29: 45573.042 | G29: =(F29-#REF!)*24 -> #REF!
B30: 2 | C30: ROLANDO LLAIQUE | D30: Maquinado | E30: Maquinado de diámetro de salida de cilindro | F30: 45573.042 | G30: =(F30-#REF!)*24 -> #REF!
A32: 45587 | B32: OT 292024 (EMERGENCIA) - 22/10
B33: # | C33: NOMBRES | D33: AREA | E33: TRABAJOS | F33: FECHA Y HORA SALIDA | G33: MONTO
B34: 1 | C34: JUSTO AROCUTIPA | D34: Soldadura | F34: 45587.802 | G34: 10
B35: 2 | C35: JOSE HUAMANI | D35: Fresa | F35: 45587.833 | G35: 10
B36: 3 | C36: ROLANDO LLAYQUE | D36: Maquinado | F36: 45587.833 | G36: 10 | J36: OT | K36: DESC | L36: CANT. | N36: COSTO | O36: COSTO TOTAL
G37: =SUM(G34:G36) -> 30 | J37: 289624 | K37: Dados de anclaje | L37: 4 | N37: 25 | O37: =N37*L37 -> 100
J38: 291524 | K38: Dados de anclaje | L38: 4 | N38: 25 | O38: =N38*L38 -> 100
A39: 45588 | B39: 45588 | J39: 292824 | K39: Dados de anclaje | L39: 4 | N39: 25 | O39: =N39*L39 -> 100
B40: # | C40: NOMBRES | D40: AREA | E40: TRABAJOS | F40: FECHA Y HORA SALIDA | G40: MONTO | J40: 295024 | K40: Dados de anclaje | L40: 4 | N40: 25 | O40: =N40*L40 -> 100
B41: 1 | C41: JUSTO AROCUTIPA | D41: Soldadura | F41: 45588.875 | G41: 25 | O41: =SUM(O37:O40) -> 400
B42: 2 | C42: VICTOR CACERES | D42: Soldadura | F42: 45588.875 | G42: 25
B43: 3 | C43: LUIS HUERTA | D43: EVALUACION | F43: 45588.875 | G43: 25
G44: =SUM(G41:G43) -> 75
A46: 45589 | B46: 45589
B47: # | C47: NOMBRES | D47: AREA | E47: TRABAJOS | F47: FECHA Y HORA SALIDA | G47: MONTO
B48: 1 | C48: JUSTO AROCUTIPA | D48: Soldadura | F48: 45589.875 | G48: 25
B49: 2 | C49: VICTOR CACERES | D49: Soldadura | F49: 45589.875 | G49: 25
B50: 3 | C50: LUIS HUERTA | D50: Evaluacion | F50: 45589.875 | G50: 25
B51: 4 | C51: LUIS RAMOS | D51: Torno | F51: 45589.875 | G51: 25
B52: 5 | C52: ROLANDO LLAYQUE | D52: Torno | F52: 45589.875 | G52: 25
B53: 6 | C53: GABRIEL ANCO | D53: Torno | F53: 45589.875 | G53: 25
B54: 7 | C54: JOSE HUAMANI | D54: Fresa | F54: 45589.875 | G54: 25
G55: =SUM(G48:G54) -> 175
A57: 45590 | B57: 45590
B58: # | C58: NOMBRES | D58: AREA | E58: TRABAJOS | F58: FECHA Y HORA SALIDA | G58: MONTO
B59: 1 | C59: JUSTO AROCUTIPA | D59: Soldadura | F59: 45590.875 | G59: 25
B60: 2 | C60: VICTOR CACERES | D60: Soldadura | F60: 45590.875 | G60: 25
B61: 3 | C61: LUIS HUERTA | D61: Evaluacion | F61: 45590.875 | G61: 25
B62: 4 | C62: LUIS RAMOS | D62: Torno | F62: 45590.833 | G62: 10
G63: =SUM(G59:G62) -> 85
A66: 45591 | B66: 45591
B67: # | C67: NOMBRES | D67: AREA | E67: TRABAJOS | F67: FECHA Y HORA SALIDA | G67: MONTO
B68: 1 | C68: JUSTO AROCUTIPA | D68: Soldadura | F68: 45591.6 | G68: 25
B69: 3 | C69: LUIS HUERTA | D69: Evaluacion | F69: 45591.625 | G69: 25
B70: 4 | C70: LUIS RAMOS | D70: Torno | F70: 45591.542 | G70: 10
B71: 5 | C71: ROLANDO LLAYQUE | D71: Torno | F71: 45591.625 | G71: 25
B72: 6 | C72: GABRIEL ANCO | D72: Torno | F72: 45591.625 | G72: 25
B73: 7 | C73: JOSE HUAMANI | D73: Fresa | F73: 45591.542 | G73: 10
B74: 8 | C74: JIMMY CUBA | D74: Evaluacion | F74: 45591.562 | G74: 10
B75: 9 | C75: LUIS CHOQUE | D75: Evaluacion | F75: 45591.5 | G75: 10
G76: =SUM(G68:G75) -> 140
B79: RESUMEN DE PAGOS - 21/10 - 26/10
B80: # | C80: NOMBRES | D80: AREA | E80: TRABAJOS | F80: # DIAS | G80: MONTO
B81: 1 | C81: GABRIEL ANCO | D81: Maquinado | F81: =COUNTIF($C$32:$C$75,C81) -> 2 | G81: =SUMIF($C$32:$C$75,C81,$G$32:$G$75) -> 50
B82: 2 | C82: ROLANDO LLAYQUE | D82: Maquinado | F82: =COUNTIF($C$32:$C$75,C82) -> 3 | G82: =SUMIF($C$32:$C$75,C82,$G$32:$G$75) -> 60
B83: 3 | C83: LUIS RAMOS | D83: Maquinado | F83: =COUNTIF($C$32:$C$75,C83) -> 3 | G83: =SUMIF($C$32:$C$75,C83,$G$32:$G$75) -> 45
B84: 4 | C84: JOSE HUAMANI | D84: Maquinado | F84: =COUNTIF($C$32:$C$75,C84) -> 3 | G84: =SUMIF($C$32:$C$75,C84,$G$32:$G$75) -> 45
B85: 5 | C85: JUSTO AROCUTIPA | D85: Soldadura | F85: =COUNTIF($C$32:$C$75,C85) -> 5 | G85: =SUMIF($C$32:$C$75,C85,$G$32:$G$75) -> 110
B86: 7 | C86: LUIS CHOQUE | D86: Evaluación | F86: =COUNTIF($C$32:$C$75,C86) -> 1 | G86: =SUMIF($C$32:$C$75,C86,$G$32:$G$75) -> 10
B87: 8 | C87: JIMMY CUBA | D87: Evaluación | F87: =COUNTIF($C$32:$C$75,C87) -> 1 | G87: =SUMIF($C$32:$C$75,C87,$G$32:$G$75) -> 10
B88: 9 | C88: LUIS HUERTA | D88: Evaluación | F88: =COUNTIF($C$32:$C$75,C88) -> 4 | G88: =SUMIF($C$32:$C$75,C88,$G$32:$G$75) -> 100
B89: 10 | C89: VICTOR CACERES | D89: Soldadura | F89: =COUNTIF($C$32:$C$75,C89) -> 3 | G89: =SUMIF($C$32:$C$75,C89,$G$32:$G$75) -> 75
G90: =SUM(G81:G89) -> 505
A93: 45593 | B93: 45593
B94: # | C94: NOMBRES | D94: AREA | E94: TRABAJOS | F94: FECHA Y HORA SALIDA | G94: MONTO
B95: 1 | C95: VICTOR CACERES | D95: Soldadura | F95: 45593.833 | G95: 10
B96: 2 | C96: ROLANDO LLAYQUE | D96: Torno | F96: 45593.875 | G96: 25
B97: 3 | C97: GABRIEL ANCO | D97: Torno | F97: 45593.833 | G97: 10
G98: =SUM(G95:G97) -> 45
A100: 45594 | B100: 45594
B101: # | C101: NOMBRES | D101: AREA | E101: TRABAJOS | F101: FECHA Y HORA SALIDA | G101: MONTO
B102: 1 | C102: JUSTO AROCUTIPA | D102: Soldadura | F102: 45594.875 | G102: 25
B103: 2 | C103: VICTOR CACERES | D103: Soldadura | F103: 45594.875 | G103: 25
B104: 3 | C104: ROLANDO LLAYQUE | D104: Torno | F104: 45593.875 | G104: 25
B105: 4 | C105: GABRIEL ANCO | D105: Torno | F105: 45594.875 | G105: 25
B106: 5 | C106: LUIS RAMOS | D106: Torno | F106: 45594.833 | G106: 10
B107: 6 | C107: LUIS HUERTA | D107: Evaluacion | F107: 45594.875 | G107: 25
G108: =SUM(G102:G107) -> 135
A110: 45595 | B110: 45595
B111: # | C111: NOMBRES | D111: AREA | E111: TRABAJOS | F111: FECHA Y HORA SALIDA | G111: MONTO
B112: 1 | C112: JUSTO AROCUTIPA | D112: Soldadura | F112: 45595.875 | G112: 25
B113: 2 | C113: ROLANDO LLAYQUE | D113: Torno | F113: 45595.875 | G113: 25
B114: 3 | C114: GABRIEL ANCO | D114: Torno | F114: 45595.875 | G114: 25
B115: 4 | C115: LUIS RAMOS | D115: Torno | F115: 45595.833 | G115: 10
B116: 5 | C116: LUIS HUERTA | D116: Evaluacion | F116: 45595.875 | G116: 25
G117: =SUM(G112:G116) -> 110
...

Sheet Resumen horas extra
B3: N° | C3: NOMBRE | D3: ENERO | E3: FEBRERO | F3: MARZO | G3: TRIMESTRE 1 | H3: ABRIL | I3: MAYO | J3: JUNIO | K3: TRIMESTRE 2 | L3: JULIO
B5: 1 | C5: GABRIEL ANCO | D5: =_xlfn.XLOOKUP($C5,$C$30:$C$48,$D$30:$D$48)*24 -> 12.333333 | E5: - | F5: =_xlfn.XLOOKUP($C5,$J$30:$J$48,$L$30:$L$48)*24 -> 26.5 | G5: =SUM(D5:F5) -> 38.833333 | H5: =_xlfn.XLOOKUP($C5,$N$30:$N$48,$O$30:$O$48)*24 -> 12.5 | I5: =_xlfn.XLOOKUP($C5,$Q$30:$Q$48,$R$30:$R$48)*24 -> 41 | J5: =_xlfn.XLOOKUP($C5,$T$30:$T$48,$U$30:$U$48)*24 -> 21 | K5: =SUM(H5:J5) -> 74.5 | L5: =_xlfn.XLOOKUP(C5,$W$30:$W$48,$X$30:$X$48)*24 -> 28.5
B6: 2 | C6: ALONZO OTAZU | D6: - | E6: =_xlfn.XLOOKUP($C6,$F$29:$F$47,$H$29:$H$47)*24 -> 5 | F6: =_xlfn.XLOOKUP($C6,$J$30:$J$48,$L$30:$L$48)*24 -> 11.666667 | G6: =SUM(D6:F6) -> 16.666667 | H6: =_xlfn.XLOOKUP($C6,$N$30:$N$48,$O$30:$O$48)*24 -> 17.083333 | I6: =_xlfn.XLOOKUP($C6,$Q$30:$Q$48,$R$30:$R$48)*24 -> 17 | J6: =_xlfn.XLOOKUP($C6,$T$30:$T$48,$U$30:$U$48)*24 -> 17.666667 | K6: =SUM(H6:J6) -> 51.75 | L6: =_xlfn.XLOOKUP(C6,$W$30:$W$48,$X$30:$X$48)*24 -> 9.5
B7: 3 | C7: LUIS RAMOS | D7: =_xlfn.XLOOKUP($C7,$C$30:$C$48,$D$30:$D$48)*24 -> 14 | E7: - | F7: =_xlfn.XLOOKUP($C7,$J$30:$J$48,$L$30:$L$48)*24 -> 12.5 | G7: =SUM(D7:F7) -> 26.5 | H7: - | I7: =_xlfn.XLOOKUP($C7,$Q$30:$Q$48,$R$30:$R$48)*24 -> 21 | J7: =_xlfn.XLOOKUP($C7,$T$30:$T$48,$U$30:$U$48)*24 -> 13 | K7: =SUM(H7:J7) -> 34 | L7: =_xlfn.XLOOKUP(C7,$W$30:$W$48,$X$30:$X$48)*24 -> 15.5
B8: 4 | C8: JOSE HUAMANI | D8: =_xlfn.XLOOKUP($C8,$C$30:$C$48,$D$30:$D$48)*24 -> 13.833333 | E8: =_xlfn.XLOOKUP($C8,$F$29:$F$47,$H$29:$H$47)*24 -> 7.1666667 | F8: =_xlfn.XLOOKUP($C8,$J$30:$J$48,$L$30:$L$48)*24 -> 15 | G8: =SUM(D8:F8) -> 36 | H8: =_xlfn.XLOOKUP($C8,$N$30:$N$48,$O$30:$O$48)*24 -> 19.333333 | I8: =_xlfn.XLOOKUP($C8,$Q$30:$Q$48,$R$30:$R$48)*24 -> 16 | J8: =_xlfn.XLOOKUP($C8,$T$30:$T$48,$U$30:$U$48)*24 -> 9 | K8: =SUM(H8:J8) -> 44.333333 | L8: =_xlfn.XLOOKUP(C8,$W$30:$W$48,$X$30:$X$48)*24 -> 19.5
B9: 5 | C9: ROLANDO LLAYQUE | D9: - | E9: - | F9: - | G9: =SUM(D9:F9) -> 0 | H9: - | I9: - | J9: =_xlfn.XLOOKUP($C9,$T$30:$T$48,$U$30:$U$48)*24 -> 24 | K9: =SUM(H9:J9) -> 24 | L9: =_xlfn.XLOOKUP(C9,$W$30:$W$48,$X$30:$X$48)*24 -> 19.5
B10: 6 | C10: JUSTO AROCUTIPA | D10: =_xlfn.XLOOKUP($C10,$C$30:$C$48,$D$30:$D$48)*24 -> 10 | E10: =_xlfn.XLOOKUP($C10,$F$29:$F$47,$H$29:$H$47)*24 -> 8.3333333 | F10: =_xlfn.XLOOKUP($C10,$J$30:$J$48,$L$30:$L$48)*24 -> 19 | G10: =SUM(D10:F10) -> 37.333333 | H10: =_xlfn.XLOOKUP($C10,$N$30:$N$48,$O$30:$O$48)*24 -> 33.666667 | I10: =_xlfn.XLOOKUP($C10,$Q$30:$Q$48,$R$30:$R$48)*24 -> 36.5 | J10: =_xlfn.XLOOKUP($C10,$T$30:$T$48,$U$30:$U$48)*24 -> 35 | K10: =SUM(H10:J10) -> 105.16667 | L10: =_xlfn.XLOOKUP(C10,$W$30:$W$48,$X$30:$X$48)*24 -> 16.5
B11: 7 | C11: JEANCARLO IBARRA | D11: - | E11: - | F11: - | G11: =SUM(D11:F11) -> 0 | H11: =_xlfn.XLOOKUP($C11,$N$30:$N$48,$O$30:$O$48)*24 -> 27 | I11: =_xlfn.XLOOKUP($C11,$Q$30:$Q$48,$R$30:$R$48)*24 -> 47 | J11: =_xlfn.XLOOKUP($C11,$T$30:$T$48,$U$30:$U$48)*24 -> 27 | K11: =SUM(H11:J11) -> 101 | L11: =_xlfn.XLOOKUP(C11,$W$30:$W$48,$X$30:$X$48)*24 -> 19.5
B12: 8 | C12: LUIS HUERTA | D12: =_xlfn.XLOOKUP($C12,$C$30:$C$48,$D$30:$D$48)*24 -> 26.166667 | E12: - | F12: - | G12: =SUM(D12:F12) -> 26.166667 | H12: =_xlfn.XLOOKUP($C12,$N$30:$N$48,$O$30:$O$48)*24 -> 27.166667 | I12: =_xlfn.XLOOKUP($C12,$Q$30:$Q$48,$R$30:$R$48)*24 -> 39.5 | J12: =_xlfn.XLOOKUP($C12,$T$30:$T$48,$U$30:$U$48)*24 -> 16 | K12: =SUM(H12:J12) -> 82.666667 | L12: =_xlfn.XLOOKUP(C12,$W$30:$W$48,$X$30:$X$48)*24 -> 9.5
B13: 9 | C13: LUIS CHOQUE | D13: =_xlfn.XLOOKUP($C13,$C$30:$C$48,$D$30:$D$48)*24 -> 12.666667 | E13: - | F13: =_xlfn.XLOOKUP($C13,$J$30:$J$48,$L$30:$L$48)*24 -> 12 | G13: =SUM(D13:F13) -> 24.666667 | H13: =_xlfn.XLOOKUP($C13,$N$30:$N$48,$O$30:$O$48)*24 -> 17.25 | I13: =_xlfn.XLOOKUP($C13,$Q$30:$Q$48,$R$30:$R$48)*24 -> 28 | J13: =_xlfn.XLOOKUP($C13,$T$30:$T$48,$U$30:$U$48)*24 -> 3 | K13: =SUM(H13:J13) -> 48.25 | L13: =_xlfn.XLOOKUP(C13,$W$30:$W$48,$X$30:$X$48)*24 -> 9.5
B14: 10 | C14: ENRIQUE YANA | D14: - | E14: - | F14: - | G14: =SUM(D14:F14) -> 0 | H14: =_xlfn.XLOOKUP($C14,$N$30:$N$48,$O$30:$O$48)*24 -> 16.083333 | I14: =_xlfn.XLOOKUP($C14,$Q$30:$Q$48,$R$30:$R$48)*24 -> 31.5 | J14: =_xlfn.XLOOKUP($C14,$T$30:$T$48,$U$30:$U$48)*24 -> 17 | K14: =SUM(H14:J14) -> 64.583333 | L14: =_xlfn.XLOOKUP(C14,$W$30:$W$48,$X$30:$X$48)*24 -> 9.5
B15: 11 | C15: GABRIEL GALLEGOS | D15: =_xlfn.XLOOKUP($C15,$C$30:$C$48,$D$30:$D$48)*24 -> 13.75 | E15: - | F15: =_xlfn.XLOOKUP($C15,$J$30:$J$48,$L$30:$L$48)*24 -> 15 | G15: =SUM(D15:F15) -> 28.75 | H15: =_xlfn.XLOOKUP($C15,$N$30:$N$48,$O$30:$O$48)*24 -> 13.333333 | I15: =_xlfn.XLOOKUP($C15,$Q$30:$Q$48,$R$30:$R$48)*24 -> 28 | J15: =_xlfn.XLOOKUP($C15,$T$30:$T$48,$U$30:$U$48)*24 -> 16 | K15: =SUM(H15:J15) -> 57.333333 | L15: -
B16: 12 | C16: ERICK CARDENAS | D16: =_xlfn.XLOOKUP($C16,$C$30:$C$48,$D$30:$D$48)*24 -> 10 | E16: =_xlfn.XLOOKUP($C16,$F$29:$F$47,$H$29:$H$47)*24 -> 5 | F16: =_xlfn.XLOOKUP($C16,$J$30:$J$48,$L$30:$L$48)*24 -> 1.5 | G16: =SUM(D16:F16) -> 16.5 | H16: =_xlfn.XLOOKUP($C16,$N$30:$N$48,$O$30:$O$48)*24 -> 14 | I16: =_xlfn.XLOOKUP($C16,$Q$30:$Q$48,$R$30:$R$48)*24 -> 39.5 | J16: =_xlfn.XLOOKUP($C16,$T$30:$T$48,$U$30:$U$48)*24 -> 19.5 | K16: =SUM(H16:J16) -> 73 | L16: =_xlfn.XLOOKUP(C16,$W$30:$W$48,$X$30:$X$48)*24 -> 9.5
B17: 13 | C17: KEVIN MORAN | D17: - | E17: =_xlfn.XLOOKUP($C17,$F$29:$F$47,$H$29:$H$47)*24 -> 5 | F17: - | G17: =SUM(D17:F17) -> 5 | H17: - | I17: =_xlfn.XLOOKUP($C17,$Q$30:$Q$48,$R$30:$R$48)*24 -> 13 | J17: =_xlfn.XLOOKUP($C17,$T$30:$T$48,$U$30:$U$48)*24 -> 16 | K17: =SUM(H17:J17) -> 29 | L17: =_xlfn.XLOOKUP(C17,$W$30:$W$48,$X$30:$X$48)*24 -> 9.5
B18: 14 | C18: SIDANE HUARANCCA | D18: =_xlfn.XLOOKUP($C18,$C$30:$C$48,$D$30:$D$48)*24 -> 11.166667 | E18: =_xlfn.XLOOKUP($C18,$F$29:$F$47,$H$29:$H$47)*24 -> 3.75 | F18: =_xlfn.XLOOKUP($C18,$J$30:$J$48,$L$30:$L$48)*24 -> 12 | G18: =SUM(D18:F18) -> 26.916667 | H18: =_xlfn.XLOOKUP($C18,$N$30:$N$48,$O$30:$O$48)*24 -> 23.5 | I18: - | J18: =_xlfn.XLOOKUP($C18,$T$30:$T$48,$U$30:$U$48)*24 -> 11.5 | K18: =SUM(H18:J18) -> 35 | L18: =_xlfn.XLOOKUP(C18,$W$30:$W$48,$X$30:$X$48)*24 -> 9.5
B19: 15 | C19: PIERO PACSI | D19: =_xlfn.XLOOKUP($C19,$C$30:$C$48,$D$30:$D$48)*24 -> 7 | E19: =_xlfn.XLOOKUP($C19,$F$29:$F$47,$H$29:$H$47)*24 -> 6.6666667 | F19: - | G19: =SUM(D19:F19) -> 13.666667 | H19: - | I19: - | J19: - | K19: =SUM(H19:J19) -> 0 | L19: -
B20: 16 | C20: FERNANDO BARRIENTOS | D20: =_xlfn.XLOOKUP($C20,$C$30:$C$48,$D$30:$D$48)*24 -> 24.916667 | E20: =_xlfn.XLOOKUP($C20,$F$29:$F$47,$H$29:$H$47)*24 -> 24.083333 | F20: =_xlfn.XLOOKUP($C20,$J$30:$J$48,$L$30:$L$48)*24 -> 29.333333 | G20: =SUM(D20:F20) -> 78.333333 | H20: =_xlfn.XLOOKUP($C20,$N$30:$N$48,$O$30:$O$48)*24 -> 7 | I20: =_xlfn.XLOOKUP($C20,$Q$30:$Q$48,$R$30:$R$48)*24 -> 6 | J20: - | K20: =SUM(H20:J20) -> 13 | L20: -
B21: 17 | C21: JIMMY CUBA | D21: =_xlfn.XLOOKUP($C21,$C$30:$C$48,$D$30:$D$48)*24 -> 7.3333333 | E21: - | F21: =_xlfn.XLOOKUP($C21,$J$30:$J$48,$L$30:$L$48)*24 -> 11.5 | G21: =SUM(D21:F21) -> 18.833333 | H21: - | I21: - | J21: - | K21: =SUM(H21:J21) -> 0 | L21: -
C22: TOTAL | D22: =SUM(D10:D21) -> 123 | E22: =SUM(E10:E21) -> 52.833333 | F22: =SUM(F10:F21) -> 100.33333 | G22: =SUM(G10:G21) -> 276.16667 | H22: =SUM(H10:H21) -> 179 | I22: =SUM(I10:I21) -> 269 | J22: =SUM(J10:J21) -> 161 | K22: =SUM(K10:K21) -> 609 | L22: =SUM(L10:L21) -> 93
C27: ENERO | F27: FEBRERO | J27: MARZO | N27: ABRIL | Q27: MAYO | T27: JUNIO | W27: JULIO
C28: CUADRO RESUMEN | F28: CUADRO RESUMEN | J28: CUADRO RESUMEN | N28: CUADRO RESUMEN | Q28: CUADRO RESUMEN | T28: CUADRO RESUMEN | W28: CUADRO RESUMEN
C29: COLABORADOR | D29: TOTAL HORAS | F29: COLABORADOR | H29: TOTAL HORAS | J29: COLABORADOR | L29: TOTAL HORAS | N29: COLABORADOR | O29: TOTAL HORAS | Q29: COLABORADOR | R29: TOTAL HORAS | T29: COLABORADOR | U29: TOTAL HORAS | W29: COLABORADOR | X29: TOTAL HORAS
C30: ALFREDO MURILLO | D30: 0.48958333 | F30: ALFREDO MURILLO | H30: 0.55555556 | J30: ALONZO OTAZU | L30: 0.48611111 | N30: ALFREDO MURILLO | O30: 0.34375 | Q30: ALONZO OTAZU | R30: 0.70833333 | T30: ALONZO OTAZU | U30: 0.73611111 | W30: ALONZO OTAZU | X30: 0.39583333
C31: ANTONIO ZUMAETA | D31: 0.39583333 | F31: ALONZO OTAZU | H31: 0.20833333 | J31: GABRIEL GALLEGOS | L31: 0.625 | N31: ALONZO OTAZU | O31: 0.71180556 | Q31: DIEGO JAIME | R31: 0.33333333 | T31: ENRIQUE YANA | U31: 0.70833333 | W31: DIEGO JAIME | X31: 0.39583333
C32: DIEGO JAIME | D32: 0.48958333 | F32: DIEGO JAIME | H32: 0.86805556 | J32: ERICK CARDENAS | L32: 0.0625 | N32: DIEGO JAIME | O32: 0.041666667 | Q32: GABRIEL GALLEGOS | R32: 1.1666667 | T32: ERICK CARDENAS | U32: 0.8125 | W32: DIEGO MUÑOZ | X32: 0.22916667
C33: GABRIEL GALLEGOS | D33: 0.57291667 | F33: ELIZABETH UMAYASI | H33: 0.38541667 | J33: FERNANDO BARRIENTOS | L33: 29:20:00 | N33: GABRIEL GALLEGOS | O33: 13:20:00 | Q33: ENRIQUE YANA | R33: 1.3125 | T33: GABRIEL ANCO | U33: 0.875 | W33: ENRIQUE YANA | X33: 0.39583333
C34: ERICK CARDENAS | D34: 0.41666667 | F34: ERICK CARDENAS | H34: 0.20833333 | J34: GABRIEL ANCO | L34: 26:30:00 | N34: ENRIQUE YANA | O34: 16:05:00 | Q34: ERICK CARDENAS | R34: 1.6458333 | T34: GABRIEL GALLEGOS | U34: 0.66666667 | W34: ERICK CARDENAS | X34: 0.39583333
C35: FERNANDO BARRIENTOS | D35: 24:55:00 | F35: FERNANDO BARRIENTOS | H35: 24:05:00 | J35: JIMMY CUBA | L35: 0.47916667 | N35: ERICK CARDENAS | O35: 0.58333333 | Q35: FERNANDO BARRIENTOS | R35: 0.25 | T35: JEANCARLO IBARRA | U35: 27:00:00 | W35: GABRIEL ANCO | X35: 28:30:00
C36: GABRIEL ANCO | D36: 0.51388889 | F36: JOSE HUAMANI | H36: 0.29861111 | J36: JOSE HUAMANI | L36: 0.625 | N36: FERNANDO BARRIENTOS | O36: 0.29166667 | Q36: GABRIEL ANCO | R36: 1.7083333 | T36: JOSE HUAMANI | U36: 0.375 | W36: GABRIEL GALLEGOS | X36: 0.39583333
C37: JIMMY CUBA | D37: 0.30555556 | F37: JUSTO AROCUTIPA | H37: 0.34722222 | J37: JUAN VERA | L37: 0.82638889 | N37: GABRIEL ANCO | O37: 0.52083333 | Q37: JEANCARLO IBARRA | R37: 1.9583333 | T37: JUAN VERA | U37: 28:00:00 | W37: JEANCARLO IBARRA | X37: 19:30:00
C38: JOSE HUAMANI | D38: 0.57638889 | F38: JUVENAL MORALES | H38: 0.54166667 | J38: JUSTO AROCUTIPA | L38: 0.79166667 | N38: JEANCARLO IBARRA | O38: 27:00:00 | Q38: JOSE HUAMANI | R38: 0.66666667 | T38: JUSTO AROCUTIPA | U38: 35:00:00 | W38: JOSE HUAMANI | X38: 19:30:00
C39: JOSE LLAYQUE | D39: 0.66666667 | F39: KEVIN MORAN | H39: 0.20833333 | J39: JUVENAL MORALES | L39: 0.66666667 | N39: JOSE HUAMANI | O39: 0.80555556 | Q39: JOSE LLAYQUE | R39: 1.5208333 | T39: JUVENAL SERPA | U39: 0.66666667 | W39: JUAN VERA | X39: 0.72916667
C40: JUAN VERA | D40: 0.14236111 | F40: PIERO PACSI | H40: 0.27777778 | J40: LUIS CHOQUE | L40: 0.5 | N40: JOSE LLAYQUE | O40: 0.66666667 | Q40: JUAN VERA | R40: 1.0416667 | T40: KEVIN MORAN | U40: 0.66666667 | W40: JUSTO AROCUTIPA | X40: 0.6875
C41: JUSTO AROCUTIPA | D41: 0.41666667 | F41: SIDANE HUARANCCA | H41: 0.15625 | J41: LUIS RAMOS | L41: 0.52083333 | N41: JUAN VERA | O41: 31:05:00 | Q41: JUSTO AROCUTIPA | R41: 1.5208333 | T41: LUIS CHOQUE | U41: 0.125 | W41: JUVENAL SERPA | X41: 0.45833333
C42: JUVENAL MORALES | D42: 0.55555556 | F42: DANTE TRISTAN | H42: 0.16666667 | J42: MIRIAN CCANAHUIRE | L42: 0.26388889 | N42: JUSTO AROCUTIPA | O42: 33:40:00 | Q42: JUVENAL MORALES | R42: 0.33333333 | T42: LUIS HUERTA | U42: 0.66666667 | W42: KEVIN MORAN | X42: 0.39583333
C43: LUIS CHOQUE | D43: 0.52777778 | J43: SIDANE HUARANCCA | L43: 0.5 | N43: JUVENAL MORALES | O43: 0.79166667 | Q43: KEVIN MORAN | R43: 0.54166667 | T43: LUIS RAMOS | U43: 0.54166667 | W43: LUIS CHOQUE | X43: 0.39583333
C44: LUIS HUERTA | D44: 26:10:00 | N44: LUIS CHOQUE | O44: 0.71875 | Q44: LUIS CHOQUE | R44: 1.1666667 | T44: ROLANDO LLAYQUE | U44: 24:00:00 | W44: LUIS HUERTA | X44: 0.39583333
C45: LUIS RAMOS | D45: 0.58333333 | N45: LUIS HUERTA | O45: 27:10:00 | Q45: LUIS HUERTA | R45: 1.6458333 | T45: SIDANE HUARANCCA | U45: 0.47916667 | W45: LUIS RAMOS | X45: 0.64583333
C46: MIRIAN CCANAHUIRE | D46: 0.22222222 | N46: RODRIGO HUAMANI | O46: 0.16666667 | Q46: LUIS RAMOS | R46: 0.875 | W46: RODRIGO HUAMANI | X46: 0.39583333
C47: PIERO PACSI | D47: 0.29166667 | N47: SIDANE HUARANCCA | O47: 0.97916667 | Q47: SIDANE HUANRANCCA | R47: 0.95833333 | W47: ROLANDO LLAYQUE | X47: 0.8125
C48: SIDANE HUARANCCA | D48: 0.46527778 | W48: SIDANE HUARANCCA | X48: 0.39583333

Sheet Status MOD
D3: &K | E3: CLIENTE | F3: DESCRIPCION | G3: BASE METALICA | H3: EQUIPO | I3: MODELO | J3: POS | K3: Nº PARTE | L3: NRO OC | M3: FECHA EST | N3: DIAS EN TALLER | O3: STATUS FINAL | P3: TIPO DE REPARACION | Q3: ESTADO DE REPARACION (PROCESOS) | R3: COMENTARIOS
M4: ENTREGA
D5: 288724 | E5: BAMBAS | F5: CILINDRO DE BOOM | G5: SI | H5: CATERPILLAR | I5: 390DL | J5: RH | K5: 353-9648 | L5: 4400586157 | M5: 45594 | N5: 45 | O5: PROCESO | P5: NO ESTANDAR | Q5: 1 | R5: En armado
D6: 288824 | E6: BAMBAS | F6: FRENO DE SERVICIO Y PARQUEO | G6: SI | H6: CATERPILLAR | I6: 24M | J6: LH | K6: 271-9321 | L6: 4400585966 | M6: 45591 | N6: 44 | O6: LISTO PARA DESPACHO | P6: ESTANDAR | Q6: 1 | R6: ENTREGADO
D7: 288924 | E7: BAMBAS | F7: FRENO DE SERVICIO Y PARQUEO | G7: SI | H7: CATERPILLAR | I7: 24M | J7: RH | K7: 271-9321 | L7: 4400585971 | M7: 45591 | N7: 44 | O7: LISTO PARA DESPACHO | P7: ESTANDAR | Q7: 1 | R7: ENTREGADO
D8: 290624 | E8: BAMBAS | F8: CILINDRO DE BLADE TIP | G8: SI | H8: CATERPILLAR | I8: 24M | K8: 605-8794 | L8: 4400587631 | N8: 36 | O8: PROCESO | P8: NO ESTANDAR | Q8: 0.9 | R8: Falta retirar pistón de vástago roto. / Luego se procede a armar
D9: 291024 | E9: BAMBAS | F9: CILINDRO DE LEVANTE DE BULLDOZER | G9: SI | H9: CATERPILLAR | I9: 844H | J9: LH | K9: 502-5819 | L9: 4400587575 | M9: 45594 | N9: 36 | O9: ARMADO | P9: ESTANDAR | Q9: 0.95 | R9: F, Pulido de tapa. / Luego se arma
D10: 291124 | E10: BAMBAS | F10: CILINDRO DE INCLINACION DE BULLDOZER | G10: SI | H10: CATERPILLAR | I10: 844H | K10: 516-8026 | L10: 4400587576 | M10: 45591 | N10: 36 | O10: PROCESO | P10: NO ESTANDAR | Q10: 1 | R10: ENTREGADO
D11: 291224 | E11: BAMBAS | F11: CILINDRO DE ARTICULACION | G11: SI | H11: CATERPILLAR | I11: 24M | J11: LH | K11: 273-1733 | L11: 4400587580 | M11: 45595 | N11: 36 | O11: PROCESO | P11: ESTANDAR | Q11: 0.9 | R11: Flata maquinado de espiga. / Luego se arma
D12: 291324 | E12: BAMBAS | F12: CILINDRO DE LEVANTE DE BULLDOZER | G12: SI | H12: CATERPILLAR | I12: 844H | K12: 502-5819 | L12: 4400587589 | N12: 36 | O12: PROCESO | P12: NO ESTANDAR | Q12: 0.55 | R12: Falta maquinado de barra de vástago, soldadura, maquinado de soldadura. / Luego se arma
D13: 291724 | E13: BAMBAS | F13: RUEDA DELANTERA | G13: SI | H13: KOMATSU | I13: 930E-4SE | J13: LH | K13: 58F3240013 | L13: 4400588879 | M13: 45596 | N13: 33 | O13: PROCESO | P13: ESTANDAR
D14: 291824 | E14: BAMBAS | F14: CILINDRO DE SUSPENSION DELANTERA | G14: SI | H14: KOMATSU | I14: 930E-4SE | J14: LH | K14: XB3916 | L14: 4400588878 | M14: 45596 | N14: 33 | O14: PROCESO | P14: ESTANDAR
D15: 291924 | E15: BAMBAS | F15: CILINDRO DE INCLINACION | G15: SI | H15: CATERPILLAR | I15: 980G | K15: 112-5004 | L15: 4400587573 | M15: 45594 | N15: 33 | O15: PROCESO | P15: ESTANDAR | Q15: 0.95 | R15: Falta pulido de tapa y piston. / Listo para armado
D16: 292324 | E16: BAMBAS | F16: CILINDRO DE LEVANTE DE BULLDOZER | G16: SI | H16: CATERPILLAR | I16: D11T | K16: 252-0471 | L16: 4400588271 | M16: 45595 | N16: 33 | O16: PROCESO | P16: ESTANDAR | Q16: 0.65 | R16: Falta sacar cojinete de vástago y rellenar, barrenado. / Luego se arma
D17: 292424 | E17: BAMBAS | F17: CILINDRO DE SUSPENSION POSTERIOR | G17: SI | H17: KOMATSU | I17: 930E-4SE | K17: EM8844 | L17: 4400588656 | N17: 33 | O17: PROCESO | P17: NO ESTANDAR | Q17: 0.05 | R17: En proceso de rellenado de ojo de vástago, falta cromado, barrenado. / Falta rellenar ojo de cilindo, barrenar. / Luego se arma
D18: 296124 | E18: BAMBAS | F18: CILINDRO DE SUSPENSION POSTERIOR | G18: SI | H18: KOMATSU | I18: 930E-4SE | K18: EM8844 | L18: 4400592049 | M18: 45600 | N18: 16 | O18: PROCESO | P18: ESTANDAR | Q18: 0.1 | R18: Falta cromado, barrenado. / Falta rellenar ojo de cilindo, barrenar. / Luego se arma
D19: 296724 | E19: BAMBAS | F19: CILINDRO DE BUCKET | G19: NO | H19: CATERPILLAR | I19: 390FL | K19: 582-7096 | L19: 4400590529 | N19: 16 | O19: PROCESO | P19: NO ESTANDAR | Q19: 0 | R19: Hay que mandar a fabricar a un tercero el cancamo de vástago. / Es fab. Completa de vástago. / F. Rectificar tapa. / F. rellenas, barrenar, bruñir cilindro.
D20: 297324 | E20: BAMBAS | F20: CILINDRO DE BUCKET | G20: SI | H20: CATERPILLAR | I20: 390DL | K20: 5827096 | L20: 4400591719 | N20: 11 | O20: PROCESO | P20: ESTANDAR | Q20: 0.15 | R20: En proceso de cromado, falta rellenado y barrenado de cilindro. /
D21: ​
D25: HP&K | E25: CLIENTE | F25: DESCRIPCION | G25: EQUIPO | H25: MODELO | I25: POS | J25: Nº PARTE | K25: NRO OC | L25: CRITICIDAD | M25: STATUS FINAL | N25: % AVANCE
D27: 281024 | E27: ANTAPACCAY | F27: CILINDRO HIDRAULICO DE CLAM | G27: CATERPILLAR | H27: 6060FS | I27: RH | J27: 4592050 | K27: 4500514311 | L27: ALTA | M27: ARMADO | N27: 1
D28: 285724 | E28: ANTAPACCAY | F28: CILINDRO DE LEVANTE | G28: CATERPILLAR | H28: 994F | I28: RH | J28: 5695376 | K28: 4500520964 | L28: ALTA | M28: PROCESO | N28: 0.5 | O28: REPROCESO POR FALLA EN SOLDADURA
D29: 288324 | E29: ANTAPACCAY | F29: CILINDRO DE INCLINACION DE BULLDOZER | G29: CATERPILLAR | H29: D11T | I29: LH | J29: 3672259 | K29: 4500525799 | L29: ALTA | M29: ARMADO | N29: 1
D30: 289624 | E30: ANTAPACCAY | F30: CILINDRO DE INCLINACION DE BULLDOZER | G30: CATERPILLAR | H30: 844K | I30: RH | J30: 1098832 | K30: 4500530645 | L30: ALTA | M30: ARMADO | N30: 1
D31: 289724 | E31: ANTAPACCAY | F31: CILINDRO DE STICK | G31: CATERPILLAR | H31: 390DL | J31: 3631685 | K31: 4500530646 | L31: MEDIA | M31: PROCESO | N31: 0.5 | O31: REPROCESO POR CALIDAD EN TUBO
D32: 292824 | E32: ANTAPACCAY | F32: CILINDRO DE INCLINACION DE BULLDOZER | G32: CATERPILLAR | H32: 844K | I32: LH | J32: 1098833 | K32: 4500530644 | L32: ALTA | M32: ARMADO | N32: 0.9 | O32: EN PROCESO DE ARMADO, FALTA PRUEBA
D33: 292924 | E33: ANTAPACCAY | F33: CILINDRO DE STICK | G33: CATERPILLAR | H33: 390FL | J33: 3153375 | K33: 4500531305 | L33: MEDIA | M33: PROCESO | N33: 0.35
D34: 293024 | E34: ANTAPACCAY | F34: ACUMULADOR DE DIRECCION | G34: CATERPILLAR | H34: 797F | I34: P2 | J34: 2777219 | K34: 4500531281 | L34: ALTA | M34: ARMADO | N34: 1
D35: 293124 | E35: ANTAPACCAY | F35: CILINDRO DE DIRECCION | G35: CATERPILLAR | H35: 844K | I35: RH | J35: 6E1244 | K35: 4500531308 | L35: ALTA | M35: ARMADO | N35: 1
D36: 293224 | E36: ANTAPACCAY | F36: CILINDRO DE DIRECCION | G36: CATERPILLAR | H36: 797F | I36: LH | J36: 1946171 | K36: 4500531279 | L36: ALTA | M36: ARMADO | N36: 1
D40: HP&K | E40: CLIENTE | F40: DESCRIPCION | G40: EQUIPO | H40: MODELO | I40: POS | J40: Nº PARTE | K40: NRO OC | L40: CRITICIDAD | M40: STATUS FINAL | N40: % AVANCE
D42: 291324 | E42: BAMBAS | F42: CILINDRO DE LEVANTE DE BULLDOZER | G42: CATERPILLAR | H42: 844H | J42: 502-5819 | K42: 4400587589 | L42: ALTA | M42: ARMADO | N42: 1
D43: 291724 | E43: BAMBAS | F43: RUEDA DELANTERA | G43: KOMATSU | H43: 930E-4SE | I43: LH | J43: 58F3240013 | K43: 4400588879 | L43: ALTA | M43: ARMADO | N43: 1
D44: 291824 | E44: BAMBAS | F44: CILINDRO DE SUSPENSION DELANTERA | G44: KOMATSU | H44: 930E-4SE | I44: LH | J44: XB3916 | K44: 4400588878 | L44: ALTA | M44: ARMADO | N44: 1
D45: 291924 | E45: BAMBAS | F45: CILINDRO DE INCLINACION | G45: CATERPILLAR | H45: 980G | J45: 112-5004 | K45: 4400587573 | L45: MEDIA | M45: ARMADO | N45: 1
D46: 292124 | E46: BAMBAS | F46: CILINDRO DE LEVANTE DE RIPPER | G46: CATERPILLAR | H46: 24 | J46: 6058762 | K46: 4400588269 | L46: ALTA | M46: PROCESO | N46: 0.15
D47: 292324 | E47: BAMBAS | F47: CILINDRO DE LEVANTE DE BULLDOZER | G47: CATERPILLAR | H47: D11T | J47: 252-0471 | K47: 4400588271 | L47: ALTA | M47: ARMADO | N47: 1
D48: 292424 | E48: BAMBAS | F48: CILINDRO DE SUSPENSION POSTERIOR | G48: KOMATSU | H48: 930E-4SE | J48: EM8844 | K48: 4400588656 | L48: ALTA | M48: PROCESO | N48: 0.45
D49: 293724 | E49: BAMBAS | F49: CILINDRO DE DIRECCION | G49: KOMATSU | H49: 980E | J49: 58B4150120 | K49: 4400589586 | L49: ALTA | M49: ARMADO | N49: 1
